Workbook

Sheet COMO_USAR
A1: CONSTRUDATA ENGENHARIA | PLANILHA MESTRE SLNR SANTOS — COMO USAR | 20/03/2026
A3: ABA | B3: DESCRIÇÃO
A4: CRONO_MACRO | B4: Cronograma macro — controle de metros, equipes e datas por núcleo
A5: FATORES | B5: Fatores de composição de material (editável — amarelo)
A6: CUSTOS | B6: Preços unitários SINAPI/SABESP + premissas do contrato
A7: DIMENSIONAMENTO | B7: Equipes por setor (linkado ao CRONO_MACRO)
A8: PLEITO | B8: Pleito de acréscimo — análise financeira
A9: ADITIVOS | B9: Aditivos contratuais — 8 itens
A10: PRIMAVERA_P6 | B10: Exportação para MS Project / Primavera P6
A11: N07_NOROESTE | B11: Novos núcleos — Zona Noroeste (883LA + 2.113LE = 2.996 lig)
A12: N08_V_PROGRESSO | B12: Novos núcleos — Vila Progresso (585LA + 1.280LE = 1.865 lig)
A13: N09_Z_LESTE | B13: Novos núcleos — Zona Leste (480LA + 921LE = 1.401 lig)
A14: N10_CONJUNTO | B14: Novos núcleos — Conjunto (656LA + 1.016LE = 1.672 lig)
... A36: PEDIDO_URGENTE | B36: Pedido urgente 30 dias — R$4,2M (emitir AGORA)
A38: ⚙ PREMISSAS — editar estas células antes de usar
A39: PREMISSA | B39: VALOR ATUAL / INSTRUÇÃO
A40: M/Lig (metros por ligação) | B40: 2 — CRONO_MACRO F3 — mantido em 2 (vala compartilhada água+esgoto)
A41: R$/m (custo médio contrato) | B41: 910 — CRONO_MACRO H3 — atualizar se BDI mudar
A42: Produtividade padrão | B42: 6 m/eq/dia — Editável por equipe no CRONO_MACRO coluna K
B45: ABAS INTEGRADAS (v2 - 20/03/2026):
B46: PROJETO — Dados primários editáveis (azul). Fonte de TUDO.
B47: SALDO — Projeto - Executado. 100% fórmulas de PROJETO.
B48: MATERIAIS — Fatores (amarelo) × Saldo = QTD. Muda fator → muda tudo.
B49: COMPRAS_MENSAL — Projeção mensal por núcleo (fórmulas de MATERIAIS).
B50: PEDIDO_URGENTE — O que comprar nos próximos 30 dias.
B51: GANTT_COMPRAS — Visual de execução + compras.
B52: PRIMAVERA_P6 — Exportação para Oracle Primavera P6.
B54: CADEIA: PROJETO → SALDO → MATERIAIS → COMPRAS_MENSAL + PEDIDO_URGENTE
B55: Muda 1 metro em PROJETO → cascateia até o pedido de compras.
B57: ABAS DO CONSTRUDATA PLANEJADOR (integradas):
B58: PAINEL_EXECUTIVO — Dashboard geral do projeto (extensão, custos, progresso)
... B63: FORNECEDORES — Catálogo com contatos, leads e normas técnicas

Sheet PROJETO
A1: PROJETO — Dados primários | AZUL = editável | Todas as abas de compras puxam daqui
A2: Fonte: DXFs reais + SHP executado + campo | CT 11481051 R$241M | 20/03/2026
A4: NÚCLEO | B4: PROJ AG(m) | C4: PROJ ESG(m) | D4: PROJ TOTAL | E4: EXEC AG(m) | F4: EXEC ESG(m) | G4: EXEC TOTAL | H4: MESES REST | I4: EQUIPES | J4: FONTE
A5: SM+JC | B5: 6000 | C5: 6000 | D5: =B5+C5 | E5: 5749 | F5: 2057 | G5: =E5+F5 | H5: 4 | I5: 9 | J5: DXF + SHP
A6: ISRAEL | B6: 1900 | C6: 1900 | D6: =B6+C6 | E6: 1900 | F6: 1900 | G6: =E6+F6 | H6: 0 | I6: 4 | J6: DXF + SHP
A7: TETEU | B7: 5000 | C7: 5000 | D7: =B7+C7 | E7: 1000 | F7: 1000 | G7: =E7+F7 | H7: 5 | I7: 10 | J7: Campo ~2km
A8: CRIADORES | B8: 5000 | C8: 5000 | D8: =B8+C8 | E8: 3298 | F8: 424 | G8: =E8+F8 | H8: 5 | I8: 8 | J8: DXF + SHP
A9: PANTANAL | B9: 4000 | C9: 4000 | D9: =B9+C9 | E9: 252 | F9: 260 | G9: =E9+F9 | H9: 5 | I9: 8 | J9: DXF + SHP
A10: TOTAL | B10: =SUM(B5:B9) | C10: =SUM(C5:C9) | D10: =SUM(D5:D9) | E10: =SUM(E5:E9) | F10: =SUM(F5:F9) | G10: =SUM(G5:G9)

Sheet SALDO
A1: SALDO — Projeto - Executado | 100% fórmulas da aba PROJETO
A3: NÚCLEO | B3: SALDO AG | C3: SALDO ESG | D3: SALDO TOTAL | E3: % AG | F3: % ESG | G3: % TOTAL | H3: STATUS AG | I3: STATUS ESG | J3: MESES | K3: RITMO AG/mês | L3: RITMO ESG/mês
A4: =PROJETO!A5 | B4: =PROJETO!B5-PROJETO!E5 | C4: =PROJETO!C5-PROJETO!F5 | D4: =B4+C4 | E4: =IF(PROJETO!B5>0,PROJETO!E5/PROJETO!B5,1) | F4: =IF(PROJETO!C5>0,PROJETO!F5/PROJETO!C5,1) | G4: =IF(PROJETO!D5>0,PROJETO!G5/PROJETO!D5,1) | H4: =IF(E4>=1,"PRONTO",IF(E4>=0.9,"FINALIZANDO","EM EXECUÇÃO")) | I4: =IF(F4>=1,"PRONTO",IF(F4>=0.9,"FINALIZANDO","EM EXECUÇÃO")) | J4: =PROJETO!H5 | K4: =IF(J4>0,B4/J4,0) | L4: =IF(J4>0,C4/J4,0)
A5: =PROJETO!A6 | B5: =PROJETO!B6-PROJETO!E6 | C5: =PROJETO!C6-PROJETO!F6 | D5: =B5+C5 | E5: =IF(PROJETO!B6>0,PROJETO!E6/PROJETO!B6,1) | F5: =IF(PROJETO!C6>0,PROJETO!F6/PROJETO!C6,1) | G5: =IF(PROJETO!D6>0,PROJETO!G6/PROJETO!D6,1) | H5: =IF(E5>=1,"PRONTO",IF(E5>=0.9,"FINALIZANDO","EM EXECUÇÃO")) | I5: =IF(F5>=1,"PRONTO",IF(F5>=0.9,"FINALIZANDO","EM EXECUÇÃO")) | J5: =PROJETO!H6 | K5: =IF(J5>0,B5/J5,0) | L5: =IF(J5>0,C5/J5,0)
A6: =PROJETO!A7 | B6: =PROJETO!B7-PROJETO!E7 | C6: =PROJETO!C7-PROJETO!F7 | D6: =B6+C6 | E6: =IF(PROJETO!B7>0,PROJETO!E7/PROJETO!B7,1) | F6: =IF(PROJETO!C7>0,PROJETO!F7/PROJETO!C7,1) | G6: =IF(PROJETO!D7>0,PROJETO!G7/PROJETO!D7,1) | H6: =IF(E6>=1,"PRONTO",IF(E6>=0.9,"FINALIZANDO","EM EXECUÇÃO")) | I6: =IF(F6>=1,"PRONTO",IF(F6>=0.9,"FINALIZANDO","EM EXECUÇÃO")) | J6: =PROJETO!H7 | K6: =IF(J6>0,B6/J6,0) | L6: =IF(J6>0,C6/J6,0)
A7: =PROJETO!A8 | B7: =PROJETO!B8-PROJETO!E8 | C7: =PROJETO!C8-PROJETO!F8 | D7: =B7+C7 | E7: =IF(PROJETO!B8>0,PROJETO!E8/PROJETO!B8,1) | F7: =IF(PROJETO!C8>0,PROJETO!F8/PROJETO!C8,1) | G7: =IF(PROJETO!D8>0,PROJETO!G8/PROJETO!D8,1) | H7: =IF(E7>=1,"PRONTO",IF(E7>=0.9,"FINALIZANDO","EM EXECUÇÃO")) | I7: =IF(F7>=1,"PRONTO",IF(F7>=0.9,"FINALIZANDO","EM EXECUÇÃO")) | J7: =PROJETO!H8 | K7: =IF(J7>0,B7/J7,0) | L7: =IF(J7>0,C7/J7,0)
A8: =PROJETO!A9 | B8: =PROJETO!B9-PROJETO!E9 | C8: =PROJETO!C9-PROJETO!F9 | D8: =B8+C8 | E8: =IF(PROJETO!B9>0,PROJETO!E9/PROJETO!B9,1) | F8: =IF(PROJETO!C9>0,PROJETO!F9/PROJETO!C9,1) | G8: =IF(PROJETO!D9>0,PROJETO!G9/PROJETO!D9,1) | H8: =IF(E8>=1,"PRONTO",IF(E8>=0.9,"FINALIZANDO","EM EXECUÇÃO")) | I8: =IF(F8>=1,"PRONTO",IF(F8>=0.9,"FINALIZANDO","EM EXECUÇÃO")) | J8: =PROJETO!H9 | K8: =IF(J8>0,B8/J8,0) | L8: =IF(J8>0,C8/J8,0)
A9: TOTAL | B9: =SUM(B4:B8) | C9: =SUM(C4:C8) | D9: =SUM(D4:D8) | E9: =IF(PROJETO!B10>0,PROJETO!E10/PROJETO!B10,0) | F9: =IF(PROJETO!C10>0,PROJETO!F10/PROJETO!C10,0) | G9: =IF(PROJETO!D10>0,PROJETO!G10/PROJETO!D10,0)

Sheet CRONO_MACRO
A1: CRONOGRAMA MACRO — CONTROLE TOTAL SLNR SANTOS | M/Lig=2 | R$/m=910
A2: J=EQ (equipes) | K=PROD (m/eq/dia) | L=INI (mês início 1=Abr..10=Jan) | Cores: AMARELO=editável | VERDE=calculado
B3: PREMISSAS | E3: M/Lig | F3: 2 | G3: R$/m | H3: 910
B4: NUM MES → | M4: 1 | N4: 2 | O4: 3 | P4: 4 | Q4: 5 | R4: 6 | S4: 7 | T4: 8 | U4: 9 | V4: 10
B5: DIAS UTEIS → | M5: 18 | N5: 22 | O5: 22 | P5: 23 | Q5: 23 | R5: 21 | S5: 21 | T5: 18 | U5: 17 | V5: 21
B6: MESES → | M6: Abr | N6: Mai | O6: Jun | P6: Jul | Q6: Ago | R6: Set | S6: Out | T6: Nov | U6: Dez | V6: Jan/27
A7: ON | B7: Nucleo | C7: SETOR | D7: LA | E7: LE | F7: LIG_TOT | G7: METR_TOT | H7: Inicio | I7: Fim | J7: EQ | K7: PROD | L7: INI | M7: Abr (m) | N7: Mai (m) | O7: Jun (m) | P7: Jul (m) | Q7: Ago (m) | R7: Set (m) | S7: Out (m) | T7: Nov (m) | U7: Dez (m) | V7: Jan/27 (m) | W7: MET PLAN | X7: MET SALDO | Y7: CUSTO (R$) | Z7: PESSOAS
A8: 1 | B8: JOAO CARLOS | C8: SALDO | D8: 0 | E8: 350 | F8: =D8+E8 | G8: =F8*$F$3 | H8: 15/09/25 | I8: 30/04/26 | J8: 4 | K8: 6 | L8: 1 | M8: 432 | N8: 268 | O8: 0 | P8: 0 | Q8: 0 | R8: 0 | S8: 0 | T8: 0 | U8: 0 | V8: 0 | W8: 700 | X8: 0 | Y8: 637000 | Z8: 34
A9: 1 | B9: SAO MANOEL | C9: SALDO | D9: 200 | E9: 400 | F9: =D9+E9 | G9: =F9*$F$3 | H9: 10/09/25 | I9: 29/05/26 | J9: 5 | K9: 6 | L9: 1 | M9: 540 | N9: 660 | O9: 0 | P9: 0 | Q9: 0 | R9: 0 | S9: 0 | T9: 0 | U9: 0 | V9: 0 | W9: 1200 | X9: 0 | Y9: 1092000 | Z9: 42.5
A10: 1 | B10: VILA ISRAEL | C10: SALDO | D10: 150 | E10: 300 | F10: =D10+E10 | G10: =F10*$F$3 | H10: 04/08/25 | I10: 29/05/26 | J10: 4 | K10: 6 | L10: 1 | M10: 432 | N10: 468 | O10: 0 | P10: 0 | Q10: 0 | R10: 0 | S10: 0 | T10: 0 | U10: 0 | V10: 0 | W10: 900 | X10: 0 | Y10: 819000 | Z10: 34
A11: 1 | B11: MORRO DO TETEU | C11: SALDO | D11: 700 | E11: 800 | F11: =D11+E11 | G11: =F11*$F$3 | H11: 27/10/25 | I11: 31/07/26 | J11: 10 | K11: 6 | L11: 1 | M11: 1080 | N11: 1320 | O11: 600 | P11: 0 | Q11: 0 | R11: 0 | S11: 0 | T11: 0 | U11: 0 | V11: 0 | W11: 3000 | X11: 0 | Y11: 2730000 | Z11: 85
A12: 1 | B12: VILA CRIADORES | C12: SALDO | D12: 500 | E12: 600 | F12: =D12+E12 | G12: =F12*$F$3 | H12: 15/10/25 | I12: 31/07/26 | J12: 8 | K12: 6 | L12: 1 | M12: 864 | N12: 1056 | O12: 280 | P12: 0 | Q12: 0 | R12: 0 | S12: 0 | T12: 0 | U12: 0 | V12: 0 | W12: 2200 | X12: 0 | Y12: 2002000 | Z12: 68
A13: 1 | B13: PANTANAL BAIXO | C13: SALDO | D13: 623 | E13: 453 | F13: =D13+E13 | G13: =F13*$F$3 | H13: 20/10/25 | I13: 31/07/26 | J13: 8 | K13: 6 | L13: 1 | M13: 864 | N13: 1056 | O13: 232 | P13: 0 | Q13: 0 | R13: 0 | S13: 0 | T13: 0 | U13: 0 | V13: 0 | W13: 2152 | X13: 0 | Y13: 1958320 | Z13: 68
A14: 1 | B14: NOVO NUCLEO 07 | C14: ST-ZONA NOROESTE | D14: 883 | E14: 2113 | F14: =D14+E14 | G14: =F14*$F$3 | H14: 10/04/26 | I14: 24/09/26 | J14: 10 | K14: 6 | L14: 2 | M14: 0 | N14: 1320 | O14: 1320 | P14: 1380 | Q14: 1380 | R14: 592 | S14: 0 | T14: 0 | U14: 0 | V14: 0 | W14: 5992 | X14: 0 | Y14: 5452720 | Z14: 85
A15: 1 | B15: NOVO NUCLEO 08 | C15: ST-VILA PROGRESSO | D15: 585 | E15: 1280 | F15: =D15+E15 | G15: =F15*$F$3 | H15: 11/05/26 | I15: 23/10/26 | J15: 10 | K15: 6 | L15: 2 | M15: 0 | N15: 1320 | O15: 1320 | P15: 1090 | Q15: 0 | R15: 0 | S15: 0 | T15: 0 | U15: 0 | V15: 0 | W15: 3730 | X15: 0 | Y15: 3394300 | Z15: 85
A16: 1 | B16: NOVO NUCLEO 09 | C16: ST-ZONA LESTE | D16: 480 | E16: 921 | F16: =D16+E16 | G16: =F16*$F$3 | H16: 11/05/26 | I16: 12/10/26 | J16: 10 | K16: 6 | L16: 3 | M16: 0 | N16: 0 | O16: 1320 | P16: 1380 | Q16: 102 | R16: 0 | S16: 0 | T16: 0 | U16: 0 | V16: 0 | W16: 2802 | X16: 0 | Y16: 2549820 | Z16: 85
A17: 1 | B17: NOVO NUCLEO 10 | C17: ST-CONJUNTO | D17: 656 | E17: 1016 | F17: =D17+E17 | G17: =F17*$F$3 | H17: 03/08/26 | I17: 04/01/27 | J17: 10 | K17: 6 | L17: 5 | M17: 0 | N17: 0 | O17: 0 | P17: 0 | Q17: 1380 | R17: 1260 | S17: 704 | T17: 0 | U17: 0 | V17: 0 | W17: 3344 | X17: 0 | Y17: 3043040 | Z17: 85
A18: 1 | B18: NOVO NUCLEO 11 | C18: ALAGADO/DIQUE | D18: 638 | E18: 1224 | F18: =D18+E18 | G18: =F18*$F$3 | H18: 03/08/26 | I18: 04/01/27 | J18: 10 | K18: 6 | L18: 5 | M18: 0 | N18: 0 | O18: 0 | P18: 0 | Q18: 1380 | R18: 1260 | S18: 1084 | T18: 0 | U18: 0 | V18: 0 | W18: 3724 | X18: 0 | Y18: 3388840 | Z18: 85
A19: 1 | B19: NOVO NUCLEO 12 | C19: MONTANHOSO | D19: 4367 | E19: 6144 | F19: =D19+E19 | G19: =F19*$F$3 | H19: 03/08/26 | I19: 04/01/27 | J19: 15 | K19: 12 | L19: 5 | M19: 0 | N19: 0 | O19: 0 | P19: 0 | Q19: 4140 | R19: 3780 | S19: 3780 | T19: 3240 | U19: 3060 | V19: 3022 | W19: 21022 | X19: 0 | Y19: 19130020 | Z19: 127.5
B20: TOTAL METROS | D20: =SUM(D8:D19) | E20: =SUM(E8:E19) | F20: =SUM(F8:F19) | G20: =SUM(G8:G19) | J20: =SUM(J8:J19) | M20: =SUM(M8:M19) | N20: =SUM(N8:N19) | O20: =SUM(O8:O19) | P20: =SUM(P8:P19) | Q20: =SUM(Q8:Q19) | R20: =SUM(R8:R19) | S20: =SUM(S8:S19) | T20: =SUM(T8:T19) | ... Z20: =SUM(Z8:Z19)

Sheet FATORES
A1: FATORES DE COMPOSIÇÃO — ConstruData SLNR Santos | Editável (amarelo) → propaga para MATERIAIS e COMPRAS
A2: QTD = metros_faltantes × fator. Fonte: SINAPI + histórico SLNR. SM+JC usa DXF real (não usa fator genérico)
A3: MATERIAL | B3: TIPO | C3: UN | D3: FATOR/m | E3: PRAZO ENTREGA | F3: APLICA SOBRE | G3: CBUQ TIPO | H3: OBS
A4: Tubo PVC DN200 | B4: ESG | C4: m | D4: 0.6 | E4: 3 semanas | F4: FALTA ESG
A5: Tubo PVC DN300 | B5: ESG | C5: m | D5: 0.4 | E5: 3 semanas | F5: FALTA ESG | H5: Estoque: 200m
A6: PV concreto DN1200 | B6: ESG | C6: un | D6: 0.068 | E6: 2 semanas | F6: FALTA ESG
A7: PI plástico DN600 | B7: ESG | C7: un | D7: 0.022 | E7: 2 semanas | F7: FALTA ESG
A8: Caixa inspeção | B8: ESG | C8: un | D8: 0.055 | E8: 2 semanas | F8: FALTA ESG
A9: Tubo PEAD DN63 | B9: AG | C9: m | D9: 0.7 | E9: 4 semanas | F9: FALTA AG
A10: Tubo PEAD DN110 | B10: AG | C10: m | D10: 0.3 | E10: 4 semanas | F10: FALTA AG
A11: Sela eletrofusão | B11: AG | C11: un | D11: 0.022 | E11: 2 semanas | F11: FALTA AG
A12: Cavalete/hidrom. | B12: AG | C12: un | D12: 0.017 | E12: 3 semanas | F12: FALTA AG
A13: Conexões diversas | B13: AG | C13: vb | D13: 0.011 | E13: 2 semanas | F13: FALTA AG
A14: Areia | B14: GERAL | C14: m³ | D14: 0.25 | E14: 1 semana | F14: FALTA TOTAL | H14: Fundação de vala
A15: Berço | B15: GERAL | C15: m³ | D15: 0.24 | E15: 1 semana | F15: FALTA TOTAL | H15: Apoio do tubo
A16: Brita base | B16: GERAL | C16: m³ | D16: 0.22 | E16: 1 semana | F16: FALTA TOTAL
A17: Concreto | B17: GERAL | C17: m³ | D17: 0.18 | E17: 1 semana | F17: FALTA TOTAL
A18: CBUQ provisório | B18: GERAL | C18: m² | D18: 0.88 | E18: 2 semanas | F18: FALTA TOTAL | G18: PROVISÓRIO | H18: Tapa-buraco
A19: CBUQ definitivo | B19: GERAL | C19: m² | D19: 0.88 | E19: 3 semanas | F19: FALTA TOTAL | G19: DEFINITIVO | H19: Repavimentação final
A20: PEAD PE80 PN12.5 DN63 | B20: AG | C20: m | D20: 0.6503 | E20: 4 semanas | F20: FALTA AG
A21: PEAD PE80 PN12.5 DN160 | B21: AG | C21: m | D21: 0.3107 | E21: 4 semanas | F21: FALTA AG
A22: PEAD PE80 PN10 | B22: AG | C22: m | D22: 0.0026 | E22: 4 semanas | F22: FALTA AG
A23: PVC JE PBA DN20 | B23: AG | C23: m | D23: 0.0366 | E23: 3 semanas | F23: FALTA AG
A24: Sela eletrofusão | B24: AG | C24: un | D24: 0.022 | E24: 2 semanas | F24: FALTA AG
A25: Cavalete/hidrom. | B25: AG | C25: un | D25: 0.017 | E25: 3 semanas | F25: FALTA AG
A26: Conexões diversas | B26: AG | C26: vb | D26: 0.011 | E26: 2 semanas | F26: FALTA AG
A27: Areia | B27: GERAL | C27: m³ | D27: 0.25 | E27: 1 semana | F27: FALTA TOTAL
A28: Berço | B28: GERAL | C28: m³ | D28: 0.24 | E28: 1 semana | F28: FALTA TOTAL
A29: Brita base | B29: GERAL | C29: m³ | D29: 0.22 | E29: 1 semana | F29: FALTA TOTAL
A30: Concreto | B30: GERAL | C30: m³ | D30: 0.18 | E30: 1 semana | F30: FALTA TOTAL
A31: CBUQ provisório | B31: GERAL | C31: m² | D31: 0.88 | E31: 2 semanas | F31: FALTA TOTAL | G31: PROVISÓRIO
A32: CBUQ definitivo | B32: GERAL | C32: m² | D32: 0.88 | E32: 3 semanas | F32: FALTA TOTAL | G32: DEFINITIVO
A33: METROS FALTANTES POR NÚCLEO (atualizar com cadastro)
A34: NÚCLEO | B34: FALTA ESG(m) | C34: FALTA AG(m) | D34: FALTA TOTAL(m) | E34: MESES PROD | F34: REF CRONO
A35: SM+JC | B35: 0 | C35: 5759 | D35: 5759 | E35: 4 | F35: 8+9
A36: Vila Israel | B36: 734 | C36: 1191 | D36: 1925 | E36: 3 | F36: 10
A37: Morro do Tetéu | B37: 3997 | C37: 4696 | D37: 8693 | E37: 5 | F37: 11
A38: Vila Criadores | B38: 2633 | C38: 0 | D38: 2633 | E38: 5 | F38: 12
A39: Pantanal Baixo | B39: 3318 | C39: 3402 | D39: 6720 | E39: 5 | F39: 13

Sheet CUSTOS
A1: CUSTOS — ConstruData SLNR Santos | Contrato 11481051 | TODAS as composições
A3: PREMISSAS GERAIS
A4: Metros por ligação | B4: 2 | C4: m/lig | D4: Vala compartilhada água + esgoto
A5: Custo médio por metro | B5: 910 | C5: R$/m | D5: Média ponderada escav+tubo+PV+ramal+pavim+BDI
A6: BDI | B6: 0.25 | C6: % | D6: Sobre custos diretos
A7: Total ligações | B7: 25383 | C7: lig | D7: Soma de todos os núcleos
A8: Total metros | B8: =B7*B4 | C8: m | D8: Ligações × m/lig
A9: Custo total planejado | B9: =B8*B5 | C9: R$ | D9: Metros plan × R$/m
A10: PREÇOS UNITÁRIOS DE MATERIAIS
A11: MATERIAL | B11: TIPO | C11: UN | D11: PREÇO UNIT. (R$) | E11: FONTE | F11: DATA REF. | G11: VALIDADE | H11: OBS
A12: Tubo PVC DN200 | B12: ESG | C12: m | D12: 200.12 | E12: SINAPI/SABESP | F12: Mar/26 | G12: 90 dias
A13: Tubo PVC DN300 | B13: ESG | C13: m | D13: 310 | E13: SINAPI/SABESP | F13: Mar/26 | G13: 90 dias
A14: PV concreto DN1200 | B14: ESG | C14: un | D14: 3686 | E14: SINAPI/SABESP | F14: Mar/26 | G14: 90 dias
A15: PI plástico DN600 | B15: ESG | C15: un | D15: 1412 | E15: SINAPI/SABESP | F15: Mar/26 | G15: 90 dias
A16: Caixa inspeção | B16: ESG | C16: un | D16: 1034 | E16: SINAPI/SABESP | F16: Mar/26 | G16: 90 dias
A17: Tubo PEAD DN63 | B17: AG | C17: m | D17: 85 | E17: SINAPI/SABESP | F17: Mar/26 | G17: 90 dias
A18: Tubo PEAD DN110 | B18: AG | C18: m | D18: 101.8 | E18: SINAPI/SABESP | F18: Mar/26 | G18: 90 dias
A19: PEAD PE80 PN12.5 DN63 | B19: AG | C19: m | D19: 85 | E19: SINAPI/SABESP | F19: Mar/26 | G19: 90 dias | H19: SM+JC DXF
A20: PEAD PE80 PN12.5 DN160 | B20: AG | C20: m | D20: 145 | E20: SINAPI/SABESP | F20: Mar/26 | G20: 90 dias | H20: SM+JC DXF
A21: PEAD PE80 PN10 | B21: AG | C21: m | D21: 95 | E21: SINAPI/SABESP | F21: Mar/26 | G21: 90 dias
A22: PVC JE PBA DN20 | B22: AG | C22: m | D22: 42 | E22: SINAPI/SABESP | F22: Mar/26 | G22: 90 dias
A23: Sela eletrofusão | B23: AG | C23: un | D23: 660 | E23: SINAPI/SABESP | F23: Mar/26 | G23: 90 dias
A24: Cavalete/hidrom. | B24: AG | C24: un | D24: 490 | E24: SINAPI/SABESP | F24: Mar/26 | G24: 90 dias
A25: Conexões diversas | B25: AG | C25: vb | D25: 120 | E25: SINAPI/SABESP | F25: Mar/26 | G25: 90 dias | H25: Estimativa
A26: Areia | B26: GERAL | C26: m³ | D26: 160 | E26: SINAPI | F26: Mar/26 | G26: 30 dias | H26: Fundação
A27: Berço | B27: GERAL | C27: m³ | D27: 160 | E27: SINAPI | F27: Mar/26 | G27: 30 dias | H27: Apoio tubo
A28: Brita base | B28: GERAL | C28: m³ | D28: 210 | E28: SINAPI | F28: Mar/26 | G28: 30 dias
A29: Concreto | B29: GERAL | C29: m³ | D29: 720 | E29: SINAPI | F29: Mar/26 | G29: 30 dias | H29: fck 20 MPa
A30: CBUQ provisório | B30: GERAL | C30: m² | D30: 55 | E30: SINAPI | F30: Mar/26 | G30: 30 dias | H30: Tapa-buraco 3cm
A31: CBUQ definitivo | B31: GERAL | C31: m² | D31: 120 | E31: SINAPI | F31: Mar/26 | G31: 60 dias | H31: Repavim. 5cm
A32: CUSTO POR MATERIAL — A COMPRAR × PREÇO UNITÁRIO
A33: MATERIAL | B33: UN | C33: SALDO PROJETO | D33: A COMPRAR | E33: PREÇO UNIT.(R$) | F33: CUSTO COMPRA(R$) | G33: CUSTO C/ BDI(R$) | H33: % DO TOTAL
A34: Tubo PVC DN200 | B34: m | C34: 6409.2 | D34: 6409.2 | E34: 200.12 | F34: =D34*E34 | G34: =F34*(1+CUSTOS!$B$6) | H34: =IF(SUM(G34:G53)>0,G34/SUM(G34:G53),0)
A35: Tubo PVC DN300 | B35: m | C35: 4272.8 | D35: 4072.8 | E35: 310 | F35: =D35*E35 | G35: =F35*(1+CUSTOS!$B$6) | H35: =IF(SUM(G34:G53)>0,G35/SUM(G34:G53),0)
A36: PV concreto DN1200 | B36: un | C36: 726.376 | D36: 726.376 | E36: 3686 | F36: =D36*E36 | G36: =F36*(1+CUSTOS!$B$6) | H36: =IF(SUM(G34:G53)>0,G36/SUM(G34:G53),0)
A37: PI plástico DN600 | B37: un | C37: 235.004 | D37: 235.004 | E37: 1412 | F37: =D37*E37 | G37: =F37*(1+CUSTOS!$B$6) | H37: =IF(SUM(G34:G53)>0,G37/SUM(G34:G53),0)
A38: Caixa inspeção | B38: un | C38: 587.51 | D38: 587.51 | E38: 1034 | F38: =D38*E38 | G38: =F38*(1+CUSTOS!$B$6) | H38: =IF(SUM(G34:G53)>0,G38/SUM(G34:G53),0)
A39: Tubo PEAD DN63 | B39: m | C39: 6502.3 | D39: 6502.3 | E39: 85 | F39: =D39*E39 | G39: =F39*(1+CUSTOS!$B$6) | H39: =IF(SUM(G34:G53)>0,G39/SUM(G34:G53),0)
A40: Tubo PEAD DN110 | B40: m | C40: 2786.7 | D40: 2786.7 | E40: 101.8 | F40: =D40*E40 | G40: =F40*(1+CUSTOS!$B$6) | H40: =IF(SUM(G34:G53)>0,G40/SUM(G34:G53),0)
A41: PEAD PE80 PN12.5 DN63 | B41: m | C41: 3745.0777 | D41: 3745.0777 | E41: 85 | F41: =D41*E41 | G41: =F41*(1+CUSTOS!$B$6) | H41: =IF(SUM(G34:G53)>0,G41/SUM(G34:G53),0)
A42: PEAD PE80 PN12.5 DN160 | B42: m | C42: 1789.3213 | D42: 1789.3213 | E42: 145 | F42: =D42*E42 | G42: =F42*(1+CUSTOS!$B$6) | H42: =IF(SUM(G34:G53)>0,G42/SUM(G34:G53),0)
A43: PEAD PE80 PN10 | B43: m | C43: 14.9734 | D43: 14.9734 | E43: 95 | F43: =D43*E43 | G43: =F43*(1+CUSTOS!$B$6) | H43: =IF(SUM(G34:G53)>0,G43/SUM(G34:G53),0)
A44: PVC JE PBA DN20 | B44: m | C44: 210.7794 | D44: 210.7794 | E44: 42 | F44: =D44*E44 | G44: =F44*(1+CUSTOS!$B$6) | H44: =IF(SUM(G34:G53)>0,G44/SUM(G34:G53),0)
A45: Sela eletrofusão | B45: un | C45: 331.056 | D45: 331.056 | E45: 660 | F45: =D45*E45 | G45: =F45*(1+CUSTOS!$B$6) | H45: =IF(SUM(G34:G53)>0,G45/SUM(G34:G53),0)
A46: Cavalete/hidrom. | B46: un | C46: 255.816 | D46: 255.816 | E46: 490 | F46: =D46*E46 | G46: =F46*(1+CUSTOS!$B$6) | H46: =IF(SUM(G34:G53)>0,G46/SUM(G34:G53),0)
A47: Conexões diversas | B47: vb | C47: 165.528 | D47: 165.528 | E47: 120 | F47: =D47*E47 | G47: =F47*(1+CUSTOS!$B$6) | H47: =IF(SUM(G34:G53)>0,G47/SUM(G34:G53),0)
A48: Areia | B48: m³ | C48: 6432.5 | D48: 6432.5 | E48: 160 | F48: =D48*E48 | G48: =F48*(1+CUSTOS!$B$6) | H48: =IF(SUM(G34:G53)>0,G48/SUM(G34:G53),0)
A49: Berço | B49: m³ | C49: 6175.2 | D49: 6175.2 | E49: 160 | F49: =D49*E49 | G49: =F49*(1+CUSTOS!$B$6) | H49: =IF(SUM(G34:G53)>0,G49/SUM(G34:G53),0)
A50: Brita base | B50: m³ | C50: 5660.6 | D50: 5660.6 | E50: 210 | F50: =D50*E50 | G50: =F50*(1+CUSTOS!$B$6) | H50: =IF(SUM(G34:G53)>0,G50/SUM(G34:G53),0)
A51: Concreto | B51: m³ | C51: 4631.4 | D51: 4631.4 | E51: 720 | F51: =D51*E51 | G51: =F51*(1+CUSTOS!$B$6) | H51: =IF(SUM(G34:G53)>0,G51/SUM(G34:G53),0)
A52: CBUQ provisório | B52: m² | C52: 22642.4 | D52: 22642.4 | E52: 55 | F52: =D52*E52 | G52: =F52*(1+CUSTOS!$B$6) | H52: =IF(SUM(G34:G53)>0,G52/SUM(G34:G53),0)
A53: CBUQ definitivo | B53: m² | C53: 22642.4 | D53: 22642.4 | E53: 120 | F53: =D53*E53 | G53: =F53*(1+CUSTOS!$B$6) | H53: =IF(SUM(G34:G53)>0,G53/SUM(G34:G53),0)
A54: TOTAL MATERIAIS | C54: =SUM(C34:C53) | D54: =SUM(D34:D53) | F54: =SUM(F34:F53) | G54: =SUM(G34:G53) | H54: =1
A55: RESUMO EXECUTIVO DE CUSTOS
A56: Custo total materiais (s/ BDI) | B56: 18453046
A57: Custo total materiais (c/ BDI) | B57: 23066308
A58: Custo planejado CRONO_MACRO | B58: 46197060
A59: TARGET de compra | B59: 5000000
A60: % material / custo total | B60: 0.4993025
A61: Custo por ligação (material) | B61: 908.73056
A62: Custo por metro (material) | B62: 454.36528
A63: COMPOSIÇÃO DE CUSTO POR METRO (R$ 910/m)
A64: ITEM | B64: VALOR | C64: UN | D64: DETALHAMENTO
A65: Escavação mecânica | B65: 145 | C65: R$/m | D65: Retroescavadeira + operador
A66: Tubo ESG (média DN200/300) | B66: 240 | C66: R$/m | D66: Fornecimento + assentamento
A67: Tubo AG (média PEAD) | B67: 95 | C67: R$/m | D67: Fornecimento + fusão
A68: PV / Caixas / PIs | B68: 120 | C68: R$/m | D68: Média rateada por metro
A69: Reaterro compactado | B69: 80 | C69: R$/m | D69: Areia + berço + brita + compactação
A70: Ramal predial | B70: 65 | C70: R$/m | D70: Sela + cavalete + conexão
A71: Pavimentação (CBUQ prov+def) | B71: 45 | C71: R$/m | D71: Tapa-buraco + definitivo
A72: Sinalização + segurança | B72: 15 | C72: R$/m | D72: Cones, placas, sinaleiro
A73: BDI 25% | B73: 197.5 | C73: R$/m | D73: 25% sobre diretos
A74: TOTAL | B74: 805 | C74: R$/m | D74: ≈ R$ 910/m (CRONO_MACRO!H3)

Sheet DIMENSIONAMENTO
A1: DIMENSIONAMENTO — Equipes por setor (linkado CRONO_MACRO)
A3: DIMENSIONAMENTO LINKADO
A4: NUCLEO | B4: SETOR | C4: LIG | D4: EQ | E4: PESSOAS | F4: CUSTO
A5: N07 | B5: ST-NOROESTE | C5: 2996 | D5: 10 | E5: =D5*8.5 | F5: =C5*CUSTOS!$B$4*CUSTOS!$B$5
A6: N08 | B6: ST-V.PROGRESSO | C6: 1865 | D6: 10 | E6: =D6*8.5 | F6: =C6*CUSTOS!$B$4*CUSTOS!$B$5
A7: N09 | B7: ST-Z.LESTE | C7: 1401 | D7: 10 | E7: =D7*8.5 | F7: =C7*CUSTOS!$B$4*CUSTOS!$B$5
A8: N10 | B8: ST-CONJUNTO | C8: 1672 | D8: 10 | E8: =D8*8.5 | F8: =C8*CUSTOS!$B$4*CUSTOS!$B$5
A9: N11 | B9: ALAGADO | C9: 1862 | D9: 10 | E9: =D9*8.5 | F9: =C9*CUSTOS!$B$4*CUSTOS!$B$5
A10: N12 | B10: MONTANHOSO | C10: 10511 | D10: 15 | E10: =D10*8.5 | F10: =C10*CUSTOS!$B$4*CUSTOS!$B$5
A11: TOTAL | C11: =SUM(C5:C10) | D11: =SUM(D5:D10) | E11: =SUM(E5:E10) | F11: =SUM(F5:F10)

Sheet PLEITO
A1: PLEITO — Acréscimo R$13,7M + aditivos
A3: PLEITO LINKADO
A4: INDICADOR | B4: CONTRATO | C4: REAL | D4: VALOR
A5: Produtividade | B5: 6.0 | C5: 0
A6: M/Ligacao | B6: 2.85 | C6: 0
A7: Total LIG | C7: 25383
A8: Total EQ | C8: 104
A9: Total CUSTO | D9: 50766
A10: Delta metragem | D10: R$ 9.140.812
A11: Delta produtividade | D11: R$ 4.570.406
A12: TOTAL PLEITO | D12: R$ 13.711.217
A13: Aditivos | D13: R$ 40.965.978
A14: GRANDE TOTAL | D14: R$ 64.589.554

Sheet ADITIVOS
A1: ADITIVOS — 8 itens + elevatórias
A3: ADITIVOS + ELEVATORIAS
A4: # | B4: Desc | C4: Un | D4: Qtd | E4: P.Unit | F4: Total
A5: AD-01 | B5: ESCADA CONCRETO | C5: M | D5: 900 | E5: 2856 | F5: =D5*E5
A6: AD-02 | B6: REDE ESG DN300 | C6: M | D6: 6000 | E6: 2350 | F6: =D6*E6
A7: AD-03 | B7: MND PEAD AGUA 160 | C7: M | D7: 3200 | E7: 1812.07 | F7: =D7*E7
A8: AD-04 | B8: MND PEAD ESG 315 | C8: M | D8: 1600 | E8: 3202.84 | F8: =D8*E8
A9: AD-05 | B9: PRA PEAD 150-200 | C9: M | D9: 6000 | E9: 1523.34 | F9: =D9*E9
A10: AD-07 | B10: TRANSPORTE RES | C10: UND | D10: 60 | E10: 9100 | F10: =D10*E10
A11: AD-08 | B11: SOLIDOS NAO REC | C11: KG | D11: 2430000 | E11: 1.2 | F11: =D11*E11
A12: AD-09 | B12: REATERRO HIDR | C12: M | D12: 3000 | E12: 256.79 | F12: =D12*E12
A13: EEE-1 | B13: EEE 82x50 (x2) | C13: CJ | D13: 2 | E13: 2284948.7 | F13: =D13*E13
A14: EEE-2 | B14: EEE 38x20 (x2) | C14: CJ | D14: 2 | E14: 1208730.7 | F14: =D14*E14
B15: TOTAL | F15: =SUM(F5:F14)

Sheet PRIMAVERA_P6
A1: PRIMAVERA P6 LINKADO - EQ e custo do CRONO_MACRO
A3: Act_ID | B3: WBS | C3: Activity | D3: Type | E3: Dur | F3: Start | G3: Finish | H3: Cal | I3: Cost | J3: Resource | K3: EQ | L3: LIG | M3: Notes
A4: A2000 | B4: S7.NOR.010524.PRJ | C4: PRJ Vila Alemoa | D4: TaskDep | E4: 15 | F4: 10/04/26 | H4: 5d/w | I4: 614578 | J4: Eng.Proj | K4: 1 | L4: 0
A5: A2010 | B5: S7.NOR.010524.EXE | C5: EXE Vila Alemoa | D5: TaskDep | E5: =IFERROR(ROUND(1407*CRONO_MACRO!$F$4/(CRONO_MACRO!J14/CRONO_MACRO!F14*1407*CRONO_MACRO!$D$4),0),0) | F5: 10/04/26 | G5: 24/09/26 | H5: 5d/w | I5: 6529887 | J5: Eq.Campo | K5: =IFERROR(ROUND(CRONO_MACRO!J14*1407/CRONO_MACRO!F14,0),0) | L5: 1407 | M5: 1407lig
A6: A2020 | B6: S7.NOR.010524.ASB | C6: ASB Vila Alemoa | D6: TaskDep | E6: 10 | G6: 24/09/26 | H6: 5d/w | I6: 614578 | J6: Eng.Asb | K6: 1 | L6: 0
A7: A2100 | B7: S7.NOR.010518.PRJ | C7: PRJ Ilheu Baixo | D7: TaskDep | E7: 15 | F7: 10/04/26 | H7: 5d/w | I7: 295277 | J7: Eng.Proj | K7: 1 | L7: 0
A8: A2110 | B8: S7.NOR.010518.EXE | C8: EXE Ilheu Baixo | D8: TaskDep | E8: =IFERROR(ROUND(676*CRONO_MACRO!$F$4/(CRONO_MACRO!J14/CRONO_MACRO!F14*676*CRONO_MACRO!$D$4),0),0) | F8: 10/04/26 | G8: 24/09/26 | H8: 5d/w | I8: 3137316 | J8: Eq.Campo | K8: =IFERROR(ROUND(CRONO_MACRO!J14*676/CRONO_MACRO!F14,0),0) | L8: 676 | M8: 676lig
A9: A2120 | B9: S7.NOR.010518.ASB | C9: ASB Ilheu Baixo | D9: TaskDep | E9: 10 | G9: 24/09/26 | H9: 5d/w | I9: 295277 | J9: Eng.Asb | K9: 1 | L9: 0
A10: A2200 | B10: S7.NOR.010522.PRJ | C10: PRJ NSRA Fatima | D10: TaskDep | E10: 15 | F10: 10/04/26 | H10: 5d/w | I10: 114005 | J10: Eng.Proj | K10: 1 | L10: 0
A11: A2210 | B11: S7.NOR.010522.EXE | C11: EXE NSRA Fatima | D11: TaskDep | E11: =IFERROR(ROUND(261*CRONO_MACRO!$F$4/(CRONO_MACRO!J14/CRONO_MACRO!F14*261*CRONO_MACRO!$D$4),0),0) | F11: 10/04/26 | G11: 24/09/26 | H11: 5d/w | I11: 1211301 | J11: Eq.Campo | K11: =IFERROR(ROUND(CRONO_MACRO!J14*261/CRONO_MACRO!F14,0),0) | L11: 261 | M11: 261lig
A12: A2220 | B12: S7.NOR.010522.ASB | C12: ASB NSRA Fatima | D12: TaskDep | E12: 10 | G12: 24/09/26 | H12: 5d/w | I12: 114005 | J12: Eng.Asb | K12: 1 | L12: 0
A13: A2300 | B13: S7.NOR.010526.PRJ | C13: PRJ Vila Telma | D13: TaskDep | E13: 15 | F13: 10/04/26 | H13: 5d/w | I13: 83429 | J13: Eng.Proj | K13: 1 | L13: 0
A14: A2310 | B14: S7.NOR.010526.EXE | C14: EXE Vila Telma | D14: TaskDep | E14: =IFERROR(ROUND(191*CRONO_MACRO!$F$4/(CRONO_MACRO!J14/CRONO_MACRO!F14*191*CRONO_MACRO!$D$4),0),0) | F14: 10/04/26 | G14: 24/09/26 | H14: 5d/w | I14: 886431 | J14: Eq.Campo | K14: =IFERROR(ROUND(CRONO_MACRO!J14*191/CRONO_MACRO!F14,0),0) | L14: 191 | M14: 191lig
A15: A2320 | B15: S7.NOR.010526.ASB | C15: ASB Vila Telma | D15: TaskDep | E15: 10 | G15: 24/09/26 | H15: 5d/w | I15: 83429 | J15: Eng.Asb | K15: 1 | L15: 0
A16: A2400 | B16: S7.NOR.010525.PRJ | C16: PRJ V.Alemoa Rem | D16: TaskDep | E16: 15 | F16: 10/04/26 | H16: 5d/w | I16: 43680 | J16: Eng.Proj | K16: 1 | L16: 0
A17: A2410 | B17: S7.NOR.010525.EXE | C17: EXE V.Alemoa Rem | D17: TaskDep | E17: =IFERROR(ROUND(100*CRONO_MACRO!$F$4/(CRONO_MACRO!J14/CRONO_MACRO!F14*100*CRONO_MACRO!$D$4),0),0) | F17: 10/04/26 | G17: 24/09/26 | H17: 5d/w | I17: 464100 | J17: Eq.Campo | K17: =IFERROR(ROUND(CRONO_MACRO!J14*100/CRONO_MACRO!F14,0),0) | L17: 100 | M17: 100lig
A18: A2420 | B18: S7.NOR.010525.ASB | C18: ASB V.Alemoa Rem | D18: TaskDep | E18: 10 | G18: 24/09/26 | H18: 5d/w | I18: 43680 | J18: Eng.Asb | K18: 1 | L18: 0
A19: A2500 | B19: S7.NOR.010521.PRJ | C19: PRJ Lote L Chico | D19: TaskDep | E19: 15 | F19: 10/04/26 | H19: 5d/w | I19: 41933 | J19: Eng.Proj | K19: 1 | L19: 0
A20: A2510 | B20: S7.NOR.010521.EXE | C20: EXE Lote L Chico | D20: TaskDep | E20: =IFERROR(ROUND(96*CRONO_MACRO!$F$4/(CRONO_MACRO!J14/CRONO_MACRO!F14*96*CRONO_MACRO!$D$4),0),0) | F20: 10/04/26 | G20: 24/09/26 | H20: 5d/w | I20: 445536 | J20: Eq.Campo | K20: =IFERROR(ROUND(CRONO_MACRO!J14*96/CRONO_MACRO!F14,0),0) | L20: 96 | M20: 96lig
A21: A2520 | B21: S7.NOR.010521.ASB | C21: ASB Lote L Chico | D21: TaskDep | E21: 10 | G21: 24/09/26 | H21: 5d/w | I21: 41933 | J21: Eng.Asb | K21: 1 | L21: 0
A22: A2600 | B22: S7.NOR.010523.PRJ | C22: PRJ V.Alemoa COHAB | D22: TaskDep | E22: 15 | F22: 10/04/26 | H22: 5d/w | I22: 34070 | J22: Eng.Proj | K22: 1 | L22: 0
A23: A2610 | B23: S7.NOR.010523.EXE | C23: EXE V.Alemoa COHAB | D23: TaskDep | E23: =IFERROR(ROUND(78*CRONO_MACRO!$F$4/(CRONO_MACRO!J14/CRONO_MACRO!F14*78*CRONO_MACRO!$D$4),0),0) | F23: 10/04/26 | G23: 24/09/26 | H23: 5d/w | I23: 361998 | J23: Eq.Campo | K23: =IFERROR(ROUND(CRONO_MACRO!J14*78/CRONO_MACRO!F14,0),0) | L23: 78 | M23: 78lig
A24: A2620 | B24: S7.NOR.010523.ASB | C24: ASB V.Alemoa COHAB | D24: TaskDep | E24: 10 | G24: 24/09/26 | H24: 5d/w | I24: 34070 | J24: Eng.Asb | K24: 1 | L24: 0
A25: A2700 | B25: S7.NOR.010520.PRJ | C25: PRJ Joao Barro | D25: TaskDep | E25: 15 | F25: 10/04/26 | H25: 5d/w | I25: 38002 | J25: Eng.Proj | K25: 1 | L25: 0
A26: A2710 | B26: S7.NOR.010520.EXE | C26: EXE Joao Barro | D26: TaskDep | E26: =IFERROR(ROUND(87*CRONO_MACRO!$F$4/(CRONO_MACRO!J14/CRONO_MACRO!F14*87*CRONO_MACRO!$D$4),0),0) | F26: 10/04/26 | G26: 24/09/26 | H26: 5d/w | I26: 403767 | J26: Eq.Campo | K26: =IFERROR(ROUND(CRONO_MACRO!J14*87/CRONO_MACRO!F14,0),0) | L26: 87 | M26: 87lig
A27: A2720 | B27: S7.NOR.010520.ASB | C27: ASB Joao Barro | D27: TaskDep | E27: 10 | G27: 24/09/26 | H27: 5d/w | I27: 38002 | J27: Eng.Asb | K27: 1 | L27: 0
A28: A2800 | B28: S7.NOR.010515.PRJ | C28: PRJ Saboo II | D28: TaskDep | E28: 15 | F28: 10/04/26 | H28: 5d/w | I28: 37565 | J28: Eng.Proj | K28: 1 | L28: 0
A29: A2810 | B29: S7.NOR.010515.EXE | C29: EXE Saboo II | D29: TaskDep | E29: =IFERROR(ROUND(86*CRONO_MACRO!$F$4/(CRONO_MACRO!J14/CRONO_MACRO!F14*86*CRONO_MACRO!$D$4),0),0) | F29: 10/04/26 | G29: 24/09/26 | H29: 5d/w | I29: 399126 | J29: Eq.Campo | K29: =IFERROR(ROUND(CRONO_MACRO!J14*86/CRONO_MACRO!F14,0),0) | L29: 86 | M29: 86lig
A30: A2820 | B30: S7.NOR.010515.ASB | C30: ASB Saboo II | D30: TaskDep | E30: 10 | G30: 24/09/26 | H30: 5d/w | I30: 37565 | J30: Eng.Asb | K30: 1 | L30: 0
A31: A2900 | B31: S7.NOR.010517.PRJ | C31: PRJ Fav.Butanta | D31: TaskDep | E31: 15 | F31: 10/04/26 | H31: 5d/w | I31: 6115 | J31: Eng.Proj | K31: 1 | L31: 0
A32: A2910 | B32: S7.NOR.010517.EXE | C32: EXE Fav.Butanta | D32: TaskDep | E32: =IFERROR(ROUND(14*CRONO_MACRO!$F$4/(CRONO_MACRO!J14/CRONO_MACRO!F14*14*CRONO_MACRO!$D$4),0),0) | F32: 10/04/26 | G32: 24/09/26 | H32: 5d/w | I32: 64974 | J32: Eq.Campo | K32: =IFERROR(ROUND(CRONO_MACRO!J14*14/CRONO_MACRO!F14,0),0) | L32: 14 | M32: 14lig
A33: A2920 | B33: S7.NOR.010517.ASB | C33: ASB Fav.Butanta | D33: TaskDep | E33: 10 | G33: 24/09/26 | H33: 5d/w | I33: 6115 | J33: Eng.Asb | K33: 1 | L33: 0
A34: A3000 | B34: S8.VPR.010502.PRJ | C34: PRJ R Um N.Cintra | D34: TaskDep | E34: 15 | F34: 11/05/26 | H34: 5d/w | I34: 304013 | J34: Eng.Proj | K34: 1 | L34: 0
A35: A3010 | B35: S8.VPR.010502.EXE | C35: EXE R Um N.Cintra | D35: TaskDep | E35: =IFERROR(ROUND(696*CRONO_MACRO!$F$4/(CRONO_MACRO!J15/CRONO_MACRO!F15*696*CRONO_MACRO!$D$4),0),0) | F35: 11/05/26 | G35: 23/10/26 | H35: 5d/w | I35: 3230136 | J35: Eq.Campo | K35: =IFERROR(ROUND(CRONO_MACRO!J15*696/CRONO_MACRO!F15,0),0) | L35: 696 | M35: 696lig
A36: A3020 | B36: S8.VPR.010502.ASB | C36: ASB R Um N.Cintra | D36: TaskDep | E36: 10 | G36: 23/10/26 | H36: 5d/w | I36: 304013 | J36: Eng.Asb | K36: 1 | L36: 0
A37: A3100 | B37: S8.VPR.010507.PRJ | C37: PRJ V.Progresso | D37: TaskDep | E37: 15 | F37: 11/05/26 | H37: 5d/w | I37: 265574 | J37: Eng.Proj | K37: 1 | L37: 0
A38: A3110 | B38: S8.VPR.010507.EXE | C38: EXE V.Progresso | D38: TaskDep | E38: =IFERROR(ROUND(608*CRONO_MACRO!$F$4/(CRONO_MACRO!J15/CRONO_MACRO!F15*608*CRONO_MACRO!$D$4),0),0) | F38: 11/05/26 | G38: 23/10/26 | H38: 5d/w | I38: 2821728 | J38: Eq.Campo | K38: =IFERROR(ROUND(CRONO_MACRO!J15*608/CRONO_MACRO!F15,0),0) | L38: 608 | M38: 608lig
A39: A3120 | B39: S8.VPR.010507.ASB | C39: ASB V.Progresso | D39: TaskDep | E39: 10 | G39: 23/10/26 | H39: 5d/w | I39: 265574 | J39: Eng.Asb | K39: 1 | L39: 0
A40: A3200 | B40: S8.VPR.010503.PRJ | C40: PRJ Encosta Saboo | D40: TaskDep | E40: 15 | F40: 11/05/26 | H40: 5d/w | I40: 122304 | J40: Eng.Proj | K40: 1 | L40: 0
A41: A3210 | B41: S8.VPR.010503.EXE | C41: EXE Encosta Saboo | D41: TaskDep | E41: =IFERROR(ROUND(280*CRONO_MACRO!$F$4/(CRONO_MACRO!J15/CRONO_MACRO!F15*280*CRONO_MACRO!$D$4),0),0) | F41: 11/05/26 | G41: 23/10/26 | H41: 5d/w | I41: 1299480 | J41: Eq.Campo | K41: =IFERROR(ROUND(CRONO_MACRO!J15*280/CRONO_MACRO!F15,0),0) | L41: 280 | M41: 280lig
A42: A3220 | B42: S8.VPR.010503.ASB | C42: ASB Encosta Saboo | D42: TaskDep | E42: 10 | G42: 23/10/26 | H42: 5d/w | I42: 122304 | J42: Eng.Asb | K42: 1 | L42: 0
A43: A3300 | B43: S8.VPR.010504.PRJ | C43: PRJ Menino Jesus | D43: TaskDep | E43: 15 | F43: 11/05/26 | H43: 5d/w | I43: 69014 | J43: Eng.Proj | K43: 1 | L43: 0
A44: A3310 | B44: S8.VPR.010504.EXE | C44: EXE Menino Jesus | D44: TaskDep | E44: =IFERROR(ROUND(158*CRONO_MACRO!$F$4/(CRONO_MACRO!J15/CRONO_MACRO!F15*158*CRONO_MACRO!$D$4),0),0) | F44: 11/05/26 | G44: 23/10/26 | H44: 5d/w | I44: 733278 | J44: Eq.Campo | K44: =IFERROR(ROUND(CRONO_MACRO!J15*158/CRONO_MACRO!F15,0),0) | L44: 158 | M44: 158lig
A45: A3320 | B45: S8.VPR.010504.ASB | C45: ASB Menino Jesus | D45: TaskDep | E45: 10 | G45: 23/10/26 | H45: 5d/w | I45: 69014 | J45: Eng.Asb | K45: 1 | L45: 0
A46: A3400 | B46: S8.VPR.010506.PRJ | C46: PRJ Rua Nove | D46: TaskDep | E46: 15 | F46: 11/05/26 | H46: 5d/w | I46: 23587 | J46: Eng.Proj | K46: 1 | L46: 0
A47: A3410 | B47: S8.VPR.010506.EXE | C47: EXE Rua Nove | D47: TaskDep | E47: =IFERROR(ROUND(54*CRONO_MACRO!$F$4/(CRONO_MACRO!J15/CRONO_MACRO!F15*54*CRONO_MACRO!$D$4),0),0) | F47: 11/05/26 | G47: 23/10/26 | H47: 5d/w | I47: 250614 | J47: Eq.Campo | K47: =IFERROR(ROUND(CRONO_MACRO!J15*54/CRONO_MACRO!F15,0),0) | L47: 54 | M47: 54lig
A48: A3420 | B48: S8.VPR.010506.ASB | C48: ASB Rua Nove | D48: TaskDep | E48: 10 | G48: 23/10/26 | H48: 5d/w | I48: 23587 | J48: Eng.Asb | K48: 1 | L48: 0
A49: A3500 | B49: S8.VPR.010509.PRJ | C49: PRJ R.M.Mercedes | D49: TaskDep | E49: 15 | F49: 11/05/26 | H49: 5d/w | I49: 20530 | J49: Eng.Proj | K49: 1 | L49: 0
A50: A3510 | B50: S8.VPR.010509.EXE | C50: EXE R.M.Mercedes | D50: TaskDep | E50: =IFERROR(ROUND(47*CRONO_MACRO!$F$4/(CRONO_MACRO!J15/CRONO_MACRO!F15*47*CRONO_MACRO!$D$4),0),0) | F50: 11/05/26 | G50: 23/10/26 | H50: 5d/w | I50: 218127 | J50: Eq.Campo | K50: =IFERROR(ROUND(CRONO_MACRO!J15*47/CRONO_MACRO!F15,0),0) | L50: 47 | M50: 47lig
A51: A3520 | B51: S8.VPR.010509.ASB | C51: ASB R.M.Mercedes | D51: TaskDep | E51: 10 | G51: 23/10/26 | H51: 5d/w | I51: 20530 | J51: Eng.Asb | K51: 1 | L51: 0
A52: A3600 | B52: S8.VPR.010508.PRJ | C52: PRJ V.Telma Cima | D52: TaskDep | E52: 15 | F52: 11/05/26 | H52: 5d/w | I52: 9610 | J52: Eng.Proj | K52: 1 | L52: 0
A53: A3610 | B53: S8.VPR.010508.EXE | C53: EXE V.Telma Cima | D53: TaskDep | E53: =IFERROR(ROUND(22*CRONO_MACRO!$F$4/(CRONO_MACRO!J15/CRONO_MACRO!F15*22*CRONO_MACRO!$D$4),0),0) | F53: 11/05/26 | G53: 23/10/26 | H53: 5d/w | I53: 102102 | J53: Eq.Campo | K53: =IFERROR(ROUND(CRONO_MACRO!J15*22/CRONO_MACRO!F15,0),0) | L53: 22 | M53: 22lig
A54: A3620 | B54: S8.VPR.010508.ASB | C54: ASB V.Telma Cima | D54: TaskDep | E54: 10 | G54: 23/10/26 | H54: 5d/w | I54: 9610 | J54: Eng.Asb | K54: 1 | L54: 0
A55: A3700 | B55: S9.ZLE.010473.PRJ | C55: PRJ Clovis Galvao | D55: TaskDep | E55: 15 | F55: 11/05/26 | H55: 5d/w | I55: 295277 | J55: Eng.Proj | K55: 1 | L55: 0
A56: A3710 | B56: S9.ZLE.010473.EXE | C56: EXE Clovis Galvao | D56: TaskDep | E56: =IFERROR(ROUND(676*CRONO_MACRO!$F$4/(CRONO_MACRO!J16/CRONO_MACRO!F16*676*CRONO_MACRO!$D$4),0),0) | F56: 11/05/26 | G56: 12/10/26 | H56: 5d/w | I56: 3137316 | J56: Eq.Campo | K56: =IFERROR(ROUND(CRONO_MACRO!J16*676/CRONO_MACRO!F16,0),0) | L56: 676 | M56: 676lig
A57: A3720 | B57: S9.ZLE.010473.ASB | C57: ASB Clovis Galvao | D57: TaskDep | E57: 10 | G57: 12/10/26 | H57: 5d/w | I57: 295277 | J57: Eng.Asb | K57: 1 | L57: 0
A58: A3800 | B58: S9.ZLE.010468.PRJ | C58: PRJ Div.Tiro Naval | D58: TaskDep | E58: 15 | F58: 11/05/26 | H58: 5d/w | I58: 321485 | J58: Eng.Proj | K58: 1 | L58: 0
A59: A3810 | B59: S9.ZLE.010468.EXE | C59: EXE Div.Tiro Naval | D59: TaskDep | E59: =IFERROR(ROUND(736*CRONO_MACRO!$F$4/(CRONO_MACRO!J16/CRONO_MACRO!F16*736*CRONO_MACRO!$D$4),0),0) | F59: 11/05/26 | G59: 12/10/26 | H59: 5d/w | I59: 3415776 | J59: Eq.Campo | K59: =IFERROR(ROUND(CRONO_MACRO!J16*736/CRONO_MACRO!F16,0),0) | L59: 736 | M59: 736lig
A60: A3820 | B60: S9.ZLE.010468.ASB | C60: ASB Div.Tiro Naval | D60: TaskDep | E60: 10 | G60: 12/10/26 | H60: 5d/w | I60: 321485 | J60: Eng.Asb | K60: 1 | L60: 0
A61: A3900 | B61: S9.ZLE.010474.PRJ | C61: PRJ M.Marape(a) | D61: TaskDep | E61: 15 | F61: 11/05/26 | H61: 5d/w | I61: 235872 | J61: Eng.Proj | K61: 1 | L61: 0
A62: A3910 | B62: S9.ZLE.010474.EXE | C62: EXE M.Marape(a) | D62: TaskDep | E62: =IFERROR(ROUND(540*CRONO_MACRO!$F$4/(CRONO_MACRO!J16/CRONO_MACRO!F16*540*CRONO_MACRO!$D$4),0),0) | F62: 11/05/26 | G62: 12/10/26 | H62: 5d/w | I62: 2506140 | J62: Eq.Campo | K62: =IFERROR(ROUND(CRONO_MACRO!J16*540/CRONO_MACRO!F16,0),0) | L62: 540 | M62: 540lig
A63: A3920 | B63: S9.ZLE.010474.ASB | C63: ASB M.Marape(a) | D63: TaskDep | E63: 10 | G63: 12/10/26 | H63: 5d/w | I63: 235872 | J63: Eng.Asb | K63: 1 | L63: 0
A64: A4000 | B64: S9.ZLE.010467.PRJ | C64: PRJ Cam.Marape | D64: TaskDep | E64: 15 | F64: 11/05/26 | H64: 5d/w | I64: 218837 | J64: Eng.Proj | K64: 1 | L64: 0
A65: A4010 | B65: S9.ZLE.010467.EXE | C65: EXE Cam.Marape | D65: TaskDep | E65: =IFERROR(ROUND(501*CRONO_MACRO!$F$4/(CRONO_MACRO!J16/CRONO_MACRO!F16*501*CRONO_MACRO!$D$4),0),0) | F65: 11/05/26 | G65: 12/10/26 | H65: 5d/w | I65: 2325141 | J65: Eq.Campo | K65: =IFERROR(ROUND(CRONO_MACRO!J16*501/CRONO_MACRO!F16,0),0) | L65: 501 | M65: 501lig
A66: A4020 | B66: S9.ZLE.010467.ASB | C66: ASB Cam.Marape | D66: TaskDep | E66: 10 | G66: 12/10/26 | H66: 5d/w | I66: 218837 | J66: Eng.Asb | K66: 1 | L66: 0
A67: A4100 | B67: S9.ZLE.010472.PRJ | C67: PRJ Vila Sapo | D67: TaskDep | E67: 15 | F67: 11/05/26 | H67: 5d/w | I67: 127982 | J67: Eng.Proj | K67: 1 | L67: 0
A68: A4110 | B68: S9.ZLE.010472.EXE | C68: EXE Vila Sapo | D68: TaskDep | E68: =IFERROR(ROUND(293*CRONO_MACRO!$F$4/(CRONO_MACRO!J16/CRONO_MACRO!F16*293*CRONO_MACRO!$D$4),0),0) | F68: 11/05/26 | G68: 12/10/26 | H68: 5d/w | I68: 1359813 | J68: Eq.Campo | K68: =IFERROR(ROUND(CRONO_MACRO!J16*293/CRONO_MACRO!F16,0),0) | L68: 293 | M68: 293lig
A69: A4120 | B69: S9.ZLE.010472.ASB | C69: ASB Vila Sapo | D69: TaskDep | E69: 10 | G69: 12/10/26 | H69: 5d/w | I69: 127982 | J69: Eng.Asb | K69: 1 | L69: 0
A70: A4200 | B70: S9.ZLE.010530.PRJ | C70: PRJ M.Marape(b) | D70: TaskDep | E70: 15 | F70: 11/05/26 | H70: 5d/w | I70: 117062 | J70: Eng.Proj | K70: 1 | L70: 0
A71: A4210 | B71: S9.ZLE.010530.EXE | C71: EXE M.Marape(b) | D71: TaskDep | E71: =IFERROR(ROUND(268*CRONO_MACRO!$F$4/(CRONO_MACRO!J16/CRONO_MACRO!F16*268*CRONO_MACRO!$D$4),0),0) | F71: 11/05/26 | G71: 12/10/26 | H71: 5d/w | I71: 1243788 | J71: Eq.Campo | K71: =IFERROR(ROUND(CRONO_MACRO!J16*268/CRONO_MACRO!F16,0),0) | L71: 268 | M71: 268lig
A72: A4220 | B72: S9.ZLE.010530.ASB | C72: ASB M.Marape(b) | D72: TaskDep | E72: 10 | G72: 12/10/26 | H72: 5d/w | I72: 117062 | J72: Eng.Asb | K72: 1 | L72: 0
A73: A4300 | B73: S9.ZLE.010531.PRJ | C73: PRJ M.Marape(c) | D73: TaskDep | E73: 15 | F73: 11/05/26 | H73: 5d/w | I73: 98717 | J73: Eng.Proj | K73: 1 | L73: 0
A74: A4310 | B74: S9.ZLE.010531.EXE | C74: EXE M.Marape(c) | D74: TaskDep | E74: =IFERROR(ROUND(226*CRONO_MACRO!$F$4/(CRONO_MACRO!J16/CRONO_MACRO!F16*226*CRONO_MACRO!$D$4),0),0) | F74: 11/05/26 | G74: 12/10/26 | H74: 5d/w | I74: 1048866 | J74: Eq.Campo | K74: =IFERROR(ROUND(CRONO_MACRO!J16*226/CRONO_MACRO!F16,0),0) | L74: 226 | M74: 226lig
A75: A4320 | B75: S9.ZLE.010531.ASB | C75: ASB M.Marape(c) | D75: TaskDep | E75: 10 | G75: 12/10/26 | H75: 5d/w | I75: 98717 | J75: Eng.Asb | K75: 1 | L75: 0
A76: A4400 | B76: S9.ZLE.010475.PRJ | C76: PRJ Aloj.StaCasa | D76: TaskDep | E76: 15 | F76: 11/05/26 | H76: 5d/w | I76: 66394 | J76: Eng.Proj | K76: 1 | L76: 0
A77: A4410 | B77: S9.ZLE.010475.EXE | C77: EXE Aloj.StaCasa | D77: TaskDep | E77: =IFERROR(ROUND(152*CRONO_MACRO!$F$4/(CRONO_MACRO!J16/CRONO_MACRO!F16*152*CRONO_MACRO!$D$4),0),0) | F77: 11/05/26 | G77: 12/10/26 | H77: 5d/w | I77: 705432 | J77: Eq.Campo | K77: =IFERROR(ROUND(CRONO_MACRO!J16*152/CRONO_MACRO!F16,0),0) | L77: 152 | M77: 152lig
A78: A4420 | B78: S9.ZLE.010475.ASB | C78: ASB Aloj.StaCasa | D78: TaskDep | E78: 10 | G78: 12/10/26 | H78: 5d/w | I78: 66394 | J78: Eng.Asb | K78: 1 | L78: 0
A79: A4500 | B79: S9.ZLE.010466.PRJ | C79: PRJ Av.M.Fontes | D79: TaskDep | E79: 15 | F79: 11/05/26 | H79: 5d/w | I79: 47611 | J79: Eng.Proj | K79: 1 | L79: 0
A80: A4510 | B80: S9.ZLE.010466.EXE | C80: EXE Av.M.Fontes | D80: TaskDep | E80: =IFERROR(ROUND(109*CRONO_MACRO!$F$4/(CRONO_MACRO!J16/CRONO_MACRO!F16*109*CRONO_MACRO!$D$4),0),0) | F80: 11/05/26 | G80: 12/10/26 | H80: 5d/w | I80: 505869 | J80: Eq.Campo | K80: =IFERROR(ROUND(CRONO_MACRO!J16*109/CRONO_MACRO!F16,0),0) | L80: 109 | M80: 109lig
A81: A4520 | B81: S9.ZLE.010466.ASB | C81: ASB Av.M.Fontes | D81: TaskDep | E81: 10 | G81: 12/10/26 | H81: 5d/w | I81: 47611 | J81: Eng.Asb | K81: 1 | L81: 0
A82: A4600 | B82: S9.ZLE.010470.PRJ | C82: PRJ NSRA Aparecida | D82: TaskDep | E82: 15 | F82: 11/05/26 | H82: 5d/w | I82: 44117 | J82: Eng.Proj | K82: 1 | L82: 0
A83: A4610 | B83: S9.ZLE.010470.EXE | C83: EXE NSRA Aparecida | D83: TaskDep | E83: =IFERROR(ROUND(101*CRONO_MACRO!$F$4/(CRONO_MACRO!J16/CRONO_MACRO!F16*101*CRONO_MACRO!$D$4),0),0) | F83: 11/05/26 | G83: 12/10/26 | H83: 5d/w | I83: 468741 | J83: Eq.Campo | K83: =IFERROR(ROUND(CRONO_MACRO!J16*101/CRONO_MACRO!F16,0),0) | L83: 101 | M83: 101lig
A84: A4620 | B84: S9.ZLE.010470.ASB | C84: ASB NSRA Aparecida | D84: TaskDep | E84: 10 | G84: 12/10/26 | H84: 5d/w | I84: 44117 | J84: Eng.Asb | K84: 1 | L84: 0
A85: A4700 | B85: S9.ZLE.010532.PRJ | C85: PRJ Av.MF Pach | D85: TaskDep | E85: 15 | F85: 11/05/26 | H85: 5d/w | I85: 30576 | J85: Eng.Proj | K85: 1 | L85: 0
A86: A4710 | B86: S9.ZLE.010532.EXE | C86: EXE Av.MF Pach | D86: TaskDep | E86: =IFERROR(ROUND(70*CRONO_MACRO!$F$4/(CRONO_MACRO!J16/CRONO_MACRO!F16*70*CRONO_MACRO!$D$4),0),0) | F86: 11/05/26 | G86: 12/10/26 | H86: 5d/w | I86: 324870 | J86: Eq.Campo | K86: =IFERROR(ROUND(CRONO_MACRO!J16*70/CRONO_MACRO!F16,0),0) | L86: 70 | M86: 70lig
A87: A4720 | B87: S9.ZLE.010532.ASB | C87: ASB Av.MF Pach | D87: TaskDep | E87: 10 | G87: 12/10/26 | H87: 5d/w | I87: 30576 | J87: Eng.Asb | K87: 1 | L87: 0
A88: A4800 | B88: S9.ZLE.010465.PRJ | C88: PRJ Cam.Maria Rosa | D88: TaskDep | E88: 15 | F88: 11/05/26 | H88: 5d/w | I88: 29702 | J88: Eng.Proj | K88: 1 | L88: 0
A89: A4810 | B89: S9.ZLE.010465.EXE | C89: EXE Cam.Maria Rosa | D89: TaskDep | E89: =IFERROR(ROUND(68*CRONO_MACRO!$F$4/(CRONO_MACRO!J16/CRONO_MACRO!F16*68*CRONO_MACRO!$D$4),0),0) | F89: 11/05/26 | G89: 12/10/26 | H89: 5d/w | I89: 315588 | J89: Eq.Campo | K89: =IFERROR(ROUND(CRONO_MACRO!J16*68/CRONO_MACRO!F16,0),0) | L89: 68 | M89: 68lig
A90: A4820 | B90: S9.ZLE.010465.ASB | C90: ASB Cam.Maria Rosa | D90: TaskDep | E90: 10 | G90: 12/10/26 | H90: 5d/w | I90: 29702 | J90: Eng.Asb | K90: 1 | L90: 0
A91: A4900 | B91: S10.CON.010486.PRJ | C91: PRJ M.Z.Menino(b) | D91: TaskDep | E91: 15 | F91: 03/08/26 | H91: 5d/w | I91: 383074 | J91: Eng.Proj | K91: 1 | L91: 0
A92: A4910 | B92: S10.CON.010486.EXE | C92: EXE M.Z.Menino(b) | D92: TaskDep | E92: =IFERROR(ROUND(877*CRONO_MACRO!$F$4/(CRONO_MACRO!J17/CRONO_MACRO!F17*877*CRONO_MACRO!$D$4),0),0) | F92: 03/08/26 | G92: 04/01/27 | H92: 5d/w | I92: 4070157 | J92: Eq.Campo | K92: =IFERROR(ROUND(CRONO_MACRO!J17*877/CRONO_MACRO!F17,0),0) | L92: 877 | M92: 877lig
A93: A4920 | B93: S10.CON.010486.ASB | C93: ASB M.Z.Menino(b) | D93: TaskDep | E93: 10 | G93: 04/01/27 | H93: 5d/w | I93: 383074 | J93: Eng.Asb | K93: 1 | L93: 0
A94: A5000 | B94: S10.CON.010480.PRJ | C94: PRJ Caneleira CDHU | D94: TaskDep | E94: 15 | F94: 03/08/26 | H94: 5d/w | I94: 236309 | J94: Eng.Proj | K94: 1 | L94: 0
A95: A5010 | B95: S10.CON.010480.EXE | C95: EXE Caneleira CDHU | D95: TaskDep | E95: =IFERROR(ROUND(541*CRONO_MACRO!$F$4/(CRONO_MACRO!J17/CRONO_MACRO!F17*541*CRONO_MACRO!$D$4),0),0) | F95: 03/08/26 | G95: 04/01/27 | H95: 5d/w | I95: 2510781 | J95: Eq.Campo | K95: =IFERROR(ROUND(CRONO_MACRO!J17*541/CRONO_MACRO!F17,0),0) | L95: 541 | M95: 541lig
A96: A5020 | B96: S10.CON.010480.ASB | C96: ASB Caneleira CDHU | D96: TaskDep | E96: 10 | G96: 04/01/27 | H96: 5d/w | I96: 236309 | J96: Eng.Asb | K96: 1 | L96: 0
A97: A5100 | B97: S10.CON.010485.PRJ | C97: PRJ M.Z.Menino(a) | D97: TaskDep | E97: 15 | F97: 03/08/26 | H97: 5d/w | I97: 215779 | J97: Eng.Proj | K97: 1 | L97: 0
A98: A5110 | B98: S10.CON.010485.EXE | C98: EXE M.Z.Menino(a) | D98: TaskDep | E98: =IFERROR(ROUND(494*CRONO_MACRO!$F$4/(CRONO_MACRO!J17/CRONO_MACRO!F17*494*CRONO_MACRO!$D$4),0),0) | F98: 03/08/26 | G98: 04/01/27 | H98: 5d/w | I98: 2292654 | J98: Eq.Campo | K98: =IFERROR(ROUND(CRONO_MACRO!J17*494/CRONO_MACRO!F17,0),0) | L98: 494 | M98: 494lig
A99: A5120 | B99: S10.CON.010485.ASB | C99: ASB M.Z.Menino(a) | D99: TaskDep | E99: 10 | G99: 04/01/27 | H99: 5d/w | I99: 215779 | J99: Eng.Asb | K99: 1 | L99: 0
A100: A5200 | B100: S10.CON.010490.PRJ | C100: PRJ Av.Bandeirantes | D100: TaskDep | E100: 15 | F100: 03/08/26 | H100: 5d/w | I100: 125362 | J100: Eng.Proj | K100: 1 | L100: 0
A101: A5210 | B101: S10.CON.010490.EXE | C101: EXE Av.Bandeirantes | D101: TaskDep | E101: =IFERROR(ROUND(287*CRONO_MACRO!$F$4/(CRONO_MACRO!J17/CRONO_MACRO!F17*287*CRONO_MACRO!$D$4),0),0) | F101: 03/08/26 | G101: 04/01/27 | H101: 5d/w | I101: 1331967 | J101: Eq.Campo | K101: =IFERROR(ROUND(CRONO_MACRO!J17*287/CRONO_MACRO!F17,0),0) | L101: 287 | M101: 287lig
...

Sheet N07_NOROESTE
A1: N07 — Zona Noroeste | 2.996 lig | M/Lig=2
A2: TAG | B2: NOME | C2: TIPO | D2: LA | E2: LE | F2: LIG | G2: EQ | H2: PROD | I2: Abr | J2: Mai | K2: Jun | L2: Jul | M2: Ago | N2: Set | O2: Out | P2: Nov | Q2: Dez | R2: Jan/27 | S2: PLAN | T2: SALDO | U2: CUSTO | V2: PESS
A3: 010524 | B3: Vila Alemoa | C3: UD | D3: 461 | E3: 946 | F3: 1407 | G3: 5 | H3: 6 | I3: 0 | J3: 0 | K3: 0 | L3: 0 | M3: 0 | N3: 0 | O3: 0 | P3: 0 | Q3: 0 | R3: 0 | S3: 0 | T3: 1407 | U3: 0 | V3: 42.5
A4: 010518 | B4: Ilheu Baixo | C4: UD | D4: 73 | E4: 603 | F4: 676 | G4: 2 | H4: 6 | I4: 0 | J4: 0 | K4: 0 | L4: 0 | M4: 0 | N4: 0 | O4: 0 | P4: 0 | Q4: 0 | R4: 0 | S4: 0 | T4: 676 | U4: 0 | V4: 17
A5: 010522 | B5: NSRA Fatima | C5: UD | D5: 91 | E5: 170 | F5: 261 | G5: 1 | H5: 6 | I5: 0 | J5: 0 | K5: 0 | L5: 0 | M5: 0 | N5: 0 | O5: 0 | P5: 0 | Q5: 0 | R5: 0 | S5: 0 | T5: 261 | U5: 0 | V5: 8.5
A6: 010526 | B6: Vila Telma | C6: UD | D6: 48 | E6: 143 | F6: 191 | G6: 1 | H6: 6 | I6: 0 | J6: 0 | K6: 0 | L6: 0 | M6: 0 | N6: 0 | O6: 0 | P6: 0 | Q6: 0 | R6: 0 | S6: 0 | T6: 191 | U6: 0 | V6: 8.5
A7: 010525 | B7: V.Alemoa Rem | C7: UD | D7: 50 | E7: 50 | F7: 100 | G7: 1 | H7: 6 | I7: 0 | J7: 0 | K7: 0 | L7: 0 | M7: 0 | N7: 0 | O7: 0 | P7: 0 | Q7: 0 | R7: 0 | S7: 0 | T7: 100 | U7: 0 | V7: 8.5
A8: 010521 | B8: Lote L Chico | C8: UD | D8: 48 | E8: 48 | F8: 96 | G8: 1 | H8: 6 | I8: 0 | J8: 0 | K8: 0 | L8: 0 | M8: 0 | N8: 0 | O8: 0 | P8: 0 | Q8: 0 | R8: 0 | S8: 0 | T8: 96 | U8: 0 | V8: 8.5
A9: 010523 | B9: V.Alemoa COHAB | C9: UD | D9: 39 | E9: 39 | F9: 78 | G9: 1 | H9: 6 | I9: 0 | J9: 0 | K9: 0 | L9: 0 | M9: 0 | N9: 0 | O9: 0 | P9: 0 | Q9: 0 | R9: 0 | S9: 0 | T9: 78 | U9: 0 | V9: 8.5
A10: 010520 | B10: Joao Barro | C10: UD | D10: 29 | E10: 58 | F10: 87 | G10: 1 | H10: 6 | I10: 0 | J10: 0 | K10: 0 | L10: 0 | M10: 0 | N10: 0 | O10: 0 | P10: 0 | Q10: 0 | R10: 0 | S10: 0 | T10: 87 | U10: 0 | V10: 8.5
A11: 010515 | B11: Saboo II | C11: UD | D11: 37 | E11: 49 | F11: 86 | G11: 1 | H11: 6 | I11: 0 | J11: 0 | K11: 0 | L11: 0 | M11: 0 | N11: 0 | O11: 0 | P11: 0 | Q11: 0 | R11: 0 | S11: 0 | T11: 86 | U11: 0 | V11: 8.5
A12: 010517 | B12: Fav.Butanta | C12: UD | D12: 7 | E12: 7 | F12: 14 | G12: 1 | H12: 6 | I12: 0 | J12: 0 | K12: 0 | L12: 0 | M12: 0 | N12: 0 | O12: 0 | P12: 0 | Q12: 0 | R12: 0 | S12: 0 | T12: 14 | U12: 0 | V12: 8.5
B13: TOTAL | D13: 883 | E13: 2113 | F13: 2996 | G13: 15 | I13: 0 | J13: 0 | K13: 0 | L13: 0 | M13: 0 | N13: 0 | O13: 0 | P13: 0 | Q13: 0 | R13: 0 | S13: 0 | T13: 2996 | U13: 0 | V13: 127.5
A14: MATERIAL
A15: Material | B15: Fator | C15: Total | D15: Abr | E15: Mai | F15: Jun | G15: Jul | H15: Ago | I15: Set | J15: Out | K15: Nov | L15: Dez | M15: Jan/27
A16: Tubo PVC ESG | B16: 0.55 | C16: 0 | D16: 0 | E16: 0 | F16: 0 | G16: 0 | H16: 0 | I16: 0 | J16: 0 | K16: 0 | L16: 0 | M16: 0
A17: Tubo PEAD Agua | B17: 0.65 | C17: 0 | D17: 0 | E17: 0 | F17: 0 | G17: 0 | H17: 0 | I17: 0 | J17: 0 | K17: 0 | L17: 0 | M17: 0
A18: Areia | B18: 0.27 | C18: 0 | D18: 0 | E18: 0 | F18: 0 | G18: 0 | H18: 0 | I18: 0 | J18: 0 | K18: 0 | L18: 0 | M18: 0
A19: Brita | B19: 0.12 | C19: 0 | D19: 0 | E19: 0 | F19: 0 | G19: 0 | H19: 0 | I19: 0 | J19: 0 | K19: 0 | L19: 0 | M19: 0
A20: Concreto | B20: 0.1 | C20: 0 | D20: 0 | E20: 0 | F20: 0 | G20: 0 | H20: 0 | I20: 0 | J20: 0 | K20: 0 | L20: 0 | M20: 0
A21: CBUQ | B21: 0.12 | C21: 0 | D21: 0 | E21: 0 | F21: 0 | G21: 0 | H21: 0 | I21: 0 | J21: 0 | K21: 0 | L21: 0 | M21: 0

Sheet N08_V_PROGRESSO
A1: N08 — Vila Progresso | 1.865 lig
A2: TAG | B2: NOME | C2: TIPO | D2: LA | E2: LE | F2: LIG | G2: EQ | H2: PROD | I2: Abr | J2: Mai | K2: Jun | L2: Jul | M2: Ago | N2: Set | O2: Out | P2: Nov | Q2: Dez | R2: Jan/27 | S2: PLAN | T2: SALDO | U2: CUSTO | V2: PESS
A3: 010502 | B3: R Um N.Cintra | C3: UM | D3: 246 | E3: 450 | F3: 696 | G3: 4 | H3: 3 | I3: 0 | J3: 0 | K3: 0 | L3: 0 | M3: 0 | N3: 0 | O3: 0 | P3: 0 | Q3: 0 | R3: 0 | S3: 0 | T3: 696 | U3: 0 | V3: 34
A4: 010507 | B4: V.Progresso | C4: UM | D4: 71 | E4: 537 | F4: 608 | G4: 3 | H4: 3 | I4: 0 | J4: 0 | K4: 0 | L4: 0 | M4: 0 | N4: 0 | O4: 0 | P4: 0 | Q4: 0 | R4: 0 | S4: 0 | T4: 608 | U4: 0 | V4: 25.5
A5: 010503 | B5: Encosta Saboo | C5: UM | D5: 140 | E5: 140 | F5: 280 | G5: 2 | H5: 3 | I5: 0 | J5: 0 | K5: 0 | L5: 0 | M5: 0 | N5: 0 | O5: 0 | P5: 0 | Q5: 0 | R5: 0 | S5: 0 | T5: 280 | U5: 0 | V5: 17
A6: 010504 | B6: Menino Jesus | C6: UM | D6: 79 | E6: 79 | F6: 158 | G6: 1 | H6: 3 | I6: 0 | J6: 0 | K6: 0 | L6: 0 | M6: 0 | N6: 0 | O6: 0 | P6: 0 | Q6: 0 | R6: 0 | S6: 0 | T6: 158 | U6: 0 | V6: 8.5
A7: 010506 | B7: Rua Nove | C7: UM | D7: 27 | E7: 27 | F7: 54 | G7: 1 | H7: 3 | I7: 0 | J7: 0 | K7: 0 | L7: 0 | M7: 0 | N7: 0 | O7: 0 | P7: 0 | Q7: 0 | R7: 0 | S7: 0 | T7: 54 | U7: 0 | V7: 8.5
A8: 010509 | B8: R.M.Mercedes | C8: UM | D8: 11 | E8: 36 | F8: 47 | G8: 1 | H8: 3 | I8: 0 | J8: 0 | K8: 0 | L8: 0 | M8: 0 | N8: 0 | O8: 0 | P8: 0 | Q8: 0 | R8: 0 | S8: 0 | T8: 47 | U8: 0 | V8: 8.5
A9: 010508 | B9: V.Telma Cima | C9: UM | D9: 11 | E9: 11 | F9: 22 | G9: 1 | H9: 3 | I9: 0 | J9: 0 | K9: 0 | L9: 0 | M9: 0 | N9: 0 | O9: 0 | P9: 0 | Q9: 0 | R9: 0 | S9: 0 | T9: 22 | U9: 0 | V9: 8.5
B10: TOTAL | D10: 585 | E10: 1280 | F10: 1865 | G10: 13 | I10: 0 | J10: 0 | K10: 0 | L10: 0 | M10: 0 | N10: 0 | O10: 0 | P10: 0 | Q10: 0 | R10: 0 | S10: 0 | T10: 1865 | U10: 0 | V10: 110.5
A11: MATERIAL
A12: Material | B12: Fator | C12: Total | D12: Abr | E12: Mai | F12: Jun | G12: Jul | H12: Ago | I12: Set | J12: Out | K12: Nov | L12: Dez | M12: Jan/27
A13: Tubo PVC ESG | B13: 0.55 | C13: 0 | D13: 0 | E13: 0 | F13: 0 | G13: 0 | H13: 0 | I13: 0 | J13: 0 | K13: 0 | L13: 0 | M13: 0
A14: Tubo PEAD Agua | B14: 0.65 | C14: 0 | D14: 0 | E14: 0 | F14: 0 | G14: 0 | H14: 0 | I14: 0 | J14: 0 | K14: 0 | L14: 0 | M14: 0
A15: Areia | B15: 0.27 | C15: 0 | D15: 0 | E15: 0 | F15: 0 | G15: 0 | H15: 0 | I15: 0 | J15: 0 | K15: 0 | L15: 0 | M15: 0
A16: Brita | B16: 0.12 | C16: 0 | D16: 0 | E16: 0 | F16: 0 | G16: 0 | H16: 0 | I16: 0 | J16: 0 | K16: 0 | L16: 0 | M16: 0
A17: Concreto | B17: 0.1 | C17: 0 | D17: 0 | E17: 0 | F17: 0 | G17: 0 | H17: 0 | I17: 0 | J17: 0 | K17: 0 | L17: 0 | M17: 0
A18: CBUQ | B18: 0.12 | C18: 0 | D18: 0 | E18: 0 | F18: 0 | G18: 0 | H18: 0 | I18: 0 | J18: 0 | K18: 0 | L18: 0 | M18: 0

Sheet N09_Z_LESTE
A1: N09 — Zona Leste | 1.401 lig
A2: TAG | B2: NOME | C2: TIPO | D2: LA | E2: LE | F2: LIG | G2: EQ | H2: PROD | I2: Abr | J2: Mai | K2: Jun | L2: Jul | M2: Ago | N2: Set | O2: Out | P2: Nov | Q2: Dez | R2: Jan/27 | S2: PLAN | T2: SALDO | U2: CUSTO | V2: PESS
A3: 010473 | B3: Clovis Galvao | C3: UM | D3: 172 | E3: 504 | F3: 676 | G3: 5 | H3: 3 | I3: 0 | J3: 0 | K3: 0 | L3: 0 | M3: 0 | N3: 0 | O3: 0 | P3: 0 | Q3: 0 | R3: 0 | S3: 0 | T3: 676 | U3: 0 | V3: 42.5
A4: 010468 | B4: Div.Tiro Naval | C4: MO | D4: 217 | E4: 519 | F4: 736 | G4: 5 | H4: 2.3 | I4: 0 | J4: 0 | K4: 0 | L4: 0 | M4: 0 | N4: 0 | O4: 0 | P4: 0 | Q4: 0 | R4: 0 | S4: 0 | T4: 736 | U4: 0 | V4: 42.5
A5: 010474 | B5: M.Marape(a) | C5: MO | D5: 209 | E5: 331 | F5: 540 | G5: 4 | H5: 2.3 | I5: 0 | J5: 0 | K5: 0 | L5: 0 | M5: 0 | N5: 0 | O5: 0 | P5: 0 | Q5: 0 | R5: 0 | S5: 0 | T5: 540 | U5: 0 | V5: 34
A6: 010467 | B6: Cam.Marape | C6: MO | D6: 152 | E6: 349 | F6: 501 | G6: 4 | H6: 2.3 | I6: 0 | J6: 0 | K6: 0 | L6: 0 | M6: 0 | N6: 0 | O6: 0 | P6: 0 | Q6: 0 | R6: 0 | S6: 0 | T6: 501 | U6: 0 | V6: 34
A7: 010472 | B7: Vila Sapo | C7: UM | D7: 131 | E7: 162 | F7: 293 | G7: 2 | H7: 3 | I7: 0 | J7: 0 | K7: 0 | L7: 0 | M7: 0 | N7: 0 | O7: 0 | P7: 0 | Q7: 0 | R7: 0 | S7: 0 | T7: 293 | U7: 0 | V7: 17
A8: 010530 | B8: M.Marape(b) | C8: MO | D8: 104 | E8: 164 | F8: 268 | G8: 2 | H8: 2.3 | I8: 0 | J8: 0 | K8: 0 | L8: 0 | M8: 0 | N8: 0 | O8: 0 | P8: 0 | Q8: 0 | R8: 0 | S8: 0 | T8: 268 | U8: 0 | V8: 17
A9: 010531 | B9: M.Marape(c) | C9: MO | D9: 88 | E9: 138 | F9: 226 | G9: 2 | H9: 2.3 | I9: 0 | J9: 0 | K9: 0 | L9: 0 | M9: 0 | N9: 0 | O9: 0 | P9: 0 | Q9: 0 | R9: 0 | S9: 0 | T9: 226 | U9: 0 | V9: 17
A10: 010475 | B10: Aloj.StaCasa | C10: UM | D10: 76 | E10: 76 | F10: 152 | G10: 1 | H10: 3 | I10: 0 | J10: 0 | K10: 0 | L10: 0 | M10: 0 | N10: 0 | O10: 0 | P10: 0 | Q10: 0 | R10: 0 | S10: 0 | T10: 152 | U10: 0 | V10: 8.5
A11: 010466 | B11: Av.M.Fontes | C11: UM | D11: 45 | E11: 64 | F11: 109 | G11: 1 | H11: 3 | I11: 0 | J11: 0 | K11: 0 | L11: 0 | M11: 0 | N11: 0 | O11: 0 | P11: 0 | Q11: 0 | R11: 0 | S11: 0 | T11: 109 | U11: 0 | V11: 8.5
A12: 010470 | B12: NSRA Aparecida | C12: UM | D12: 27 | E12: 74 | F12: 101 | G12: 1 | H12: 3 | I12: 0 | J12: 0 | K12: 0 | L12: 0 | M12: 0 | N12: 0 | O12: 0 | P12: 0 | Q12: 0 | R12: 0 | S12: 0 | T12: 101 | U12: 0 | V12: 8.5
A13: 010532 | B13: Av.MF Pach | C13: UM | D13: 29 | E13: 41 | F13: 70 | G13: 1 | H13: 3 | I13: 0 | J13: 0 | K13: 0 | L13: 0 | M13: 0 | N13: 0 | O13: 0 | P13: 0 | Q13: 0 | R13: 0 | S13: 0 | T13: 70 | U13: 0 | V13: 8.5
A14: 010465 | B14: Cam.Maria Rosa | C14: MO | D14: 34 | E14: 34 | F14: 68 | G14: 1 | H14: 2.3 | I14: 0 | J14: 0 | K14: 0 | L14: 0 | M14: 0 | N14: 0 | O14: 0 | P14: 0 | Q14: 0 | R14: 0 | S14: 0 | T14: 68 | U14: 0 | V14: 8.5
B15: TOTAL | D15: 1284 | E15: 2456 | F15: 3740 | G15: 29 | I15: 0 | J15: 0 | K15: 0 | L15: 0 | M15: 0 | N15: 0 | O15: 0 | P15: 0 | Q15: 0 | R15: 0 | S15: 0 | T15: 3740 | U15: 0 | V15: 246.5
A16: MATERIAL
A17: Material | B17: Fator | C17: Total | D17: Abr | E17: Mai | F17: Jun | G17: Jul | H17: Ago | I17: Set | J17: Out | K17: Nov | L17: Dez | M17: Jan/27
A18: Tubo PVC ESG | B18: 0.55 | C18: 0 | D18: 0 | E18: 0 | F18: 0 | G18: 0 | H18: 0 | I18: 0 | J18: 0 | K18: 0 | L18: 0 | M18: 0
A19: Tubo PEAD Agua | B19: 0.65 | C19: 0 | D19: 0 | E19: 0 | F19: 0 | G19: 0 | H19: 0 | I19: 0 | J19: 0 | K19: 0 | L19: 0 | M19: 0
A20: Areia | B20: 0.27 | C20: 0 | D20: 0 | E20: 0 | F20: 0 | G20: 0 | H20: 0 | I20: 0 | J20: 0 | K20: 0 | L20: 0 | M20: 0
A21: Brita | B21: 0.12 | C21: 0 | D21: 0 | E21: 0 | F21: 0 | G21: 0 | H21: 0 | I21: 0 | J21: 0 | K21: 0 | L21: 0 | M21: 0
A22: Concreto | B22: 0.1 | C22: 0 | D22: 0 | E22: 0 | F22: 0 | G22: 0 | H22: 0 | I22: 0 | J22: 0 | K22: 0 | L22: 0 | M22: 0
A23: CBUQ | B23: 0.12 | C23: 0 | D23: 0 | E23: 0 | F23: 0 | G23: 0 | H23: 0 | I23: 0 | J23: 0 | K23: 0 | L23: 0 | M23: 0

Sheet N10_CONJUNTO
A1: N10 — Conjunto | 1.672 lig
A2: TAG | B2: NOME | C2: TIPO | D2: LA | E2: LE | F2: LIG | G2: EQ | H2: PROD | I2: Abr | J2: Mai | K2: Jun | L2: Jul | M2: Ago | N2: Set | O2: Out | P2: Nov | Q2: Dez | R2: Jan/27 | S2: PLAN | T2: SALDO | U2: CUSTO | V2: PESS
A3: 010486 | B3: M.Z.Menino(b) | C3: MO | D3: 195 | E3: 682 | F3: 877 | G3: 5 | H3: 2.3 | I3: 0 | J3: 0 | K3: 0 | L3: 0 | M3: 0 | N3: 0 | O3: 0 | P3: 0 | Q3: 0 | R3: 0 | S3: 0 | T3: 877 | U3: 0 | V3: 42.5
A4: 010480 | B4: Caneleira CDHU | C4: UR | D4: 264 | E4: 277 | F4: 541 | G4: 3 | H4: 4 | I4: 0 | J4: 0 | K4: 0 | L4: 0 | M4: 0 | N4: 0 | O4: 0 | P4: 0 | Q4: 0 | R4: 0 | S4: 0 | T4: 541 | U4: 0 | V4: 25.5
A5: 010485 | B5: M.Z.Menino(a) | C5: MO | D5: 194 | E5: 300 | F5: 494 | G5: 3 | H5: 2.3 | I5: 0 | J5: 0 | K5: 0 | L5: 0 | M5: 0 | N5: 0 | O5: 0 | P5: 0 | Q5: 0 | R5: 0 | S5: 0 | T5: 494 | U5: 0 | V5: 25.5
A6: 010490 | B6: Av.Bandeirantes | C6: UM | D6: 90 | E6: 197 | F6: 287 | G6: 2 | H6: 3 | I6: 0 | J6: 0 | K6: 0 | L6: 0 | M6: 0 | N6: 0 | O6: 0 | P6: 0 | Q6: 0 | R6: 0 | S6: 0 | T6: 287 | U6: 0 | V6: 17
A7: 010481 | B7: V.Ayrton Senna | C7: UR | D7: 70 | E7: 169 | F7: 239 | G7: 1 | H7: 4 | I7: 0 | J7: 0 | K7: 0 | L7: 0 | M7: 0 | N7: 0 | O7: 0 | P7: 0 | Q7: 0 | R7: 0 | S7: 0 | T7: 239 | U7: 0 | V7: 8.5
A8: 010484 | B8: V.Esperanca | C8: UR | D8: 52 | E8: 168 | F8: 220 | G8: 1 | H8: 4 | I8: 0 | J8: 0 | K8: 0 | L8: 0 | M8: 0 | N8: 0 | O8: 0 | P8: 0 | Q8: 0 | R8: 0 | S8: 0 | T8: 220 | U8: 0 | V8: 8.5
A9: 010494 | B9: Av.W.Leao | C9: UM | D9: 39 | E9: 64 | F9: 103 | G9: 1 | H9: 3 | I9: 0 | J9: 0 | K9: 0 | L9: 0 | M9: 0 | N9: 0 | O9: 0 | P9: 0 | Q9: 0 | R9: 0 | S9: 0 | T9: 103 | U9: 0 | V9: 8.5
A10: 010492 | B10: R.S.Geraldo | C10: UM | D10: 46 | E10: 46 | F10: 92 | G10: 1 | H10: 3 | I10: 0 | J10: 0 | K10: 0 | L10: 0 | M10: 0 | N10: 0 | O10: 0 | P10: 0 | Q10: 0 | R10: 0 | S10: 0 | T10: 92 | U10: 0 | V10: 8.5
A11: 010476 | B11: Fav.Piratininga | C11: UR | D11: 33 | E11: 33 | F11: 66 | G11: 1 | H11: 4 | I11: 0 | J11: 0 | K11: 0 | L11: 0 | M11: 0 | N11: 0 | O11: 0 | P11: 0 | Q11: 0 | R11: 0 | S11: 0 | T11: 66 | U11: 0 | V11: 8.5
A12: 010493 | B12: S.Bento II | C12: UM | D12: 27 | E12: 27 | F12: 54 | G12: 1 | H12: 3 | I12: 0 | J12: 0 | K12: 0 | L12: 0 | M12: 0 | N12: 0 | O12: 0 | P12: 0 | Q12: 0 | R12: 0 | S12: 0 | T12: 54 | U12: 0 | V12: 8.5
A13: 010495 | B13: Trav.Sta Casa | C13: UM | D13: 22 | E13: 22 | F13: 44 | G13: 1 | H13: 3 | I13: 0 | J13: 0 | K13: 0 | L13: 0 | M13: 0 | N13: 0 | O13: 0 | P13: 0 | Q13: 0 | R13: 0 | S13: 0 | T13: 44 | U13: 0 | V13: 8.5
A14: 010491 | B14: Av.Getulio | C14: UM | D14: 13 | E14: 13 | F14: 26 | G14: 1 | H14: 3 | I14: 0 | J14: 0 | K14: 0 | L14: 0 | M14: 0 | N14: 0 | O14: 0 | P14: 0 | Q14: 0 | R14: 0 | S14: 0 | T14: 26 | U14: 0 | V14: 8.5
B15: TOTAL | D15: 1045 | E15: 1998 | F15: 3043 | G15: 21 | I15: 0 | J15: 0 | K15: 0 | L15: 0 | M15: 0 | N15: 0 | O15: 0 | P15: 0 | Q15: 0 | R15: 0 | S15: 0 | T15: 3043 | U15: 0 | V15: 178.5
A16: MATERIAL
A17: Material | B17: Fator | C17: Total | D17: Abr | E17: Mai | F17: Jun | G17: Jul | H17: Ago | I17: Set | J17: Out | K17: Nov | L17: Dez | M17: Jan/27
A18: Tubo PVC ESG | B18: 0.55 | C18: 0 | D18: 0 | E18: 0 | F18: 0 | G18: 0 | H18: 0 | I18: 0 | J18: 0 | K18: 0 | L18: 0 | M18: 0
A19: Tubo PEAD Agua | B19: 0.65 | C19: 0 | D19: 0 | E19: 0 | F19: 0 | G19: 0 | H19: 0 | I19: 0 | J19: 0 | K19: 0 | L19: 0 | M19: 0
A20: Areia | B20: 0.27 | C20: 0 | D20: 0 | E20: 0 | F20: 0 | G20: 0 | H20: 0 | I20: 0 | J20: 0 | K20: 0 | L20: 0 | M20: 0
A21: Brita | B21: 0.12 | C21: 0 | D21: 0 | E21: 0 | F21: 0 | G21: 0 | H21: 0 | I21: 0 | J21: 0 | K21: 0 | L21: 0 | M21: 0
A22: Concreto | B22: 0.1 | C22: 0 | D22: 0 | E22: 0 | F22: 0 | G22: 0 | H22: 0 | I22: 0 | J22: 0 | K22: 0 | L22: 0 | M22: 0
A23: CBUQ | B23: 0.12 | C23: 0 | D23: 0 | E23: 0 | F23: 0 | G23: 0 | H23: 0 | I23: 0 | J23: 0 | K23: 0 | L23: 0 | M23: 0

Sheet N11_ALAGADO
A1: N11 — Alagado/Dique | 1.862 lig
A2: TAG | B2: NOME | C2: TIPO | D2: LA | E2: LE | F2: LIG | G2: EQ | H2: PROD | I2: Abr | J2: Mai | K2: Jun | L2: Jul | M2: Ago | N2: Set | O2: Out | P2: Nov | Q2: Dez | R2: Jan/27 | S2: PLAN | T2: SALDO | U2: CUSTO | V2: PESS
A3: 010519 | B3: Dique V.Gilda | C3: AL | D3: 634 | E3: 811 | F3: 1445 | G3: 8 | H3: 2.5 | I3: 0 | J3: 0 | K3: 0 | L3: 0 | M3: 0 | N3: 0 | O3: 0 | P3: 0 | Q3: 0 | R3: 0 | S3: 0 | T3: 1445 | U3: 0 | V3: 68
A4: 010497 | B4: Reg.AG Dique | C4: AL | D4: 0 | E4: 408 | F4: 408 | G4: 2 | H4: 2.5 | I4: 0 | J4: 0 | K4: 0 | L4: 0 | M4: 0 | N4: 0 | O4: 0 | P4: 0 | Q4: 0 | R4: 0 | S4: 0 | T4: 408 | U4: 0 | V4: 17
A5: 010516 | B5: Dique VG(c) | C5: AL | D5: 3 | E5: 4 | F5: 7 | G5: 1 | H5: 2.5 | I5: 0 | J5: 0 | K5: 0 | L5: 0 | M5: 0 | N5: 0 | O5: 0 | P5: 0 | Q5: 0 | R5: 0 | S5: 0 | T5: 7 | U5: 0 | V5: 8.5
A6: 010499 | B6: Dique S.Manoel | C6: AL | D6: 1 | E6: 1 | F6: 2 | G6: 1 | H6: 2.5 | I6: 0 | J6: 0 | K6: 0 | L6: 0 | M6: 0 | N6: 0 | O6: 0 | P6: 0 | Q6: 0 | R6: 0 | S6: 0 | T6: 2 | U6: 0 | V6: 8.5
B7: TOTAL | D7: 638 | E7: 1224 | F7: 1862 | G7: 12 | I7: 0 | J7: 0 | K7: 0 | L7: 0 | M7: 0 | N7: 0 | O7: 0 | P7: 0 | Q7: 0 | R7: 0 | S7: 0 | T7: 1862 | U7: 0 | V7: 102
A8: MATERIAL
A9: Material | B9: Fator | C9: Total | D9: Abr | E9: Mai | F9: Jun | G9: Jul | H9: Ago | I9: Set | J9: Out | K9: Nov | L9: Dez | M9: Jan/27
A10: Tubo PVC ESG | B10: 0.55 | C10: 0 | D10: 0 | E10: 0 | F10: 0 | G10: 0 | H10: 0 | I10: 0 | J10: 0 | K10: 0 | L10: 0 | M10: 0
A11: Tubo PEAD Agua | B11: 0.65 | C11: 0 | D11: 0 | E11: 0 | F11: 0 | G11: 0 | H11: 0 | I11: 0 | J11: 0 | K11: 0 | L11: 0 | M11: 0
A12: Areia | B12: 0.27 | C12: 0 | D12: 0 | E12: 0 | F12: 0 | G12: 0 | H12: 0 | I12: 0 | J12: 0 | K12: 0 | L12: 0 | M12: 0
A13: Brita | B13: 0.12 | C13: 0 | D13: 0 | E13: 0 | F13: 0 | G13: 0 | H13: 0 | I13: 0 | J13: 0 | K13: 0 | L13: 0 | M13: 0
A14: Concreto | B14: 0.1 | C14: 0 | D14: 0 | E14: 0 | F14: 0 | G14: 0 | H14: 0 | I14: 0 | J14: 0 | K14: 0 | L14: 0 | M14: 0
A15: CBUQ | B15: 0.12 | C15: 0 | D15: 0 | E15: 0 | F15: 0 | G15: 0 | H15: 0 | I15: 0 | J15: 0 | K15: 0 | L15: 0 | M15: 0

Sheet N12_MONTANHOSO
A1: N12 — Montanhoso | 10.511 lig
A2: TAG | B2: NOME | C2: TIPO | D2: LA | E2: LE | F2: LIG | G2: EQ | H2: PROD | I2: Abr | J2: Mai | K2: Jun | L2: Jul | M2: Ago | N2: Set | O2: Out | P2: Nov | Q2: Dez | R2: Jan/27 | S2: PLAN | T2: SALDO | U2: CUSTO | V2: PESS
A3: 010460 | B3: Pacheco AP | C3: MO | D3: 239 | E3: 687 | F3: 926 | G3: 1 | H3: 2.3 | I3: 0 | J3: 0 | K3: 0 | L3: 0 | M3: 0 | N3: 0 | O3: 0 | P3: 0 | Q3: 0 | R3: 0 | S3: 0 | T3: 926 | U3: 0 | V3: 8.5
A4: 010455 | B4: Sta Maria | C4: MO | D4: 237 | E4: 388 | F4: 625 | G4: 1 | H4: 2.3 | I4: 0 | J4: 0 | K4: 0 | L4: 0 | M4: 0 | N4: 0 | O4: 0 | P4: 0 | Q4: 0 | R4: 0 | S4: 0 | T4: 625 | U4: 0 | V4: 8.5
A5: 010457 | B5: S.Bento I | C5: MO | D5: 632 | E5: 1 | F5: 633 | G5: 1 | H5: 2.3 | I5: 0 | J5: 0 | K5: 0 | L5: 0 | M5: 0 | N5: 0 | O5: 0 | P5: 0 | Q5: 0 | R5: 0 | S5: 0 | T5: 633 | U5: 0 | V5: 8.5
A6: 010452 | B6: Lomba Penha | C6: MO | D6: 567 | E6: 1 | F6: 568 | G6: 1 | H6: 2.3 | I6: 0 | J6: 0 | K6: 0 | L6: 0 | M6: 0 | N6: 0 | O6: 0 | P6: 0 | Q6: 0 | R6: 0 | S6: 0 | T6: 568 | U6: 0 | V6: 8.5
A7: 010449 | B7: ZEIS S.Bento | C7: MO | D7: 199 | E7: 344 | F7: 543 | G7: 1 | H7: 2.3 | I7: 0 | J7: 0 | K7: 0 | L7: 0 | M7: 0 | N7: 0 | O7: 0 | P7: 0 | Q7: 0 | R7: 0 | S7: 0 | T7: 543 | U7: 0 | V7: 8.5
A8: 010464 | B8: GRusso-JGS | C8: MO | D8: 235 | E8: 473 | F8: 708 | G8: 1 | H8: 2.3 | I8: 0 | J8: 0 | K8: 0 | L8: 0 | M8: 0 | N8: 0 | O8: 0 | P8: 0 | Q8: 0 | R8: 0 | S8: 0 | T8: 708 | U8: 0 | V8: 8.5
A9: 010458 | B9: Torquato Dias | C9: MO | D9: 43 | E9: 342 | F9: 385 | G9: 1 | H9: 2.3 | I9: 0 | J9: 0 | K9: 0 | L9: 0 | M9: 0 | N9: 0 | O9: 0 | P9: 0 | Q9: 0 | R9: 0 | S9: 0 | T9: 385 | U9: 0 | V9: 8.5
A10: 010527 | B10: Area Tunel | C10: MO | D10: 95 | E10: 239 | F10: 334 | G10: 1 | H10: 2.3 | I10: 0 | J10: 0 | K10: 0 | L10: 0 | M10: 0 | N10: 0 | O10: 0 | P10: 0 | Q10: 0 | R10: 0 | S10: 0 | T10: 334 | U10: 0 | V10: 8.5
A11: 010489 | B11: M.Serrat II | C11: MO | D11: 136 | E11: 136 | F11: 272 | G11: 1 | H11: 2.3 | I11: 0 | J11: 0 | K11: 0 | L11: 0 | M11: 0 | N11: 0 | O11: 0 | P11: 0 | Q11: 0 | R11: 0 | S11: 0 | T11: 272 | U11: 0 | V11: 8.5
A12: 010461 | B12: V.Cesar | C12: MO | D12: 125 | E12: 125 | F12: 250 | G12: 1 | H12: 2.3 | I12: 0 | J12: 0 | K12: 0 | L12: 0 | M12: 0 | N12: 0 | O12: 0 | P12: 0 | Q12: 0 | R12: 0 | S12: 0 | T12: 250 | U12: 0 | V12: 8.5
A13: 010453 | B13: N.Cintra I | C13: MO | D13: 30 | E13: 195 | F13: 225 | G13: 1 | H13: 2.3 | I13: 0 | J13: 0 | K13: 0 | L13: 0 | M13: 0 | N13: 0 | O13: 0 | P13: 0 | Q13: 0 | R13: 0 | S13: 0 | T13: 225 | U13: 0 | V13: 8.5
A14: 010528 | B14: Av.Pref.Dr.A | C14: MO | D14: 108 | E14: 108 | F14: 216 | G14: 1 | H14: 2.3 | I14: 0 | J14: 0 | K14: 0 | L14: 0 | M14: 0 | N14: 0 | O14: 0 | P14: 0 | Q14: 0 | R14: 0 | S14: 0 | T14: 216 | U14: 0 | V14: 8.5
... A25: 010448 | B25: Caneleira III | C25: MO | D25: 1 | E25: 1 | F25: 2 | G25: 1 | H25: 2.3 | I25: 0 | J25: 0 | K25: 0 | L25: 0 | M25: 0 | N25: 0 | O25: 0 | P25: 0 | Q25: 0 | R25: 0 | S25: 0 | T25: 2 | U25: 0 | V25: 8.5
B26: TOTAL | D26: 3174 | E26: 3627 | F26: 6801 | G26: 23 | I26: 0 | J26: 0 | K26: 0 | L26: 0 | M26: 0 | N26: 0 | O26: 0 | P26: 0 | Q26: 0 | R26: 0 | S26: 0 | T26: 6801 | U26: 0 | V26: 195.5
A27: MATERIAL
A28: Material | B28: Fator | C28: Total | D28: Abr | E28: Mai | F28: Jun | G28: Jul | H28: Ago | I28: Set | J28: Out | K28: Nov | L28: Dez | M28: Jan/27
A29: Tubo PVC ESG | B29: 0.55 | C29: 0 | D29: 0 | E29: 0 | F29: 0 | G29: 0 | H29: 0 | I29: 0 | J29: 0 | K29: 0 | L29: 0 | M29: 0
A30: Tubo PEAD Agua | B30: 0.65 | C30: 0 | D30: 0 | E30: 0 | F30: 0 | G30: 0 | H30: 0 | I30: 0 | J30: 0 | K30: 0 | L30: 0 | M30: 0
A31: Areia | B31: 0.27 | C31: 0 | D31: 0 | E31: 0 | F31: 0 | G31: 0 | H31: 0 | I31: 0 | J31: 0 | K31: 0 | L31: 0 | M31: 0
A32: Brita | B32: 0.12 | C32: 0 | D32: 0 | E32: 0 | F32: 0 | G32: 0 | H32: 0 | I32: 0 | J32: 0 | K32: 0 | L32: 0 | M32: 0
A33: Concreto | B33: 0.1 | C33: 0 | D33: 0 | E33: 0 | F33: 0 | G33: 0 | H33: 0 | I33: 0 | J33: 0 | K33: 0 | L33: 0 | M33: 0
A34: CBUQ | B34: 0.12 | C34: 0 | D34: 0 | E34: 0 | F34: 0 | G34: 0 | H34: 0 | I34: 0 | J34: 0 | K34: 0 | L34: 0 | M34: 0

Sheet SD_JOAO_CARLOS
A1: SD — João Carlos | ESG 91% | AGU 5.759m restante
A3: EQ: | B3: 4 | C3: PROD: | D3: 6 | E3: INI: | F3: 1
A4: PROGRESSO: | B4: ESG: 867/955m (91%) | E4: AG: 930/93m (998%)
A5: TIPO | B5: ID | C5: PV INI | D5: PV FIM | E5: EXT(m) | F5: DN | G5: MATERIAL | H5: PROF(m) | I5: ESCAV(m3) | J5: STATUS
A6: ESGOTO | B6: T-001 | C6: PI 68 | D6: PI 64 | E6: 26.32 | F6: 300 | G6: Tubo PVC | H6: 1.59 | I6: 33.41 | J6: PENDENTE
A7: ESGOTO | B7: T-002 | C7: PI 62 | D7: PI 44 | E7: 10.45 | F7: 300 | G7: Tubo PVC | H7: 3.11 | I7: 26.01 | J7: PENDENTE
A8: ESGOTO | B8: T-003 | C8: PI 44 | D8: PI 02 | E8: 8.28 | F8: 300 | G8: Tubo PVC | H8: 4.32 | I8: 28.6 | J8: PENDENTE
A9: ESGOTO | B9: T-004 | C9: PI 06 | D9: PI 16 | E9: 35.86 | F9: 300 | G9: Tubo PVC | H9: 1.77 | I9: 50.66 | J9: PENDENTE
A10: ESGOTO | B10: T-005 | C10: PI 62 | D10: PI 63 | E10: 12.77 | F10: 300 | G10: Tubo PVC | H10: 1.87 | I10: 19.07 | J10: PENDENTE
A11: ESGOTO | B11: T-006 | C11: PI 64 | D11: PI 63 | E11: 9.35 | F11: 300 | G11: Tubo PVC | H11: 1.96 | I11: 14.69 | J11: PENDENTE
A12: ESGOTO | B12: T-007 | C12: PI 16 | D12: PI 19 | E12: 8.4 | F12: 200 | G12: Tubo PVC | H12: 2.6 | I12: 17.48 | J12: PENDENTE
A13: ESGOTO | B13: T-008 | C13: PI 118 | D13: PI 115 | E13: 13.75 | F13: 1000 | G13: Tubo de Concreto | H13: 0.73 | I13: 8.02 | J13: PENDENTE
A14: ESGOTO | B14: T-009 | C14: PI 115 | D14: PI 113 | E14: 11.52 | F14: 1000 | G14: Tubo de Concreto | H14: 0.98 | I14: 9.06 | J14: PENDENTE
A15: ESGOTO | B15: T-010 | C15: PI 68 | D15: PI 65 | E15: 10.76 | F15: 1000 | G15: Tubo de Concreto | H15: 0.69 | I15: 5.96 | J15: PENDENTE
A16: ESGOTO | B16: T-011 | C16: PI 65 | D16: PI 64 | E16: 10.69 | F16: 1000 | G16: Tubo de Concreto | H16: 1.19 | I16: 10.21 | J16: PENDENTE
A17: ESGOTO | B17: T-012 | C17: PI 64 | D17: PI 63 | E17: 9.38 | F17: 1000 | G17: Tubo de Concreto | H17: 1.96 | I17: 14.74 | J17: PENDENTE
... A95: AGUA | B95: T-045 | C95: PI 03 | D95: PI 04 | E95: 2 | F95: 200 | G95: Tubo PVC | H95: 0.3 | I95: 0.48 | J95: PENDENTE
A96: TOTAL | E96: 1047.95

Sheet SD_SAO_MANOEL
A1: SD — São Manoel | ESG >100% | AGU 3.769m executado
A3: EQ: | B3: 5 | C3: PROD: | D3: 6 | E3: INI: | F3: 1
A4: PROGRESSO: | B4: ESG: 1384/955m (145%) | E4: AG: 3769/93m (4046%)
A5: TIPO | B5: ID | C5: PV INI | D5: PV FIM | E5: EXT(m) | F5: DN | G5: MATERIAL | H5: PROF(m) | I5: ESCAV(m3) | J5: STATUS
A6: ESGOTO | B6: T-001 | C6: PI 68 | D6: PI 64 | E6: 26.32 | F6: 300 | G6: Tubo PVC | H6: 1.59 | I6: 33.41 | J6: PENDENTE
A7: ESGOTO | B7: T-002 | C7: PI 62 | D7: PI 44 | E7: 10.45 | F7: 300 | G7: Tubo PVC | H7: 3.11 | I7: 26.01 | J7: PENDENTE
A8: ESGOTO | B8: T-003 | C8: PI 44 | D8: PI 02 | E8: 8.28 | F8: 300 | G8: Tubo PVC | H8: 4.32 | I8: 28.6 | J8: PENDENTE
A9: ESGOTO | B9: T-004 | C9: PI 06 | D9: PI 16 | E9: 35.86 | F9: 300 | G9: Tubo PVC | H9: 1.77 | I9: 50.66 | J9: PENDENTE
A10: ESGOTO | B10: T-005 | C10: PI 62 | D10: PI 63 | E10: 12.77 | F10: 300 | G10: Tubo PVC | H10: 1.87 | I10: 19.07 | J10: PENDENTE
A11: ESGOTO | B11: T-006 | C11: PI 64 | D11: PI 63 | E11: 9.35 | F11: 300 | G11: Tubo PVC | H11: 1.96 | I11: 14.69 | J11: PENDENTE
A12: ESGOTO | B12: T-007 | C12: PI 16 | D12: PI 19 | E12: 8.4 | F12: 200 | G12: Tubo PVC | H12: 2.6 | I12: 17.48 | J12: PENDENTE
A13: ESGOTO | B13: T-008 | C13: PI 118 | D13: PI 115 | E13: 13.75 | F13: 1000 | G13: Tubo de Concreto | H13: 0.73 | I13: 8.02 | J13: PENDENTE
A14: ESGOTO | B14: T-009 | C14: PI 115 | D14: PI 113 | E14: 11.52 | F14: 1000 | G14: Tubo de Concreto | H14: 0.98 | I14: 9.06 | J14: PENDENTE
A15: ESGOTO | B15: T-010 | C15: PI 68 | D15: PI 65 | E15: 10.76 | F15: 1000 | G15: Tubo de Concreto | H15: 0.69 | I15: 5.96 | J15: PENDENTE
A16: ESGOTO | B16: T-011 | C16: PI 65 | D16: PI 64 | E16: 10.69 | F16: 1000 | G16: Tubo de Concreto | H16: 1.19 | I16: 10.21 | J16: PENDENTE
A17: ESGOTO | B17: T-012 | C17: PI 64 | D17: PI 63 | E17: 9.38 | F17: 1000 | G17: Tubo de Concreto | H17: 1.96 | I17: 14.74 | J17: PENDENTE
... A95: AGUA | B95: T-045 | C95: PI 03 | D95: PI 04 | E95: 2 | F95: 200 | G95: Tubo PVC | H95: 0.3 | I95: 0.48 | J95: PENDENTE
A96: TOTAL | E96: 1047.95

Sheet SD_VILA_ISRAEL
A1: SD — Vila Israel | ESG 66% | AGU sem projeto
A3: EQ: | B3: 4 | C3: PROD: | D3: 6 | E3: INI: | F3: 1
A4: PROGRESSO: | B4: ESG: 1406/2140m (66%) | E4: AG: sem projeto agua
A5: TIPO | B5: ID | C5: PV INI | D5: PV FIM | E5: EXT(m) | F5: DN | G5: MATERIAL | H5: PROF(m) | I5: ESCAV(m3) | J5: STATUS
A6: ESGOTO | B6: T-001 | C6: PI 194 | D6: PI 195 | E6: 6.9 | F6: 200 | G6: Tubo PVC | H6: 0.6 | I6: 3.31 | J6: PENDENTE
A7: ESGOTO | B7: T-002 | C7: PI 195 | D7: PI 196 | E7: 7.37 | F7: 200 | G7: Tubo PVC | H7: 0.6 | I7: 3.54 | J7: PENDENTE
A8: ESGOTO | B8: T-003 | C8: PI 196 | D8: PI 197 | E8: 5.41 | F8: 200 | G8: Tubo PVC | H8: 0.6 | I8: 2.6 | J8: PENDENTE
A9: ESGOTO | B9: T-004 | C9: PI 197 | D9: PI 196 | E9: 2.5 | F9: 200 | G9: Tubo PVC | H9: 0.6 | I9: 1.2 | J9: PENDENTE
A10: ESGOTO | B10: T-005 | C10: PI 196 | D10: PI 195 | E10: 2.5 | F10: 200 | G10: Tubo PVC | H10: 0.6 | I10: 1.2 | J10: PENDENTE
A11: ESGOTO | B11: T-006 | C11: PI 195 | D11: PI 194 | E11: 2.5 | F11: 200 | G11: Tubo PVC | H11: 0.6 | I11: 1.2 | J11: PENDENTE
A12: ESGOTO | B12: T-007 | C12: PI 195 | D12: PI 208 | E12: 4.99 | F12: 200 | G12: Tubo PVC | H12: 0.58 | I12: 2.32 | J12: PENDENTE
A13: ESGOTO | B13: T-008 | C13: PI 208 | D13: PI 209 | E13: 16.94 | F13: 200 | G13: Tubo PVC | H13: 1.18 | I13: 16.01 | J13: PENDENTE
A14: ESGOTO | B14: T-009 | C14: PI 209 | D14: PI 211 | E14: 3.32 | F14: 200 | G14: Tubo PVC | H14: 1.88 | I14: 4.98 | J14: PENDENTE
A15: ESGOTO | B15: T-010 | C15: PI 209 | D15: PI 212 | E15: 28.64 | F15: 200 | G15: Tubo PVC | H15: 1.2 | I15: 27.49 | J15: PENDENTE
A16: ESGOTO | B16: T-011 | C16: PI 212 | D16: PI 213 | E16: 22.87 | F16: 200 | G16: Tubo PVC | H16: 0.6 | I16: 10.98 | J16: PENDENTE
A17: ESGOTO | B17: T-012 | C17: PI 213 | D17: PI 214 | E17: 15.9 | F17: 200 | G17: Tubo PVC | H17: 0.6 | I17: 7.63 | J17: PENDENTE
... A265: ESGOTO | B265: T-260 | C265: PV 27 | D265: PI 211 | E265: 6.63 | F265: 200 | G265: Tubo PVC | H265: 1.27 | I265: 6.76 | J265: PENDENTE
A266: TOTAL | E266: 2140.41

Sheet SD_MORRO_TETEU
A1: SD — Morro do Tetéu | ESG 21% | AGU 74%
A3: EQ: | B3: 10 | C3: PROD: | D3: 6 | E3: INI: | F3: 1
A4: PROGRESSO: | B4: ESG: 1037/5034m (21%) | E4: AG: 338/457m (74%)
A5: TIPO | B5: ID | C5: PV INI | D5: PV FIM | E5: EXT(m) | F5: DN | G5: MATERIAL | H5: PROF(m) | I5: ESCAV(m3) | J5: STATUS
A6: ESGOTO | B6: T-001 | C6: PI 102 | D6: PI 103 | E6: 15.82 | F6: 200 | G6: Tubo PVC | H6: 0.6 | I6: 7.59 | J6: PENDENTE
A7: ESGOTO | B7: T-002 | C7: PI 103 | D7: PI 104 | E7: 10.57 | F7: 200 | G7: Tubo PVC | H7: 0.6 | I7: 5.07 | J7: PENDENTE
A8: ESGOTO | B8: T-003 | C8: PI 104 | D8: PI 105 | E8: 2.59 | F8: 200 | G8: Tubo PVC | H8: 0.6 | I8: 1.24 | J8: PENDENTE
A9: ESGOTO | B9: T-004 | C9: PI 105 | D9: PI 106 | E9: 8.88 | F9: 200 | G9: Tubo PVC | H9: 0.6 | I9: 4.26 | J9: PENDENTE
A10: ESGOTO | B10: T-005 | C10: PI 106 | D10: PI 107 | E10: 2.24 | F10: 200 | G10: Tubo PVC | H10: 0.6 | I10: 1.08 | J10: PENDENTE
A11: ESGOTO | B11: T-006 | C11: PI 107 | D11: PI 108 | E11: 4.35 | F11: 200 | G11: Tubo PVC | H11: 0.6 | I11: 2.09 | J11: PENDENTE
A12: ESGOTO | B12: T-007 | C12: PI 108 | D12: PI 109 | E12: 2.15 | F12: 200 | G12: Tubo PVC | H12: 0.6 | I12: 1.03 | J12: PENDENTE
A13: ESGOTO | B13: T-008 | C13: PI 109 | D13: PI 110 | E13: 10.67 | F13: 200 | G13: Tubo PVC | H13: 0.6 | I13: 5.12 | J13: PENDENTE
A14: ESGOTO | B14: T-009 | C14: PI 111 | D14: PI 112 | E14: 10.85 | F14: 200 | G14: Tubo PVC | H14: 0.6 | I14: 5.21 | J14: PENDENTE
A15: ESGOTO | B15: T-010 | C15: PI 112 | D15: PI 113 | E15: 3.91 | F15: 200 | G15: Tubo PVC | H15: 0.6 | I15: 1.88 | J15: PENDENTE
A16: ESGOTO | B16: T-011 | C16: PI 114 | D16: PI 115 | E16: 9.39 | F16: 200 | G16: Tubo PVC | H16: 1.2 | I16: 9.01 | J16: PENDENTE
A17: ESGOTO | B17: T-012 | C17: PI 115 | D17: PI 116 | E17: 9.76 | F17: 200 | G17: Tubo PVC | H17: 0.6 | I17: 4.68 | J17: PENDENTE
... A1338: AGUA | B1338: T-785 | C1338: PI 270 | D1338: PI 268 | E1338: 1.05 | F1338: 200 | G1338: Tubo PVC | H1338: 0.6 | I1338: 0.5 | J1338: PENDENTE
A1339: TOTAL | E1339: 5490.94

Sheet SD_VILA_CRIADORES
A1: SD — Vila Criadores | ESG 10% | AGU 3.147m exec.
A3: EQ: | B3: 8 | C3: PROD: | D3: 6 | E3: INI: | F3: 1
A4: PROGRESSO: | B4: ESG: 297/2930m (10%) | E4: AG: 3147/255m (1235%)
A5: TIPO | B5: ID | C5: PV INI | D5: PV FIM | E5: EXT(m) | F5: DN | G5: MATERIAL | H5: PROF(m) | I5: ESCAV(m3) | J5: STATUS
A6: ESGOTO | B6: T-001 | C6: PI 75 | D6: PI 76 | E6: 15.77 | F6: 200 | G6: Tubo PVC | H6: 0.6 | I6: 7.57 | J6: PENDENTE
A7: ESGOTO | B7: T-002 | C7: PI 76 | D7: PI 77 | E7: 32.88 | F7: 200 | G7: Tubo PVC | H7: 0.6 | I7: 15.78 | J7: PENDENTE
A8: ESGOTO | B8: T-003 | C8: PI 77 | D8: PI 79 | E8: 2.24 | F8: 200 | G8: Tubo PVC | H8: 0.6 | I8: 1.08 | J8: PENDENTE
A9: ESGOTO | B9: T-004 | C9: PI 79 | D9: PI 77 | E9: 1.34 | F9: 200 | G9: Tubo PVC | H9: 0.6 | I9: 0.64 | J9: PENDENTE
A10: ESGOTO | B10: T-005 | C10: PI 81 | D10: PI 82 | E10: 1.05 | F10: 200 | G10: Tubo PVC | H10: 0.6 | I10: 0.5 | J10: PENDENTE
A11: ESGOTO | B11: T-006 | C11: PI 81 | D11: PI 82 | E11: 0.63 | F11: 200 | G11: Tubo PVC | H11: 0.6 | I11: 0.3 | J11: PENDENTE
A12: ESGOTO | B12: T-007 | C12: PI 82 | D12: PI 83 | E12: 37.25 | F12: 200 | G12: Tubo PVC | H12: 0.6 | I12: 17.88 | J12: PENDENTE
A13: ESGOTO | B13: T-008 | C13: PI 84 | D13: PI 85 | E13: 30.91 | F13: 200 | G13: Tubo PVC | H13: 0.6 | I13: 14.84 | J13: PENDENTE
A14: ESGOTO | B14: T-009 | C14: PI 85 | D14: PI 86 | E14: 30.82 | F14: 200 | G14: Tubo PVC | H14: 0.6 | I14: 14.79 | J14: PENDENTE
A15: ESGOTO | B15: T-010 | C15: PI 86 | D15: PI 87 | E15: 27.48 | F15: 200 | G15: Tubo PVC | H15: 0.66 | I15: 14.52 | J15: PENDENTE
A16: ESGOTO | B16: T-011 | C16: PI 135 | D16: PI 136 | E16: 11.08 | F16: 200 | G16: Tubo PVC | H16: 0.69 | I16: 6.16 | J16: PENDENTE
A17: ESGOTO | B17: T-012 | C17: PI 136 | D17: PI 137 | E17: 32.92 | F17: 200 | G17: Tubo PVC | H17: 0.69 | I17: 18.31 | J17: PENDENTE
... A154: AGUA | B154: T-003 | C154: PI 01 | D154: PI 02 | E154: 3.72 | F154: 110 | G154: Tubo PE 80 NTS194 PN 12.5 | H154: 1.5 | I154: 4.46 | J154: PENDENTE
A155: TOTAL | E155: 3184.9

Sheet SD_PANTANAL_BAIXO
A1: SD — Pantanal Baixo | ESG 4% | AGU sem projeto
A3: EQ: | B3: 8 | C3: PROD: | D3: 6 | E3: INI: | F3: 1
A4: PROGRESSO: | B4: ESG: 153/3471m (4%) | E4: AG: sem projeto agua
A5: TIPO | B5: ID | C5: PV INI | D5: PV FIM | E5: EXT(m) | F5: DN | G5: MATERIAL | H5: PROF(m) | I5: ESCAV(m3) | J5: STATUS
A6: ESGOTO | B6: T-001 | C6: PV 01 | D6: PV 02 | E6: 13.57 | F6: 300 | G6: Tubo PVC | H6: 0.8 | I6: 8.68 | J6: PENDENTE
A7: ESGOTO | B7: T-002 | C7: PV 02 | D7: PV 03 | E7: 16.65 | F7: 300 | G7: Tubo PVC | H7: 1 | I7: 13.32 | J7: PENDENTE
A8: ESGOTO | B8: T-003 | C8: PV 03 | D8: PV 04 | E8: 23.47 | F8: 300 | G8: Tubo PVC | H8: 1 | I8: 18.78 | J8: PENDENTE
A9: ESGOTO | B9: T-004 | C9: PV 04 | D9: PV 05 | E9: 12.5 | F9: 300 | G9: Tubo PVC | H9: 0.8 | I9: 8 | J9: PENDENTE
A10: ESGOTO | B10: T-005 | C10: PV 05 | D10: PV 06 | E10: 29.64 | F10: 300 | G10: Tubo PVC | H10: 0.8 | I10: 18.97 | J10: PENDENTE
A11: ESGOTO | B11: T-006 | C11: PV 06 | D11: PV 07 | E11: 8.55 | F11: 300 | G11: Tubo PVC | H11: 0.9 | I11: 6.16 | J11: PENDENTE
A12: ESGOTO | B12: T-007 | C12: PV 07 | D12: PV 08 | E12: 27.46 | F12: 300 | G12: Tubo PVC | H12: 1.05 | I12: 23.07 | J12: PENDENTE
A13: ESGOTO | B13: T-008 | C13: PV 08 | D13: PV 09 | E13: 32.36 | F13: 300 | G13: Tubo PVC | H13: 1.35 | I13: 34.95 | J13: PENDENTE
A14: ESGOTO | B14: T-009 | C14: PV 09 | D14: PV 10 | E14: 51.01 | F14: 300 | G14: Tubo PVC | H14: 1.65 | I14: 67.33 | J14: PENDENTE
A15: ESGOTO | B15: T-010 | C15: PV 10 | D15: PV 11 | E15: 31.62 | F15: 300 | G15: Tubo PVC | H15: 2.08 | I15: 52.49 | J15: PENDENTE
A16: ESGOTO | B16: T-011 | C16: PV 01 | D16: PV 12 | E16: 31.96 | F16: 300 | G16: Tubo PVC | H16: 0.8 | I16: 20.45 | J16: PENDENTE
A17: ESGOTO | B17: T-012 | C17: PV 12 | D17: PV 13 | E17: 14.92 | F17: 300 | G17: Tubo PVC | H17: 0.8 | I17: 9.55 | J17: PENDENTE
... A318: ESGOTO | B318: T-313 | C318: PI 152 | D318: PV 21 | E318: 40.61 | F318: 200 | G318: Tubo PVC | H318: 1.58 | I318: 51.3 | J318: PENDENTE
A319: TOTAL | E319: 3471.26

Sheet PROJ_vs_EXEC
A1: PROJETO vs EXECUTADO — Linkado à aba PROJETO
A3: NÚCLEO | B3: PROJ ESG | C3: EXEC ESG | D3: % ESG | E3: FALTA ESG | F3: PROJ AG | G3: EXEC AG | H3: % AG | I3: FALTA AG | J3: PROJ TOT | K3: EXEC TOT | L3: % TOT | M3: CUSTO EXEC
A4: =PROJETO!A5 | B4: =PROJETO!C5 | C4: =PROJETO!F5 | D4: =IF(B4>0,C4/B4,0) | E4: =B4-C4 | F4: =PROJETO!B5 | G4: =PROJETO!E5 | H4: =IF(F4>0,G4/F4,0) | I4: =F4-G4 | J4: =B4+F4 | K4: =C4+G4 | L4: =IF(J4>0,K4/J4,0) | M4: =K4*910
A5: =PROJETO!A6 | B5: =PROJETO!C6 | C5: =PROJETO!F6 | D5: =IF(B5>0,C5/B5,0) | E5: =B5-C5 | F5: =PROJETO!B6 | G5: =PROJETO!E6 | H5: =IF(F5>0,G5/F5,0) | I5: =F5-G5 | J5: =B5+F5 | K5: =C5+G5 | L5: =IF(J5>0,K5/J5,0) | M5: =K5*910
A6: =PROJETO!A7 | B6: =PROJETO!C7 | C6: =PROJETO!F7 | D6: =IF(B6>0,C6/B6,0) | E6: =B6-C6 | F6: =PROJETO!B7 | G6: =PROJETO!E7 | H6: =IF(F6>0,G6/F6,0) | I6: =F6-G6 | J6: =B6+F6 | K6: =C6+G6 | L6: =IF(J6>0,K6/J6,0) | M6: =K6*910
A7: =PROJETO!A8 | B7: =PROJETO!C8 | C7: =PROJETO!F8 | D7: =IF(B7>0,C7/B7,0) | E7: =B7-C7 | F7: =PROJETO!B8 | G7: =PROJETO!E8 | H7: =IF(F7>0,G7/F7,0) | I7: =F7-G7 | J7: =B7+F7 | K7: =C7+G7 | L7: =IF(J7>0,K7/J7,0) | M7: =K7*910
A8: =PROJETO!A9 | B8: =PROJETO!C9 | C8: =PROJETO!F9 | D8: =IF(B8>0,C8/B8,0) | E8: =B8-C8 | F8: =PROJETO!B9 | G8: =PROJETO!E9 | H8: =IF(F8>0,G8/F8,0) | I8: =F8-G8 | J8: =B8+F8 | K8: =C8+G8 | L8: =IF(J8>0,K8/J8,0) | M8: =K8*910
A9: TOTAL | B9: =SUM(B4:B8) | C9: =SUM(C4:C8) | D9: =IF(B9>0,C9/B9,0) | E9: =B9-C9 | F9: =SUM(F4:F8) | G9: =SUM(G4:G8) | H9: =IF(F9>0,G9/F9,0) | I9: =F9-G9 | J9: =B9+F9 | K9: =C9+G9 | L9: =IF(J9>0,K9/J9,0) | M9: =K9*910

Sheet MATERIAL_DELTA
A1: MATERIAL DELTA — Linkado PROJETO + SALDO
A3: NÚCLEO | B3: SALDO AG | C3: SALDO ESG | D3: SALDO TOTAL | E3: CUSTO SALDO | F3: MESES | G3: STATUS
A4: =PROJETO!A5 | B4: =SALDO!B4 | C4: =SALDO!C4 | D4: =SALDO!D4 | E4: =D4*910 | F4: =PROJETO!H5 | G4: =IF(D4=0,"PRONTO",IF(D4<1000,"FINALIZANDO","EXECUTANDO"))
A5: =PROJETO!A6 | B5: =SALDO!B5 | C5: =SALDO!C5 | D5: =SALDO!D5 | E5: =D5*910 | F5: =PROJETO!H6 | G5: =IF(D5=0,"PRONTO",IF(D5<1000,"FINALIZANDO","EXECUTANDO"))
A6: =PROJETO!A7 | B6: =SALDO!B6 | C6: =SALDO!C6 | D6: =SALDO!D6 | E6: =D6*910 | F6: =PROJETO!H7 | G6: =IF(D6=0,"PRONTO",IF(D6<1000,"FINALIZANDO","EXECUTANDO"))
A7: =PROJETO!A8 | B7: =SALDO!B7 | C7: =SALDO!C7 | D7: =SALDO!D7 | E7: =D7*910 | F7: =PROJETO!H8 | G7: =IF(D7=0,"PRONTO",IF(D7<1000,"FINALIZANDO","EXECUTANDO"))
A8: =PROJETO!A9 | B8: =SALDO!B8 | C8: =SALDO!C8 | D8: =SALDO!D8 | E8: =D8*910 | F8: =PROJETO!H9 | G8: =IF(D8=0,"PRONTO",IF(D8<1000,"FINALIZANDO","EXECUTANDO"))
A9: TOTAL | B9: =SUM(B4:B8) | C9: =SUM(C4:C8) | D9: =SUM(D4:D8) | E9: =D9*910 | G9: =IF(D9=0,"PRONTO",IF(D9<1000,"FINALIZANDO","EXECUTANDO"))

Sheet CONSUMIDO_vs_CONSUMIR
A1: CONSUMIDO vs CONSUMIR — Linkado PROJETO + MATERIAIS
A3: NÚCLEO | B3: MATERIAL | C3: QTD COMPRAR | D3: P.UNIT | E3: CUSTO | F3: LEAD
A4: =PROJETO!A5 | B4: =MATERIAIS!A23 | C4: =MATERIAIS!C23 | D4: =MATERIAIS!E5 | E4: =C4*D4 | F4: =MATERIAIS!F5
A5: =PROJETO!A5 | B5: =MATERIAIS!A24 | C5: =MATERIAIS!C24 | D5: =MATERIAIS!E6 | E5: =C5*D5 | F5: =MATERIAIS!F6
A6: =PROJETO!A5 | B6: =MATERIAIS!A25 | C6: =MATERIAIS!C25 | D6: =MATERIAIS!E7 | E6: =C6*D6 | F6: =MATERIAIS!F7
A7: =PROJETO!A5 | B7: =MATERIAIS!A26 | C7: =MATERIAIS!C26 | D7: =MATERIAIS!E8 | E7: =C7*D7 | F7: =MATERIAIS!F8
A8: =PROJETO!A5 | B8: =MATERIAIS!A27 | C8: =MATERIAIS!C27 | D8: =MATERIAIS!E9 | E8: =C8*D8 | F8: =MATERIAIS!F9
A9: =PROJETO!A5 | B9: =MATERIAIS!A28 | C9: =MATERIAIS!C28 | D9: =MATERIAIS!E10 | E9: =C9*D9 | F9: =MATERIAIS!F10
A10: =PROJETO!A5 | B10: =MATERIAIS!A29 | C10: =MATERIAIS!C29 | D10: =MATERIAIS!E11 | E10: =C10*D10 | F10: =MATERIAIS!F11
A11: =PROJETO!A5 | B11: =MATERIAIS!A30 | C11: =MATERIAIS!C30 | D11: =MATERIAIS!E12 | E11: =C11*D11 | F11: =MATERIAIS!F12
A12: =PROJETO!A5 | B12: =MATERIAIS!A31 | C12: =MATERIAIS!C31 | D12: =MATERIAIS!E13 | E12: =C12*D12 | F12: =MATERIAIS!F13
A13: =PROJETO!A5 | B13: =MATERIAIS!A32 | C13: =MATERIAIS!C32 | D13: =MATERIAIS!E14 | E13: =C13*D13 | F13: =MATERIAIS!F14
A14: =PROJETO!A5 | B14: =MATERIAIS!A33 | C14: =MATERIAIS!C33 | D14: =MATERIAIS!E15 | E14: =C14*D14 | F14: =MATERIAIS!F15
A15: =PROJETO!A5 | B15: =MATERIAIS!A34 | C15: =MATERIAIS!C34 | D15: =MATERIAIS!E16 | E15: =C15*D15 | F15: =MATERIAIS!F16
A16: =PROJETO!A5 | B16: =MATERIAIS!A35 | C16: =MATERIAIS!C35 | D16: =MATERIAIS!E17 | E16: =C16*D16 | F16: =MATERIAIS!F17
A17: =PROJETO!A5 | B17: =MATERIAIS!A36 | C17: =MATERIAIS!C36 | D17: =MATERIAIS!E18 | E17: =C17*D17 | F17: =MATERIAIS!F18
A19: =PROJETO!A6 | B19: =MATERIAIS!A23 | C19: =MATERIAIS!D23 | D19: =MATERIAIS!E5 | E19: =C19*D19 | F19: =MATERIAIS!F5
A20: =PROJETO!A6 | B20: =MATERIAIS!A24 | C20: =MATERIAIS!D24 | D20: =MATERIAIS!E6 | E20: =C20*D20 | F20: =MATERIAIS!F6
A21: =PROJETO!A6 | B21: =MATERIAIS!A25 | C21: =MATERIAIS!D25 | D21: =MATERIAIS!E7 | E21: =C21*D21 | F21: =MATERIAIS!F7
A22: =PROJETO!A6 | B22: =MATERIAIS!A26 | C22: =MATERIAIS!D26 | D22: =MATERIAIS!E8 | E22: =C22*D22 | F22: =MATERIAIS!F8
A23: =PROJETO!A6 | B23: =MATERIAIS!A27 | C23: =MATERIAIS!D27 | D23: =MATERIAIS!E9 | E23: =C23*D23 | F23: =MATERIAIS!F9
A24: =PROJETO!A6 | B24: =MATERIAIS!A28 | C24: =MATERIAIS!D28 | D24: =MATERIAIS!E10 | E24: =C24*D24 | F24: =MATERIAIS!F10
A25: =PROJETO!A6 | B25: =MATERIAIS!A29 | C25: =MATERIAIS!D29 | D25: =MATERIAIS!E11 | E25: =C25*D25 | F25: =MATERIAIS!F11
A26: =PROJETO!A6 | B26: =MATERIAIS!A30 | C26: =MATERIAIS!D30 | D26: =MATERIAIS!E12 | E26: =C26*D26 | F26: =MATERIAIS!F12
A27: =PROJETO!A6 | B27: =MATERIAIS!A31 | C27: =MATERIAIS!D31 | D27: =MATERIAIS!E13 | E27: =C27*D27 | F27: =MATERIAIS!F13
A28: =PROJETO!A6 | B28: =MATERIAIS!A32 | C28: =MATERIAIS!D32 | D28: =MATERIAIS!E14 | E28: =C28*D28 | F28: =MATERIAIS!F14
A29: =PROJETO!A6 | B29: =MATERIAIS!A33 | C29: =MATERIAIS!D33 | D29: =MATERIAIS!E15 | E29: =C29*D29 | F29: =MATERIAIS!F15
A30: =PROJETO!A6 | B30: =MATERIAIS!A34 | C30: =MATERIAIS!D34 | D30: =MATERIAIS!E16 | E30: =C30*D30 | F30: =MATERIAIS!F16
A31: =PROJETO!A6 | B31: =MATERIAIS!A35 | C31: =MATERIAIS!D35 | D31: =MATERIAIS!E17 | E31: =C31*D31 | F31: =MATERIAIS!F17
A32: =PROJETO!A6 | B32: =MATERIAIS!A36 | C32: =MATERIAIS!D36 | D32: =MATERIAIS!E18 | E32: =C32*D32 | F32: =MATERIAIS!F18
A34: =PROJETO!A7 | B34: =MATERIAIS!A23 | C34: =MATERIAIS!E23 | D34: =MATERIAIS!E5 | E34: =C34*D34 | F34: =MATERIAIS!F5
A35: =PROJETO!A7 | B35: =MATERIAIS!A24 | C35: =MATERIAIS!E24 | D35: =MATERIAIS!E6 | E35: =C35*D35 | F35: =MATERIAIS!F6
A36: =PROJETO!A7 | B36: =MATERIAIS!A25 | C36: =MATERIAIS!E25 | D36: =MATERIAIS!E7 | E36: =C36*D36 | F36: =MATERIAIS!F7
A37: =PROJETO!A7 | B37: =MATERIAIS!A26 | C37: =MATERIAIS!E26 | D37: =MATERIAIS!E8 | E37: =C37*D37 | F37: =MATERIAIS!F8
A38: =PROJETO!A7 | B38: =MATERIAIS!A27 | C38: =MATERIAIS!E27 | D38: =MATERIAIS!E9 | E38: =C38*D38 | F38: =MATERIAIS!F9
A39: =PROJETO!A7 | B39: =MATERIAIS!A28 | C39: =MATERIAIS!E28 | D39: =MATERIAIS!E10 | E39: =C39*D39 | F39: =MATERIAIS!F10
A40: =PROJETO!A7 | B40: =MATERIAIS!A29 | C40: =MATERIAIS!E29 | D40: =MATERIAIS!E11 | E40: =C40*D40 | F40: =MATERIAIS!F11
A41: =PROJETO!A7 | B41: =MATERIAIS!A30 | C41: =MATERIAIS!E30 | D41: =MATERIAIS!E12 | E41: =C41*D41 | F41: =MATERIAIS!F12
A42: =PROJETO!A7 | B42: =MATERIAIS!A31 | C42: =MATERIAIS!E31 | D42: =MATERIAIS!E13 | E42: =C42*D42 | F42: =MATERIAIS!F13
A43: =PROJETO!A7 | B43: =MATERIAIS!A32 | C43: =MATERIAIS!E32 | D43: =MATERIAIS!E14 | E43: =C43*D43 | F43: =MATERIAIS!F14
A44: =PROJETO!A7 | B44: =MATERIAIS!A33 | C44: =MATERIAIS!E33 | D44: =MATERIAIS!E15 | E44: =C44*D44 | F44: =MATERIAIS!F15
A45: =PROJETO!A7 | B45: =MATERIAIS!A34 | C45: =MATERIAIS!E34 | D45: =MATERIAIS!E16 | E45: =C45*D45 | F45: =MATERIAIS!F16
A46: =PROJETO!A7 | B46: =MATERIAIS!A35 | C46: =MATERIAIS!E35 | D46: =MATERIAIS!E17 | E46: =C46*D46 | F46: =MATERIAIS!F17
A47: =PROJETO!A7 | B47: =MATERIAIS!A36 | C47: =MATERIAIS!E36 | D47: =MATERIAIS!E18 | E47: =C47*D47 | F47: =MATERIAIS!F18
A49: =PROJETO!A8 | B49: =MATERIAIS!A23 | C49: =MATERIAIS!F23 | D49: =MATERIAIS!E5 | E49: =C49*D49 | F49: =MATERIAIS!F5
A50: =PROJETO!A8 | B50: =MATERIAIS!A24 | C50: =MATERIAIS!F24 | D50: =MATERIAIS!E6 | E50: =C50*D50 | F50: =MATERIAIS!F6
A51: =PROJETO!A8 | B51: =MATERIAIS!A25 | C51: =MATERIAIS!F25 | D51: =MATERIAIS!E7 | E51: =C51*D51 | F51: =MATERIAIS!F7
A52: =PROJETO!A8 | B52: =MATERIAIS!A26 | C52: =MATERIAIS!F26 | D52: =MATERIAIS!E8 | E52: =C52*D52 | F52: =MATERIAIS!F8
A53: =PROJETO!A8 | B53: =MATERIAIS!A27 | C53: =MATERIAIS!F27 | D53: =MATERIAIS!E9 | E53: =C53*D53 | F53: =MATERIAIS!F9
A54: =PROJETO!A8 | B54: =MATERIAIS!A28 | C54: =MATERIAIS!F28 | D54: =MATERIAIS!E10 | E54: =C54*D54 | F54: =MATERIAIS!F10
A55: =PROJETO!A8 | B55: =MATERIAIS!A29 | C55: =MATERIAIS!F29 | D55: =MATERIAIS!E11 | E55: =C55*D55 | F55: =MATERIAIS!F11
A56: =PROJETO!A8 | B56: =MATERIAIS!A30 | C56: =MATERIAIS!F30 | D56: =MATERIAIS!E12 | E56: =C56*D56 | F56: =MATERIAIS!F12
A57: =PROJETO!A8 | B57: =MATERIAIS!A31 | C57: =MATERIAIS!F31 | D57: =MATERIAIS!E13 | E57: =C57*D57 | F57: =MATERIAIS!F13
A58: =PROJETO!A8 | B58: =MATERIAIS!A32 | C58: =MATERIAIS!F32 | D58: =MATERIAIS!E14 | E58: =C58*D58 | F58: =MATERIAIS!F14
A59: =PROJETO!A8 | B59: =MATERIAIS!A33 | C59: =MATERIAIS!F33 | D59: =MATERIAIS!E15 | E59: =C59*D59 | F59: =MATERIAIS!F15
A60: =PROJETO!A8 | B60: =MATERIAIS!A34 | C60: =MATERIAIS!F34 | D60: =MATERIAIS!E16 | E60: =C60*D60 | F60: =MATERIAIS!F16
A61: =PROJETO!A8 | B61: =MATERIAIS!A35 | C61: =MATERIAIS!F35 | D61: =MATERIAIS!E17 | E61: =C61*D61 | F61: =MATERIAIS!F17
A62: =PROJETO!A8 | B62: =MATERIAIS!A36 | C62: =MATERIAIS!F36 | D62: =MATERIAIS!E18 | E62: =C62*D62 | F62: =MATERIAIS!F18
A64: =PROJETO!A9 | B64: =MATERIAIS!A23 | C64: =MATERIAIS!G23 | D64: =MATERIAIS!E5 | E64: =C64*D64 | F64: =MATERIAIS!F5
A65: =PROJETO!A9 | B65: =MATERIAIS!A24 | C65: =MATERIAIS!G24 | D65: =MATERIAIS!E6 | E65: =C65*D65 | F65: =MATERIAIS!F6
A66: =PROJETO!A9 | B66: =MATERIAIS!A25 | C66: =MATERIAIS!G25 | D66: =MATERIAIS!E7 | E66: =C66*D66 | F66: =MATERIAIS!F7
A67: =PROJETO!A9 | B67: =MATERIAIS!A26 | C67: =MATERIAIS!G26 | D67: =MATERIAIS!E8 | E67: =C67*D67 | F67: =MATERIAIS!F8
A68: =PROJETO!A9 | B68: =MATERIAIS!A27 | C68: =MATERIAIS!G27 | D68: =MATERIAIS!E9 | E68: =C68*D68 | F68: =MATERIAIS!F9
A69: =PROJETO!A9 | B69: =MATERIAIS!A28 | C69: =MATERIAIS!G28 | D69: =MATERIAIS!E10 | E69: =C69*D69 | F69: =MATERIAIS!F10
A70: =PROJETO!A9 | B70: =MATERIAIS!A29 | C70: =MATERIAIS!G29 | D70: =MATERIAIS!E11 | E70: =C70*D70 | F70: =MATERIAIS!F11
A71: =PROJETO!A9 | B71: =MATERIAIS!A30 | C71: =MATERIAIS!G30 | D71: =MATERIAIS!E12 | E71: =C71*D71 | F71: =MATERIAIS!F12
A72: =PROJETO!A9 | B72: =MATERIAIS!A31 | C72: =MATERIAIS!G31 | D72: =MATERIAIS!E13 | E72: =C72*D72 | F72: =MATERIAIS!F13
A73: =PROJETO!A9 | B73: =MATERIAIS!A32 | C73: =MATERIAIS!G32 | D73: =MATERIAIS!E14 | E73: =C73*D73 | F73: =MATERIAIS!F14
A74: =PROJETO!A9 | B74: =MATERIAIS!A33 | C74: =MATERIAIS!G33 | D74: =MATERIAIS!E15 | E74: =C74*D74 | F74: =MATERIAIS!F15
A75: =PROJETO!A9 | B75: =MATERIAIS!A34 | C75: =MATERIAIS!G34 | D75: =MATERIAIS!E16 | E75: =C75*D75 | F75: =MATERIAIS!F16
A76: =PROJETO!A9 | B76: =MATERIAIS!A35 | C76: =MATERIAIS!G35 | D76: =MATERIAIS!E17 | E76: =C76*D76 | F76: =MATERIAIS!F17
A77: =PROJETO!A9 | B77: =MATERIAIS!A36 | C77: =MATERIAIS!G36 | D77: =MATERIAIS!E18 | E77: =C77*D77 | F77: =MATERIAIS!F18

Sheet MAT_DXF
A1: MATERIAL EXTRAÍDO DOS DXFs — ProSanitário (fonte primária)
A3: MATERIAIS EXTRAIDOS DOS DXF — Caixas, PVs, PIs, Conexoes, Tubos
A4: Extraido automaticamente de 11 DXFs do projeto executivo
A5: NUCLEO | B5: MATERIAL | C5: QTD | D5: EXT(m) | E5: FONTE
A6: JOAO_CARLOS | B6: Conexão/Equipamento | C6: 314 | E6: DXF Projeto
A7: JOAO_CARLOS | B7: Tubo PEAD (outros) | C7: 305 | D7: 10075.4 | E7: DXF Projeto
A8: JOAO_CARLOS | B8: Tubo PVC DN200 | C8: 13 | D8: 382.6 | E8: DXF Projeto
A9: SAO_MANOEL | B9: PI (Ponto de Inflexão) | C9: 4925 | E9: DXF Projeto
A10: SAO_MANOEL | B10: Conexão/Equipamento | C10: 514 | E10: DXF Projeto
A11: SAO_MANOEL | B11: Tubo (PAREDE-VISTA) | C11: 434 | D11: 81.7 | E11: DXF Projeto
A12: SAO_MANOEL | B12: Tubo PEAD (outros) | C12: 353 | D12: 11521.8 | E12: DXF Projeto
A13: SAO_MANOEL | B13: PV/Caixa (layer) | C13: 341 | E13: DXF Projeto
A14: SAO_MANOEL | B14: Tubo (PAREDE CONCRETO CORTE) | C14: 264 | D14: 654.4 | E14: DXF Projeto
A15: SAO_MANOEL | B15: Tubo (PS_PERFIL_TUBO) | C15: 258 | D15: 13581.2 | E15: DXF Projeto
A16: SAO_MANOEL | B16: Tubo PVC DN200 | C16: 232 | D16: 3745.5 | E16: DXF Projeto
A17: SAO_MANOEL | B17: Tubo (TUBO_DE_CONCRETO) | C17: 111 | D17: 1524.2 | E17: DXF Projeto
A18: SAO_MANOEL | B18: Tubo (LIN - REDE EXISTENTE SECU) | C18: 25 | D18: 994.6 | E18: DXF Projeto
A19: SAO_MANOEL | B19: Tubo (SGC-TUBOS (DESENHO BIFILA) | C19: 8 | D19: 4.3 | E19: DXF Projeto
A20: SAO_MANOEL | B20: Tubo (LIN - REDE PROJETADA) | C20: 3 | D20: 704.7 | E20: DXF Projeto
A21: SAO_MANOEL | B21: PV/Caixa Inspeção | C21: 2 | E21: DXF Projeto
A22: SAO_MANOEL | B22: Tubo (LIN - REDE 600 - PLUVIAL) | C22: 1 | D22: 207.6 | E22: DXF Projeto
A23: VILA_ISRAEL | B23: Tubo PEAD (outros) | C23: 691 | D23: 9037.9 | E23: DXF Projeto
A24: VILA_ISRAEL | B24: PV/Caixa (layer) | C24: 309 | E24: DXF Projeto
A25: VILA_ISRAEL | B25: Tubo PVC DN200 | C25: 164 | D25: 1916.6 | E25: DXF Projeto
A26: VILA_ISRAEL | B26: Tubo (PS_PERFIL_TUBO) | C26: 123 | D26: 3330.6 | E26: DXF Projeto
A27: VILA_ISRAEL | B27: Conexão/Equipamento | C27: 34 | E27: DXF Projeto
A28: MORRO_TETEU | B28: PV/Caixa (layer) | C28: 753 | E28: DXF Projeto
A29: MORRO_TETEU | B29: Tubo PVC DN200 | C29: 520 | D29: 8207.8 | E29: DXF Projeto
A30: MORRO_TETEU | B30: Tubo PEAD (outros) | C30: 358 | D30: 4827.4 | E30: DXF Projeto
A31: MORRO_TETEU | B31: Conexão/Equipamento | C31: 26 | E31: DXF Projeto
A32: MORRO_TETEU | B32: Tubo (PS_PERFIL_TUBO) | C32: 16 | D32: 673.4 | E32: DXF Projeto
A33: VILA_CRIADORES | B33: Tubo (PS_PERFIL_TUBO) | C33: 173 | D33: 8470 | E33: DXF Projeto
A34: VILA_CRIADORES | B34: Tubo PEAD (outros) | C34: 130 | D34: 4137.9 | E34: DXF Projeto
A35: VILA_CRIADORES | B35: PV/Caixa (layer) | C35: 128 | E35: DXF Projeto
A36: VILA_CRIADORES | B36: Tubo PVC DN200 | C36: 86 | D36: 1970 | E36: DXF Projeto
A37: VILA_CRIADORES | B37: Conexão/Equipamento | C37: 2 | E37: DXF Projeto
A38: PANTANAL_BAIXO | B38: Tubo PEAD (outros) | C38: 398 | D38: 7168.3 | E38: DXF Projeto
A39: PANTANAL_BAIXO | B39: PV/Caixa (layer) | C39: 280 | E39: DXF Projeto
A40: PANTANAL_BAIXO | B40: Tubo PVC DN200 | C40: 222 | D40: 3328.6 | E40: DXF Projeto
A41: PANTANAL_BAIXO | B41: Tubo (PS_PERFIL_TUBO) | C41: 128 | D41: 5637.7 | E41: DXF Projeto
A42: PANTANAL_BAIXO | B42: Conexão/Equipamento | C42: 16 | E42: DXF Projeto

Sheet TRECHOS_TODOS
A1: TRECHOS TODOS — 2238 trechos PV-a-PV consolidados (todos os saldos)
A3: TODOS OS TRECHOS — 2235 trechos | 6 nucleos saldo
A4: Filtro por nucleo/tipo/DN/status | STATUS amarelo = atualizar com cadastro execucao
A5: NUCLEO | B5: TIPO | C5: ID | D5: PV INI | E5: PV FIM | F5: EXT(m) | G5: DN | H5: MATERIAL | I5: PROF(m) | J5: ESCAV(m3) | K5: DECL | L5: STATUS
A6: CARLOS | B6: ESGOTO | C6: T-001 | D6: PI 68 | E6: PI 64 | F6: 26.32 | G6: 300 | H6: Tubo PVC | I6: 1.59 | J6: 33.41 | K6: 0.042819 | L6: PENDENTE
A7: CARLOS | B7: ESGOTO | C7: T-002 | D7: PI 62 | E7: PI 44 | F7: 10.45 | G7: 300 | H7: Tubo PVC | I7: 3.11 | J7: 26.01 | K7: 0.246632 | L7: PENDENTE
A8: CARLOS | B8: ESGOTO | C8: T-003 | D8: PI 44 | E8: PI 02 | F8: 8.28 | G8: 300 | H8: Tubo PVC | I8: 4.32 | J8: 28.6 | K8: 0.005809 | L8: PENDENTE
A9: CARLOS | B9: ESGOTO | C9: T-004 | D9: PI 06 | E9: PI 16 | F9: 35.86 | G9: 300 | H9: Tubo PVC | I9: 1.77 | J9: 50.66 | K9: 0.043422 | L9: PENDENTE
A10: CARLOS | B10: ESGOTO | C10: T-005 | D10: PI 62 | E10: PI 63 | F10: 12.77 | G10: 300 | H10: Tubo PVC | I10: 1.87 | J10: 19.07 | K10: 0.004049 | L10: PENDENTE
A11: CARLOS | B11: ESGOTO | C11: T-006 | D11: PI 64 | E11: PI 63 | F11: 9.35 | G11: 300 | H11: Tubo PVC | I11: 1.96 | J11: 14.69 | K11: 0.004963 | L11: PENDENTE
A12: CARLOS | B12: ESGOTO | C12: T-007 | D12: PI 16 | E12: PI 19 | F12: 8.4 | G12: 200 | H12: Tubo PVC | I12: 2.6 | J12: 17.48 | K12: 0.006167 | L12: PENDENTE
A13: CARLOS | B13: ESGOTO | C13: T-008 | D13: PI 118 | E13: PI 115 | F13: 13.75 | G13: 1000 | H13: Tubo de Concreto | I13: 0.73 | J13: 8.02 | K13: 0.037876 | L13: PENDENTE
A14: CARLOS | B14: ESGOTO | C14: T-009 | D14: PI 115 | E14: PI 113 | F14: 11.52 | G14: 1000 | H14: Tubo de Concreto | I14: 0.98 | J14: 9.06 | K14: 0.003403 | L14: PENDENTE
A15: CARLOS | B15: ESGOTO | C15: T-010 | D15: PI 68 | E15: PI 65 | F15: 10.76 | G15: 1000 | H15: Tubo de Concreto | I15: 0.69 | J15: 5.96 | K15: 0.059712 | L15: PENDENTE
A16: CARLOS | B16: ESGOTO | C16: T-011 | D16: PI 65 | E16: PI 64 | F16: 10.69 | G16: 1000 | H16: Tubo de Concreto | I16: 1.19 | J16: 10.21 | K16: 0.165529 | L16: PENDENTE
A17: CARLOS | B17: ESGOTO | C17: T-012 | D17: PI 64 | E17: PI 63 | F17: 9.38 | G17: 1000 | H17: Tubo de Concreto | I17: 1.96 | J17: 14.74 | K17: 0.004947 | L17: PENDENTE
... A2240: TETEU | B2240: ESGOTO | C2240: T-548 | D2240: PI 84 | E2240: PV 37 | F2240: 3.79 | G2240: 300 | H2240: Tubo PVC | I2240: 0.65 | J2240: 1.97 | K2240: 0.212269 | L2240: PENDENTE
A2241: TOTAL | F2241: 16383.41 | J2241: 11172.93

Sheet CURVA_S
A1: CURVA S — Linkada PROJETO/SALDO/MATERIAIS
A3: INDICADOR | B3: VALOR | C3: FONTE
A4: Extensão Projeto | B4: =PROJETO!D10 | C4: auto
A5: Executado | B5: =PROJETO!G10 | C5: auto
A6: Saldo | B6: =SALDO!D9 | C6: auto
A7: % Global | B7: =IF(PROJETO!D10>0,PROJETO!G10/PROJETO!D10,0) | C7: auto
A8: % Água | B8: =IF(PROJETO!B10>0,PROJETO!E10/PROJETO!B10,0) | C8: auto
A9: % Esgoto | B9: =IF(PROJETO!C10>0,PROJETO!F10/PROJETO!C10,0) | C9: auto
A10: Custo Executado | B10: =PROJETO!G10*910 | C10: auto
A11: Custo Saldo | B11: =SALDO!D9*910 | C11: auto
A12: Total Compras | B12: =MATERIAIS!I37 | C12: auto
A13: Pedido Mensal | B13: =PEDIDO_URGENTE!E19 | C13: auto

Sheet MEDICAO_MENSAL
A1: MEDIÇÃO MENSAL — Linkado ao PROJETO/SALDO
A3: NÚCLEO | B3: EXEC TOTAL | C3: MESES | D3: m/MÊS | E3: FAT MENSAL | F3: FAT SALDO | G3: EQ | H3: PESSOAS
A4: =PROJETO!A5 | B4: =PROJETO!G5 | C4: =PROJETO!H5 | D4: =IF(C4>0,B4/C4,0) | E4: =D4*910 | F4: =SALDO!D4*910 | G4: =PROJETO!I5 | H4: =G4*6
A5: =PROJETO!A6 | B5: =PROJETO!G6 | C5: =PROJETO!H6 | D5: =IF(C5>0,B5/C5,0) | E5: =D5*910 | F5: =SALDO!D5*910 | G5: =PROJETO!I6 | H5: =G5*6
A6: =PROJETO!A7 | B6: =PROJETO!G7 | C6: =PROJETO!H7 | D6: =IF(C6>0,B6/C6,0) | E6: =D6*910 | F6: =SALDO!D6*910 | G6: =PROJETO!I7 | H6: =G6*6
A7: =PROJETO!A8 | B7: =PROJETO!G8 | C7: =PROJETO!H8 | D7: =IF(C7>0,B7/C7,0) | E7: =D7*910 | F7: =SALDO!D7*910 | G7: =PROJETO!I8 | H7: =G7*6
A8: =PROJETO!A9 | B8: =PROJETO!G9 | C8: =PROJETO!H9 | D8: =IF(C8>0,B8/C8,0) | E8: =D8*910 | F8: =SALDO!D8*910 | G8: =PROJETO!I9 | H8: =G8*6
A9: TOTAL | B9: =SUM(B4:B8) | D9: =IF(C9>0,B9/C9,0) | E9: =D9*910 | F9: =SUM(F4:F8) | G9: =SUM(G4:G8) | H9: =SUM(H4:H8)

Sheet CRONO_COMPRAS
A1: CRONO COMPRAS — Linkado a MATERIAIS
A3: MATERIAL | B3: TOTAL | C3: LEAD | D3: Abr/26 | E3: Mai/26 | F3: Jun/26 | G3: Jul/26 | H3: Ago/26
A4: =MATERIAIS!A23 | B4: =MATERIAIS!H23 | C4: =MATERIAIS!F5 | D4: =B4/5 | E4: =B4/5 | F4: =B4/5 | G4: =B4/5 | H4: =B4/5
A5: =MATERIAIS!A24 | B5: =MATERIAIS!H24 | C5: =MATERIAIS!F6 | D5: =B5/5 | E5: =B5/5 | F5: =B5/5 | G5: =B5/5 | H5: =B5/5
A6: =MATERIAIS!A25 | B6: =MATERIAIS!H25 | C6: =MATERIAIS!F7 | D6: =B6/5 | E6: =B6/5 | F6: =B6/5 | G6: =B6/5 | H6: =B6/5
A7: =MATERIAIS!A26 | B7: =MATERIAIS!H26 | C7: =MATERIAIS!F8 | D7: =B7/5 | E7: =B7/5 | F7: =B7/5 | G7: =B7/5 | H7: =B7/5
A8: =MATERIAIS!A27 | B8: =MATERIAIS!H27 | C8: =MATERIAIS!F9 | D8: =B8/5 | E8: =B8/5 | F8: =B8/5 | G8: =B8/5 | H8: =B8/5
A9: =MATERIAIS!A28 | B9: =MATERIAIS!H28 | C9: =MATERIAIS!F10 | D9: =B9/5 | E9: =B9/5 | F9: =B9/5 | G9: =B9/5 | H9: =B9/5
A10: =MATERIAIS!A29 | B10: =MATERIAIS!H29 | C10: =MATERIAIS!F11 | D10: =B10/5 | E10: =B10/5 | F10: =B10/5 | G10: =B10/5 | H10: =B10/5
A11: =MATERIAIS!A30 | B11: =MATERIAIS!H30 | C11: =MATERIAIS!F12 | D11: =B11/5 | E11: =B11/5 | F11: =B11/5 | G11: =B11/5 | H11: =B11/5
A12: =MATERIAIS!A31 | B12: =MATERIAIS!H31 | C12: =MATERIAIS!F13 | D12: =B12/5 | E12: =B12/5 | F12: =B12/5 | G12: =B12/5 | H12: =B12/5
A13: =MATERIAIS!A32 | B13: =MATERIAIS!H32 | C13: =MATERIAIS!F14 | D13: =B13/5 | E13: =B13/5 | F13: =B13/5 | G13: =B13/5 | H13: =B13/5
A14: =MATERIAIS!A33 | B14: =MATERIAIS!H33 | C14: =MATERIAIS!F15 | D14: =B14/5 | E14: =B14/5 | F14: =B14/5 | G14: =B14/5 | H14: =B14/5
A15: =MATERIAIS!A34 | B15: =MATERIAIS!H34 | C15: =MATERIAIS!F16 | D15: =B15/5 | E15: =B15/5 | F15: =B15/5 | G15: =B15/5 | H15: =B15/5
... A17: =MATERIAIS!A36 | B17: =MATERIAIS!H36 | C17: =MATERIAIS!F18 | D17: =B17/5 | E17: =B17/5 | F17: =B17/5 | G17: =B17/5 | H17: =B17/5

Sheet MATERIAIS
A1: MATERIAIS A COMPRAR — SALDO × fatores | AMARELO = editável
A2: Muda fator ou preço → recalcula tudo automaticamente
A4: MATERIAL | B4: UN | C4: REDE | D4: FATOR(×m) | E4: P.UNIT(R$) | F4: meta
A5: Tubo PVC DN200 | B5: m | C5: ESG | D5: 0.6 | E5: 200.12 | F5: 3 sem
A6: Tubo PVC DN300 | B6: m | C6: ESG | D6: 0.4 | E6: 310 | F6: 3 sem
A7: Tubo PEAD DN63 | B7: m | C7: AG | D7: 0.7 | E7: 85 | F7: 4 sem
A8: Tubo PEAD DN110 | B8: m | C8: AG | D8: 0.3 | E8: 101.8 | F8: 4 sem
A9: PV concreto DN1200 | B9: un | C9: ESG | D9: 0.068 | E9: 3686 | F9: 2 sem
A10: PI plástico DN600 | B10: un | C10: ESG | D10: 0.022 | E10: 1412 | F10: 2 sem
A11: Caixa inspeção | B11: un | C11: ESG | D11: 0.055 | E11: 1034 | F11: 2 sem
A12: Sela eletrofusão | B12: un | C12: AG | D12: 0.022 | E12: 660 | F12: 2 sem
A13: Cavalete/hidrom. | B13: un | C13: AG | D13: 0.017 | E13: 490 | F13: 3 sem
A14: Areia berço | B14: m³ | C14: AMB | D14: 0.49 | E14: 160 | F14: 1 sem
A15: Brita base | B15: m³ | C15: AMB | D15: 0.22 | E15: 210 | F15: 1 sem
A16: Concreto | B16: m³ | C16: AMB | D16: 0.18 | E16: 720 | F16: 1 sem
... A18: Conexões diversas | B18: vb | C18: AMB | D18: 0.011 | E18: 120 | F18: 2 sem
A21: QTD POR NÚCLEO (fórmulas = SALDO × FATOR)
A22: MATERIAL | B22: REDE | C22: SM+JC | D22: ISRAEL | E22: TETEU | F22: CRIADORES | G22: PANTANAL | H22: TOTAL | I22: CUSTO TOTAL
A23: Tubo PVC DN200 | B23: ESG | C23: =MAX(0,SALDO!C4)*$D$5 | D23: =MAX(0,SALDO!C5)*$D$5 | E23: =MAX(0,SALDO!C6)*$D$5 | F23: =MAX(0,SALDO!C7)*$D$5 | G23: =MAX(0,SALDO!C8)*$D$5 | H23: =SUM(C23:G23) | I23: =H23*$E$5
A24: Tubo PVC DN300 | B24: ESG | C24: =MAX(0,SALDO!C4)*$D$6 | D24: =MAX(0,SALDO!C5)*$D$6 | E24: =MAX(0,SALDO!C6)*$D$6 | F24: =MAX(0,SALDO!C7)*$D$6 | G24: =MAX(0,SALDO!C8)*$D$6 | H24: =SUM(C24:G24) | I24: =H24*$E$6
A25: Tubo PEAD DN63 | B25: AG | C25: =MAX(0,SALDO!B4)*$D$7 | D25: =MAX(0,SALDO!B5)*$D$7 | E25: =MAX(0,SALDO!B6)*$D$7 | F25: =MAX(0,SALDO!B7)*$D$7 | G25: =MAX(0,SALDO!B8)*$D$7 | H25: =SUM(C25:G25) | I25: =H25*$E$7
A26: Tubo PEAD DN110 | B26: AG | C26: =MAX(0,SALDO!B4)*$D$8 | D26: =MAX(0,SALDO!B5)*$D$8 | E26: =MAX(0,SALDO!B6)*$D$8 | F26: =MAX(0,SALDO!B7)*$D$8 | G26: =MAX(0,SALDO!B8)*$D$8 | H26: =SUM(C26:G26) | I26: =H26*$E$8
A27: PV concreto DN1200 | B27: ESG | C27: =MAX(0,SALDO!C4)*$D$9 | D27: =MAX(0,SALDO!C5)*$D$9 | E27: =MAX(0,SALDO!C6)*$D$9 | F27: =MAX(0,SALDO!C7)*$D$9 | G27: =MAX(0,SALDO!C8)*$D$9 | H27: =SUM(C27:G27) | I27: =H27*$E$9
A28: PI plástico DN600 | B28: ESG | C28: =MAX(0,SALDO!C4)*$D$10 | D28: =MAX(0,SALDO!C5)*$D$10 | E28: =MAX(0,SALDO!C6)*$D$10 | F28: =MAX(0,SALDO!C7)*$D$10 | G28: =MAX(0,SALDO!C8)*$D$10 | H28: =SUM(C28:G28) | I28: =H28*$E$10
A29: Caixa inspeção | B29: ESG | C29: =MAX(0,SALDO!C4)*$D$11 | D29: =MAX(0,SALDO!C5)*$D$11 | E29: =MAX(0,SALDO!C6)*$D$11 | F29: =MAX(0,SALDO!C7)*$D$11 | G29: =MAX(0,SALDO!C8)*$D$11 | H29: =SUM(C29:G29) | I29: =H29*$E$11
A30: Sela eletrofusão | B30: AG | C30: =MAX(0,SALDO!B4)*$D$12 | D30: =MAX(0,SALDO!B5)*$D$12 | E30: =MAX(0,SALDO!B6)*$D$12 | F30: =MAX(0,SALDO!B7)*$D$12 | G30: =MAX(0,SALDO!B8)*$D$12 | H30: =SUM(C30:G30) | I30: =H30*$E$12
A31: Cavalete/hidrom. | B31: AG | C31: =MAX(0,SALDO!B4)*$D$13 | D31: =MAX(0,SALDO!B5)*$D$13 | E31: =MAX(0,SALDO!B6)*$D$13 | F31: =MAX(0,SALDO!B7)*$D$13 | G31: =MAX(0,SALDO!B8)*$D$13 | H31: =SUM(C31:G31) | I31: =H31*$E$13
A32: Areia berço | B32: AMB | C32: =MAX(0,SALDO!D4)*$D$14 | D32: =MAX(0,SALDO!D5)*$D$14 | E32: =MAX(0,SALDO!D6)*$D$14 | F32: =MAX(0,SALDO!D7)*$D$14 | G32: =MAX(0,SALDO!D8)*$D$14 | H32: =SUM(C32:G32) | I32: =H32*$E$14
A33: Brita base | B33: AMB | C33: =MAX(0,SALDO!D4)*$D$15 | D33: =MAX(0,SALDO!D5)*$D$15 | E33: =MAX(0,SALDO!D6)*$D$15 | F33: =MAX(0,SALDO!D7)*$D$15 | G33: =MAX(0,SALDO!D8)*$D$15 | H33: =SUM(C33:G33) | I33: =H33*$E$15
A34: Concreto | B34: AMB | C34: =MAX(0,SALDO!D4)*$D$16 | D34: =MAX(0,SALDO!D5)*$D$16 | E34: =MAX(0,SALDO!D6)*$D$16 | F34: =MAX(0,SALDO!D7)*$D$16 | G34: =MAX(0,SALDO!D8)*$D$16 | H34: =SUM(C34:G34) | I34: =H34*$E$16
A35: CBUQ repavim. | B35: AMB | C35: =MAX(0,SALDO!D4)*$D$17 | D35: =MAX(0,SALDO!D5)*$D$17 | E35: =MAX(0,SALDO!D6)*$D$17 | F35: =MAX(0,SALDO!D7)*$D$17 | G35: =MAX(0,SALDO!D8)*$D$17 | H35: =SUM(C35:G35) | I35: =H35*$E$17
A36: Conexões diversas | B36: AMB | C36: =MAX(0,SALDO!D4)*$D$18 | D36: =MAX(0,SALDO!D5)*$D$18 | E36: =MAX(0,SALDO!D6)*$D$18 | F36: =MAX(0,SALDO!D7)*$D$18 | G36: =MAX(0,SALDO!D8)*$D$18 | H36: =SUM(C36:G36) | I36: =H36*$E$18
A37: TOTAL COMPRAS | I37: =SUM(I23:I36)

Sheet COMPRAS_MENSAL
A1: PROJEÇÃO MENSAL — Saldo ÷ meses | Puxa de MATERIAIS e PROJETO
A3: =PROJETO!A5 | B3: Meses: | C3: =PROJETO!H5
A4: MATERIAL | B4: SALDO | C4: Abr/26 | D4: Mai/26 | E4: Jun/26 | F4: Jul/26 | G4: CUSTO/MÊS
A5: =MATERIAIS!A23 | B5: =MATERIAIS!C23 | C5: =IF(PROJETO!H5>0,B5/MIN(PROJETO!H5,4),0) | D5: =IF(PROJETO!H5>0,B5/MIN(PROJETO!H5,4),0) | E5: =IF(PROJETO!H5>0,B5/MIN(PROJETO!H5,4),0) | F5: =IF(PROJETO!H5>0,B5/MIN(PROJETO!H5,4),0) | G5: =C5*MATERIAIS!$E$5
A6: =MATERIAIS!A24 | B6: =MATERIAIS!C24 | C6: =IF(PROJETO!H5>0,B6/MIN(PROJETO!H5,4),0) | D6: =IF(PROJETO!H5>0,B6/MIN(PROJETO!H5,4),0) | E6: =IF(PROJETO!H5>0,B6/MIN(PROJETO!H5,4),0) | F6: =IF(PROJETO!H5>0,B6/MIN(PROJETO!H5,4),0) | G6: =C6*MATERIAIS!$E$6
A7: =MATERIAIS!A25 | B7: =MATERIAIS!C25 | C7: =IF(PROJETO!H5>0,B7/MIN(PROJETO!H5,4),0) | D7: =IF(PROJETO!H5>0,B7/MIN(PROJETO!H5,4),0) | E7: =IF(PROJETO!H5>0,B7/MIN(PROJETO!H5,4),0) | F7: =IF(PROJETO!H5>0,B7/MIN(PROJETO!H5,4),0) | G7: =C7*MATERIAIS!$E$7
A8: =MATERIAIS!A26 | B8: =MATERIAIS!C26 | C8: =IF(PROJETO!H5>0,B8/MIN(PROJETO!H5,4),0) | D8: =IF(PROJETO!H5>0,B8/MIN(PROJETO!H5,4),0) | E8: =IF(PROJETO!H5>0,B8/MIN(PROJETO!H5,4),0) | F8: =IF(PROJETO!H5>0,B8/MIN(PROJETO!H5,4),0) | G8: =C8*MATERIAIS!$E$8
A9: =MATERIAIS!A27 | B9: =MATERIAIS!C27 | C9: =IF(PROJETO!H5>0,B9/MIN(PROJETO!H5,4),0) | D9: =IF(PROJETO!H5>0,B9/MIN(PROJETO!H5,4),0) | E9: =IF(PROJETO!H5>0,B9/MIN(PROJETO!H5,4),0) | F9: =IF(PROJETO!H5>0,B9/MIN(PROJETO!H5,4),0) | G9: =C9*MATERIAIS!$E$9
A10: =MATERIAIS!A28 | B10: =MATERIAIS!C28 | C10: =IF(PROJETO!H5>0,B10/MIN(PROJETO!H5,4),0) | D10: =IF(PROJETO!H5>0,B10/MIN(PROJETO!H5,4),0) | E10: =IF(PROJETO!H5>0,B10/MIN(PROJETO!H5,4),0) | F10: =IF(PROJETO!H5>0,B10/MIN(PROJETO!H5,4),0) | G10: =C10*MATERIAIS!$E$10
A11: =MATERIAIS!A29 | B11: =MATERIAIS!C29 | C11: =IF(PROJETO!H5>0,B11/MIN(PROJETO!H5,4),0) | D11: =IF(PROJETO!H5>0,B11/MIN(PROJETO!H5,4),0) | E11: =IF(PROJETO!H5>0,B11/MIN(PROJETO!H5,4),0) | F11: =IF(PROJETO!H5>0,B11/MIN(PROJETO!H5,4),0) | G11: =C11*MATERIAIS!$E$11
A12: =MATERIAIS!A30 | B12: =MATERIAIS!C30 | C12: =IF(PROJETO!H5>0,B12/MIN(PROJETO!H5,4),0) | D12: =IF(PROJETO!H5>0,B12/MIN(PROJETO!H5,4),0) | E12: =IF(PROJETO!H5>0,B12/MIN(PROJETO!H5,4),0) | F12: =IF(PROJETO!H5>0,B12/MIN(PROJETO!H5,4),0) | G12: =C12*MATERIAIS!$E$12
A13: =MATERIAIS!A31 | B13: =MATERIAIS!C31 | C13: =IF(PROJETO!H5>0,B13/MIN(PROJETO!H5,4),0) | D13: =IF(PROJETO!H5>0,B13/MIN(PROJETO!H5,4),0) | E13: =IF(PROJETO!H5>0,B13/MIN(PROJETO!H5,4),0) | F13: =IF(PROJETO!H5>0,B13/MIN(PROJETO!H5,4),0) | G13: =C13*MATERIAIS!$E$13
A14: =MATERIAIS!A32 | B14: =MATERIAIS!C32 | C14: =IF(PROJETO!H5>0,B14/MIN(PROJETO!H5,4),0) | D14: =IF(PROJETO!H5>0,B14/MIN(PROJETO!H5,4),0) | E14: =IF(PROJETO!H5>0,B14/MIN(PROJETO!H5,4),0) | F14: =IF(PROJETO!H5>0,B14/MIN(PROJETO!H5,4),0) | G14: =C14*MATERIAIS!$E$14
A15: =MATERIAIS!A33 | B15: =MATERIAIS!C33 | C15: =IF(PROJETO!H5>0,B15/MIN(PROJETO!H5,4),0) | D15: =IF(PROJETO!H5>0,B15/MIN(PROJETO!H5,4),0) | E15: =IF(PROJETO!H5>0,B15/MIN(PROJETO!H5,4),0) | F15: =IF(PROJETO!H5>0,B15/MIN(PROJETO!H5,4),0) | G15: =C15*MATERIAIS!$E$15
A16: =MATERIAIS!A34 | B16: =MATERIAIS!C34 | C16: =IF(PROJETO!H5>0,B16/MIN(PROJETO!H5,4),0) | D16: =IF(PROJETO!H5>0,B16/MIN(PROJETO!H5,4),0) | E16: =IF(PROJETO!H5>0,B16/MIN(PROJETO!H5,4),0) | F16: =IF(PROJETO!H5>0,B16/MIN(PROJETO!H5,4),0) | G16: =C16*MATERIAIS!$E$16
A17: =MATERIAIS!A35 | B17: =MATERIAIS!C35 | C17: =IF(PROJETO!H5>0,B17/MIN(PROJETO!H5,4),0) | D17: =IF(PROJETO!H5>0,B17/MIN(PROJETO!H5,4),0) | E17: =IF(PROJETO!H5>0,B17/MIN(PROJETO!H5,4),0) | F17: =IF(PROJETO!H5>0,B17/MIN(PROJETO!H5,4),0) | G17: =C17*MATERIAIS!$E$17
A18: =MATERIAIS!A36 | B18: =MATERIAIS!C36 | C18: =IF(PROJETO!H5>0,B18/MIN(PROJETO!H5,4),0) | D18: =IF(PROJETO!H5>0,B18/MIN(PROJETO!H5,4),0) | E18: =IF(PROJETO!H5>0,B18/MIN(PROJETO!H5,4),0) | F18: =IF(PROJETO!H5>0,B18/MIN(PROJETO!H5,4),0) | G18: =C18*MATERIAIS!$E$18
A20: =PROJETO!A6 | B20: Meses: | C20: =PROJETO!H6
A21: MATERIAL | B21: SALDO | C21: Abr/26 | D21: Mai/26 | E21: Jun/26 | F21: Jul/26 | G21: CUSTO/MÊS
A22: =MATERIAIS!A23 | B22: =MATERIAIS!D23 | C22: =IF(PROJETO!H6>0,B22/MIN(PROJETO!H6,4),0) | D22: =IF(PROJETO!H6>0,B22/MIN(PROJETO!H6,4),0) | E22: =IF(PROJETO!H6>0,B22/MIN(PROJETO!H6,4),0) | F22: =IF(PROJETO!H6>0,B22/MIN(PROJETO!H6,4),0) | G22: =C22*MATERIAIS!$E$5
A23: =MATERIAIS!A24 | B23: =MATERIAIS!D24 | C23: =IF(PROJETO!H6>0,B23/MIN(PROJETO!H6,4),0) | D23: =IF(PROJETO!H6>0,B23/MIN(PROJETO!H6,4),0) | E23: =IF(PROJETO!H6>0,B23/MIN(PROJETO!H6,4),0) | F23: =IF(PROJETO!H6>0,B23/MIN(PROJETO!H6,4),0) | G23: =C23*MATERIAIS!$E$6
A24: =MATERIAIS!A25 | B24: =MATERIAIS!D25 | C24: =IF(PROJETO!H6>0,B24/MIN(PROJETO!H6,4),0) | D24: =IF(PROJETO!H6>0,B24/MIN(PROJETO!H6,4),0) | E24: =IF(PROJETO!H6>0,B24/MIN(PROJETO!H6,4),0) | F24: =IF(PROJETO!H6>0,B24/MIN(PROJETO!H6,4),0) | G24: =C24*MATERIAIS!$E$7
A25: =MATERIAIS!A26 | B25: =MATERIAIS!D26 | C25: =IF(PROJETO!H6>0,B25/MIN(PROJETO!H6,4),0) | D25: =IF(PROJETO!H6>0,B25/MIN(PROJETO!H6,4),0) | E25: =IF(PROJETO!H6>0,B25/MIN(PROJETO!H6,4),0) | F25: =IF(PROJETO!H6>0,B25/MIN(PROJETO!H6,4),0) | G25: =C25*MATERIAIS!$E$8
A26: =MATERIAIS!A27 | B26: =MATERIAIS!D27 | C26: =IF(PROJETO!H6>0,B26/MIN(PROJETO!H6,4),0) | D26: =IF(PROJETO!H6>0,B26/MIN(PROJETO!H6,4),0) | E26: =IF(PROJETO!H6>0,B26/MIN(PROJETO!H6,4),0) | F26: =IF(PROJETO!H6>0,B26/MIN(PROJETO!H6,4),0) | G26: =C26*MATERIAIS!$E$9
A27: =MATERIAIS!A28 | B27: =MATERIAIS!D28 | C27: =IF(PROJETO!H6>0,B27/MIN(PROJETO!H6,4),0) | D27: =IF(PROJETO!H6>0,B27/MIN(PROJETO!H6,4),0) | E27: =IF(PROJETO!H6>0,B27/MIN(PROJETO!H6,4),0) | F27: =IF(PROJETO!H6>0,B27/MIN(PROJETO!H6,4),0) | G27: =C27*MATERIAIS!$E$10
A28: =MATERIAIS!A29 | B28: =MATERIAIS!D29 | C28: =IF(PROJETO!H6>0,B28/MIN(PROJETO!H6,4),0) | D28: =IF(PROJETO!H6>0,B28/MIN(PROJETO!H6,4),0) | E28: =IF(PROJETO!H6>0,B28/MIN(PROJETO!H6,4),0) | F28: =IF(PROJETO!H6>0,B28/MIN(PROJETO!H6,4),0) | G28: =C28*MATERIAIS!$E$11
A29: =MATERIAIS!A30 | B29: =MATERIAIS!D30 | C29: =IF(PROJETO!H6>0,B29/MIN(PROJETO!H6,4),0) | D29: =IF(PROJETO!H6>0,B29/MIN(PROJETO!H6,4),0) | E29: =IF(PROJETO!H6>0,B29/MIN(PROJETO!H6,4),0) | F29: =IF(PROJETO!H6>0,B29/MIN(PROJETO!H6,4),0) | G29: =C29*MATERIAIS!$E$12
A30: =MATERIAIS!A31 | B30: =MATERIAIS!D31 | C30: =IF(PROJETO!H6>0,B30/MIN(PROJETO!H6,4),0) | D30: =IF(PROJETO!H6>0,B30/MIN(PROJETO!H6,4),0) | E30: =IF(PROJETO!H6>0,B30/MIN(PROJETO!H6,4),0) | F30: =IF(PROJETO!H6>0,B30/MIN(PROJETO!H6,4),0) | G30: =C30*MATERIAIS!$E$13
A31: =MATERIAIS!A32 | B31: =MATERIAIS!D32 | C31: =IF(PROJETO!H6>0,B31/MIN(PROJETO!H6,4),0) | D31: =IF(PROJETO!H6>0,B31/MIN(PROJETO!H6,4),0) | E31: =IF(PROJETO!H6>0,B31/MIN(PROJETO!H6,4),0) | F31: =IF(PROJETO!H6>0,B31/MIN(PROJETO!H6,4),0) | G31: =C31*MATERIAIS!$E$14
A32: =MATERIAIS!A33 | B32: =MATERIAIS!D33 | C32: =IF(PROJETO!H6>0,B32/MIN(PROJETO!H6,4),0) | D32: =IF(PROJETO!H6>0,B32/MIN(PROJETO!H6,4),0) | E32: =IF(PROJETO!H6>0,B32/MIN(PROJETO!H6,4),0) | F32: =IF(PROJETO!H6>0,B32/MIN(PROJETO!H6,4),0) | G32: =C32*MATERIAIS!$E$15
A33: =MATERIAIS!A34 | B33: =MATERIAIS!D34 | C33: =IF(PROJETO!H6>0,B33/MIN(PROJETO!H6,4),0) | D33: =IF(PROJETO!H6>0,B33/MIN(PROJETO!H6,4),0) | E33: =IF(PROJETO!H6>0,B33/MIN(PROJETO!H6,4),0) | F33: =IF(PROJETO!H6>0,B33/MIN(PROJETO!H6,4),0) | G33: =C33*MATERIAIS!$E$16
A34: =MATERIAIS!A35 | B34: =MATERIAIS!D35 | C34: =IF(PROJETO!H6>0,B34/MIN(PROJETO!H6,4),0) | D34: =IF(PROJETO!H6>0,B34/MIN(PROJETO!H6,4),0) | E34: =IF(PROJETO!H6>0,B34/MIN(PROJETO!H6,4),0) | F34: =IF(PROJETO!H6>0,B34/MIN(PROJETO!H6,4),0) | G34: =C34*MATERIAIS!$E$17
A35: =MATERIAIS!A36 | B35: =MATERIAIS!D36 | C35: =IF(PROJETO!H6>0,B35/MIN(PROJETO!H6,4),0) | D35: =IF(PROJETO!H6>0,B35/MIN(PROJETO!H6,4),0) | E35: =IF(PROJETO!H6>0,B35/MIN(PROJETO!H6,4),0) | F35: =IF(PROJETO!H6>0,B35/MIN(PROJETO!H6,4),0) | G35: =C35*MATERIAIS!$E$18
A37: =PROJETO!A7 | B37: Meses: | C37: =PROJETO!H7
A38: MATERIAL | B38: SALDO | C38: Abr/26 | D38: Mai/26 | E38: Jun/26 | F38: Jul/26 | G38: CUSTO/MÊS
A39: =MATERIAIS!A23 | B39: =MATERIAIS!E23 | C39: =IF(PROJETO!H7>0,B39/MIN(PROJETO!H7,4),0) | D39: =IF(PROJETO!H7>0,B39/MIN(PROJETO!H7,4),0) | E39: =IF(PROJETO!H7>0,B39/MIN(PROJETO!H7,4),0) | F39: =IF(PROJETO!H7>0,B39/MIN(PROJETO!H7,4),0) | G39: =C39*MATERIAIS!$E$5
A40: =MATERIAIS!A24 | B40: =MATERIAIS!E24 | C40: =IF(PROJETO!H7>0,B40/MIN(PROJETO!H7,4),0) | D40: =IF(PROJETO!H7>0,B40/MIN(PROJETO!H7,4),0) | E40: =IF(PROJETO!H7>0,B40/MIN(PROJETO!H7,4),0) | F40: =IF(PROJETO!H7>0,B40/MIN(PROJETO!H7,4),0) | G40: =C40*MATERIAIS!$E$6
A41: =MATERIAIS!A25 | B41: =MATERIAIS!E25 | C41: =IF(PROJETO!H7>0,B41/MIN(PROJETO!H7,4),0) | D41: =IF(PROJETO!H7>0,B41/MIN(PROJETO!H7,4),0) | E41: =IF(PROJETO!H7>0,B41/MIN(PROJETO!H7,4),0) | F41: =IF(PROJETO!H7>0,B41/MIN(PROJETO!H7,4),0) | G41: =C41*MATERIAIS!$E$7
A42: =MATERIAIS!A26 | B42: =MATERIAIS!E26 | C42: =IF(PROJETO!H7>0,B42/MIN(PROJETO!H7,4),0) | D42: =IF(PROJETO!H7>0,B42/MIN(PROJETO!H7,4),0) | E42: =IF(PROJETO!H7>0,B42/MIN(PROJETO!H7,4),0) | F42: =IF(PROJETO!H7>0,B42/MIN(PROJETO!H7,4),0) | G42: =C42*MATERIAIS!$E$8
A43: =MATERIAIS!A27 | B43: =MATERIAIS!E27 | C43: =IF(PROJETO!H7>0,B43/MIN(PROJETO!H7,4),0) | D43: =IF(PROJETO!H7>0,B43/MIN(PROJETO!H7,4),0) | E43: =IF(PROJETO!H7>0,B43/MIN(PROJETO!H7,4),0) | F43: =IF(PROJETO!H7>0,B43/MIN(PROJETO!H7,4),0) | G43: =C43*MATERIAIS!$E$9
A44: =MATERIAIS!A28 | B44: =MATERIAIS!E28 | C44: =IF(PROJETO!H7>0,B44/MIN(PROJETO!H7,4),0) | D44: =IF(PROJETO!H7>0,B44/MIN(PROJETO!H7,4),0) | E44: =IF(PROJETO!H7>0,B44/MIN(PROJETO!H7,4),0) | F44: =IF(PROJETO!H7>0,B44/MIN(PROJETO!H7,4),0) | G44: =C44*MATERIAIS!$E$10
A45: =MATERIAIS!A29 | B45: =MATERIAIS!E29 | C45: =IF(PROJETO!H7>0,B45/MIN(PROJETO!H7,4),0) | D45: =IF(PROJETO!H7>0,B45/MIN(PROJETO!H7,4),0) | E45: =IF(PROJETO!H7>0,B45/MIN(PROJETO!H7,4),0) | F45: =IF(PROJETO!H7>0,B45/MIN(PROJETO!H7,4),0) | G45: =C45*MATERIAIS!$E$11
A46: =MATERIAIS!A30 | B46: =MATERIAIS!E30 | C46: =IF(PROJETO!H7>0,B46/MIN(PROJETO!H7,4),0) | D46: =IF(PROJETO!H7>0,B46/MIN(PROJETO!H7,4),0) | E46: =IF(PROJETO!H7>0,B46/MIN(PROJETO!H7,4),0) | F46: =IF(PROJETO!H7>0,B46/MIN(PROJETO!H7,4),0) | G46: =C46*MATERIAIS!$E$12
A47: =MATERIAIS!A31 | B47: =MATERIAIS!E31 | C47: =IF(PROJETO!H7>0,B47/MIN(PROJETO!H7,4),0) | D47: =IF(PROJETO!H7>0,B47/MIN(PROJETO!H7,4),0) | E47: =IF(PROJETO!H7>0,B47/MIN(PROJETO!H7,4),0) | F47: =IF(PROJETO!H7>0,B47/MIN(PROJETO!H7,4),0) | G47: =C47*MATERIAIS!$E$13
A48: =MATERIAIS!A32 | B48: =MATERIAIS!E32 | C48: =IF(PROJETO!H7>0,B48/MIN(PROJETO!H7,4),0) | D48: =IF(PROJETO!H7>0,B48/MIN(PROJETO!H7,4),0) | E48: =IF(PROJETO!H7>0,B48/MIN(PROJETO!H7,4),0) | F48: =IF(PROJETO!H7>0,B48/MIN(PROJETO!H7,4),0) | G48: =C48*MATERIAIS!$E$14
A49: =MATERIAIS!A33 | B49: =MATERIAIS!E33 | C49: =IF(PROJETO!H7>0,B49/MIN(PROJETO!H7,4),0) | D49: =IF(PROJETO!H7>0,B49/MIN(PROJETO!H7,4),0) | E49: =IF(PROJETO!H7>0,B49/MIN(PROJETO!H7,4),0) | F49: =IF(PROJETO!H7>0,B49/MIN(PROJETO!H7,4),0) | G49: =C49*MATERIAIS!$E$15
A50: =MATERIAIS!A34 | B50: =MATERIAIS!E34 | C50: =IF(PROJETO!H7>0,B50/MIN(PROJETO!H7,4),0) | D50: =IF(PROJETO!H7>0,B50/MIN(PROJETO!H7,4),0) | E50: =IF(PROJETO!H7>0,B50/MIN(PROJETO!H7,4),0) | F50: =IF(PROJETO!H7>0,B50/MIN(PROJETO!H7,4),0) | G50: =C50*MATERIAIS!$E$16
A51: =MATERIAIS!A35 | B51: =MATERIAIS!E35 | C51: =IF(PROJETO!H7>0,B51/MIN(PROJETO!H7,4),0) | D51: =IF(PROJETO!H7>0,B51/MIN(PROJETO!H7,4),0) | E51: =IF(PROJETO!H7>0,B51/MIN(PROJETO!H7,4),0) | F51: =IF(PROJETO!H7>0,B51/MIN(PROJETO!H7,4),0) | G51: =C51*MATERIAIS!$E$17
A52: =MATERIAIS!A36 | B52: =MATERIAIS!E36 | C52: =IF(PROJETO!H7>0,B52/MIN(PROJETO!H7,4),0) | D52: =IF(PROJETO!H7>0,B52/MIN(PROJETO!H7,4),0) | E52: =IF(PROJETO!H7>0,B52/MIN(PROJETO!H7,4),0) | F52: =IF(PROJETO!H7>0,B52/MIN(PROJETO!H7,4),0) | G52: =C52*MATERIAIS!$E$18
A54: =PROJETO!A8 | B54: Meses: | C54: =PROJETO!H8
A55: MATERIAL | B55: SALDO | C55: Abr/26 | D55: Mai/26 | E55: Jun/26 | F55: Jul/26 | G55: CUSTO/MÊS
A56: =MATERIAIS!A23 | B56: =MATERIAIS!F23 | C56: =IF(PROJETO!H8>0,B56/MIN(PROJETO!H8,4),0) | D56: =IF(PROJETO!H8>0,B56/MIN(PROJETO!H8,4),0) | E56: =IF(PROJETO!H8>0,B56/MIN(PROJETO!H8,4),0) | F56: =IF(PROJETO!H8>0,B56/MIN(PROJETO!H8,4),0) | G56: =C56*MATERIAIS!$E$5
A57: =MATERIAIS!A24 | B57: =MATERIAIS!F24 | C57: =IF(PROJETO!H8>0,B57/MIN(PROJETO!H8,4),0) | D57: =IF(PROJETO!H8>0,B57/MIN(PROJETO!H8,4),0) | E57: =IF(PROJETO!H8>0,B57/MIN(PROJETO!H8,4),0) | F57: =IF(PROJETO!H8>0,B57/MIN(PROJETO!H8,4),0) | G57: =C57*MATERIAIS!$E$6
A58: =MATERIAIS!A25 | B58: =MATERIAIS!F25 | C58: =IF(PROJETO!H8>0,B58/MIN(PROJETO!H8,4),0) | D58: =IF(PROJETO!H8>0,B58/MIN(PROJETO!H8,4),0) | E58: =IF(PROJETO!H8>0,B58/MIN(PROJETO!H8,4),0) | F58: =IF(PROJETO!H8>0,B58/MIN(PROJETO!H8,4),0) | G58: =C58*MATERIAIS!$E$7
A59: =MATERIAIS!A26 | B59: =MATERIAIS!F26 | C59: =IF(PROJETO!H8>0,B59/MIN(PROJETO!H8,4),0) | D59: =IF(PROJETO!H8>0,B59/MIN(PROJETO!H8,4),0) | E59: =IF(PROJETO!H8>0,B59/MIN(PROJETO!H8,4),0) | F59: =IF(PROJETO!H8>0,B59/MIN(PROJETO!H8,4),0) | G59: =C59*MATERIAIS!$E$8
A60: =MATERIAIS!A27 | B60: =MATERIAIS!F27 | C60: =IF(PROJETO!H8>0,B60/MIN(PROJETO!H8,4),0) | D60: =IF(PROJETO!H8>0,B60/MIN(PROJETO!H8,4),0) | E60: =IF(PROJETO!H8>0,B60/MIN(PROJETO!H8,4),0) | F60: =IF(PROJETO!H8>0,B60/MIN(PROJETO!H8,4),0) | G60: =C60*MATERIAIS!$E$9
A61: =MATERIAIS!A28 | B61: =MATERIAIS!F28 | C61: =IF(PROJETO!H8>0,B61/MIN(PROJETO!H8,4),0) | D61: =IF(PROJETO!H8>0,B61/MIN(PROJETO!H8,4),0) | E61: =IF(PROJETO!H8>0,B61/MIN(PROJETO!H8,4),0) | F61: =IF(PROJETO!H8>0,B61/MIN(PROJETO!H8,4),0) | G61: =C61*MATERIAIS!$E$10
A62: =MATERIAIS!A29 | B62: =MATERIAIS!F29 | C62: =IF(PROJETO!H8>0,B62/MIN(PROJETO!H8,4),0) | D62: =IF(PROJETO!H8>0,B62/MIN(PROJETO!H8,4),0) | E62: =IF(PROJETO!H8>0,B62/MIN(PROJETO!H8,4),0) | F62: =IF(PROJETO!H8>0,B62/MIN(PROJETO!H8,4),0) | G62: =C62*MATERIAIS!$E$11
A63: =MATERIAIS!A30 | B63: =MATERIAIS!F30 | C63: =IF(PROJETO!H8>0,B63/MIN(PROJETO!H8,4),0) | D63: =IF(PROJETO!H8>0,B63/MIN(PROJETO!H8,4),0) | E63: =IF(PROJETO!H8>0,B63/MIN(PROJETO!H8,4),0) | F63: =IF(PROJETO!H8>0,B63/MIN(PROJETO!H8,4),0) | G63: =C63*MATERIAIS!$E$12
A64: =MATERIAIS!A31 | B64: =MATERIAIS!F31 | C64: =IF(PROJETO!H8>0,B64/MIN(PROJETO!H8,4),0) | D64: =IF(PROJETO!H8>0,B64/MIN(PROJETO!H8,4),0) | E64: =IF(PROJETO!H8>0,B64/MIN(PROJETO!H8,4),0) | F64: =IF(PROJETO!H8>0,B64/MIN(PROJETO!H8,4),0) | G64: =C64*MATERIAIS!$E$13
A65: =MATERIAIS!A32 | B65: =MATERIAIS!F32 | C65: =IF(PROJETO!H8>0,B65/MIN(PROJETO!H8,4),0) | D65: =IF(PROJETO!H8>0,B65/MIN(PROJETO!H8,4),0) | E65: =IF(PROJETO!H8>0,B65/MIN(PROJETO!H8,4),0) | F65: =IF(PROJETO!H8>0,B65/MIN(PROJETO!H8,4),0) | G65: =C65*MATERIAIS!$E$14
A66: =MATERIAIS!A33 | B66: =MATERIAIS!F33 | C66: =IF(PROJETO!H8>0,B66/MIN(PROJETO!H8,4),0) | D66: =IF(PROJETO!H8>0,B66/MIN(PROJETO!H8,4),0) | E66: =IF(PROJETO!H8>0,B66/MIN(PROJETO!H8,4),0) | F66: =IF(PROJETO!H8>0,B66/MIN(PROJETO!H8,4),0) | G66: =C66*MATERIAIS!$E$15
A67: =MATERIAIS!A34 | B67: =MATERIAIS!F34 | C67: =IF(PROJETO!H8>0,B67/MIN(PROJETO!H8,4),0) | D67: =IF(PROJETO!H8>0,B67/MIN(PROJETO!H8,4),0) | E67: =IF(PROJETO!H8>0,B67/MIN(PROJETO!H8,4),0) | F67: =IF(PROJETO!H8>0,B67/MIN(PROJETO!H8,4),0) | G67: =C67*MATERIAIS!$E$16
A68: =MATERIAIS!A35 | B68: =MATERIAIS!F35 | C68: =IF(PROJETO!H8>0,B68/MIN(PROJETO!H8,4),0) | D68: =IF(PROJETO!H8>0,B68/MIN(PROJETO!H8,4),0) | E68: =IF(PROJETO!H8>0,B68/MIN(PROJETO!H8,4),0) | F68: =IF(PROJETO!H8>0,B68/MIN(PROJETO!H8,4),0) | G68: =C68*MATERIAIS!$E$17
A69: =MATERIAIS!A36 | B69: =MATERIAIS!F36 | C69: =IF(PROJETO!H8>0,B69/MIN(PROJETO!H8,4),0) | D69: =IF(PROJETO!H8>0,B69/MIN(PROJETO!H8,4),0) | E69: =IF(PROJETO!H8>0,B69/MIN(PROJETO!H8,4),0) | F69: =IF(PROJETO!H8>0,B69/MIN(PROJETO!H8,4),0) | G69: =C69*MATERIAIS!$E$18
A71: =PROJETO!A9 | B71: Meses: | C71: =PROJETO!H9
A72: MATERIAL | B72: SALDO | C72: Abr/26 | D72: Mai/26 | E72: Jun/26 | F72: Jul/26 | G72: CUSTO/MÊS
A73: =MATERIAIS!A23 | B73: =MATERIAIS!G23 | C73: =IF(PROJETO!H9>0,B73/MIN(PROJETO!H9,4),0) | D73: =IF(PROJETO!H9>0,B73/MIN(PROJETO!H9,4),0) | E73: =IF(PROJETO!H9>0,B73/MIN(PROJETO!H9,4),0) | F73: =IF(PROJETO!H9>0,B73/MIN(PROJETO!H9,4),0) | G73: =C73*MATERIAIS!$E$5
A74: =MATERIAIS!A24 | B74: =MATERIAIS!G24 | C74: =IF(PROJETO!H9>0,B74/MIN(PROJETO!H9,4),0) | D74: =IF(PROJETO!H9>0,B74/MIN(PROJETO!H9,4),0) | E74: =IF(PROJETO!H9>0,B74/MIN(PROJETO!H9,4),0) | F74: =IF(PROJETO!H9>0,B74/MIN(PROJETO!H9,4),0) | G74: =C74*MATERIAIS!$E$6
A75: =MATERIAIS!A25 | B75: =MATERIAIS!G25 | C75: =IF(PROJETO!H9>0,B75/MIN(PROJETO!H9,4),0) | D75: =IF(PROJETO!H9>0,B75/MIN(PROJETO!H9,4),0) | E75: =IF(PROJETO!H9>0,B75/MIN(PROJETO!H9,4),0) | F75: =IF(PROJETO!H9>0,B75/MIN(PROJETO!H9,4),0) | G75: =C75*MATERIAIS!$E$7
A76: =MATERIAIS!A26 | B76: =MATERIAIS!G26 | C76: =IF(PROJETO!H9>0,B76/MIN(PROJETO!H9,4),0) | D76: =IF(PROJETO!H9>0,B76/MIN(PROJETO!H9,4),0) | E76: =IF(PROJETO!H9>0,B76/MIN(PROJETO!H9,4),0) | F76: =IF(PROJETO!H9>0,B76/MIN(PROJETO!H9,4),0) | G76: =C76*MATERIAIS!$E$8
A77: =MATERIAIS!A27 | B77: =MATERIAIS!G27 | C77: =IF(PROJETO!H9>0,B77/MIN(PROJETO!H9,4),0) | D77: =IF(PROJETO!H9>0,B77/MIN(PROJETO!H9,4),0) | E77: =IF(PROJETO!H9>0,B77/MIN(PROJETO!H9,4),0) | F77: =IF(PROJETO!H9>0,B77/MIN(PROJETO!H9,4),0) | G77: =C77*MATERIAIS!$E$9
A78: =MATERIAIS!A28 | B78: =MATERIAIS!G28 | C78: =IF(PROJETO!H9>0,B78/MIN(PROJETO!H9,4),0) | D78: =IF(PROJETO!H9>0,B78/MIN(PROJETO!H9,4),0) | E78: =IF(PROJETO!H9>0,B78/MIN(PROJETO!H9,4),0) | F78: =IF(PROJETO!H9>0,B78/MIN(PROJETO!H9,4),0) | G78: =C78*MATERIAIS!$E$10
A79: =MATERIAIS!A29 | B79: =MATERIAIS!G29 | C79: =IF(PROJETO!H9>0,B79/MIN(PROJETO!H9,4),0) | D79: =IF(PROJETO!H9>0,B79/MIN(PROJETO!H9,4),0) | E79: =IF(PROJETO!H9>0,B79/MIN(PROJETO!H9,4),0) | F79: =IF(PROJETO!H9>0,B79/MIN(PROJETO!H9,4),0) | G79: =C79*MATERIAIS!$E$11
A80: =MATERIAIS!A30 | B80: =MATERIAIS!G30 | C80: =IF(PROJETO!H9>0,B80/MIN(PROJETO!H9,4),0) | D80: =IF(PROJETO!H9>0,B80/MIN(PROJETO!H9,4),0) | E80: =IF(PROJETO!H9>0,B80/MIN(PROJETO!H9,4),0) | F80: =IF(PROJETO!H9>0,B80/MIN(PROJETO!H9,4),0) | G80: =C80*MATERIAIS!$E$12
A81: =MATERIAIS!A31 | B81: =MATERIAIS!G31 | C81: =IF(PROJETO!H9>0,B81/MIN(PROJETO!H9,4),0) | D81: =IF(PROJETO!H9>0,B81/MIN(PROJETO!H9,4),0) | E81: =IF(PROJETO!H9>0,B81/MIN(PROJETO!H9,4),0) | F81: =IF(PROJETO!H9>0,B81/MIN(PROJETO!H9,4),0) | G81: =C81*MATERIAIS!$E$13
A82: =MATERIAIS!A32 | B82: =MATERIAIS!G32 | C82: =IF(PROJETO!H9>0,B82/MIN(PROJETO!H9,4),0) | D82: =IF(PROJETO!H9>0,B82/MIN(PROJETO!H9,4),0) | E82: =IF(PROJETO!H9>0,B82/MIN(PROJETO!H9,4),0) | F82: =IF(PROJETO!H9>0,B82/MIN(PROJETO!H9,4),0) | G82: =C82*MATERIAIS!$E$14
A83: =MATERIAIS!A33 | B83: =MATERIAIS!G33 | C83: =IF(PROJETO!H9>0,B83/MIN(PROJETO!H9,4),0) | D83: =IF(PROJETO!H9>0,B83/MIN(PROJETO!H9,4),0) | E83: =IF(PROJETO!H9>0,B83/MIN(PROJETO!H9,4),0) | F83: =IF(PROJETO!H9>0,B83/MIN(PROJETO!H9,4),0) | G83: =C83*MATERIAIS!$E$15
A84: =MATERIAIS!A34 | B84: =MATERIAIS!G34 | C84: =IF(PROJETO!H9>0,B84/MIN(PROJETO!H9,4),0) | D84: =IF(PROJETO!H9>0,B84/MIN(PROJETO!H9,4),0) | E84: =IF(PROJETO!H9>0,B84/MIN(PROJETO!H9,4),0) | F84: =IF(PROJETO!H9>0,B84/MIN(PROJETO!H9,4),0) | G84: =C84*MATERIAIS!$E$16
A85: =MATERIAIS!A35 | B85: =MATERIAIS!G35 | C85: =IF(PROJETO!H9>0,B85/MIN(PROJETO!H9,4),0) | D85: =IF(PROJETO!H9>0,B85/MIN(PROJETO!H9,4),0) | E85: =IF(PROJETO!H9>0,B85/MIN(PROJETO!H9,4),0) | F85: =IF(PROJETO!H9>0,B85/MIN(PROJETO!H9,4),0) | G85: =C85*MATERIAIS!$E$17
A86: =MATERIAIS!A36 | B86: =MATERIAIS!G36 | C86: =IF(PROJETO!H9>0,B86/MIN(PROJETO!H9,4),0) | D86: =IF(PROJETO!H9>0,B86/MIN(PROJETO!H9,4),0) | E86: =IF(PROJETO!H9>0,B86/MIN(PROJETO!H9,4),0) | F86: =IF(PROJETO!H9>0,B86/MIN(PROJETO!H9,4),0) | G86: =C86*MATERIAIS!$E$18

Sheet PEDIDO_URGENTE
A1: PEDIDO URGENTE — Próximos 30 dias (todos os núcleos)
A2: QTD = total de MATERIAIS ÷ maior meses restante
A4: MATERIAL | B4: UN | C4: QTD/MÊS | D4: P.UNIT(R$) | E4: CUSTO/MÊS(R$) | F4: LEAD
A5: =MATERIAIS!A23 | B5: m | C5: =IF(MAX(PROJETO!H5:H9)>0,MATERIAIS!H23/MAX(PROJETO!H5:H9),0) | D5: =MATERIAIS!E5 | E5: =C5*D5 | F5: 3 sem
A6: =MATERIAIS!A24 | B6: m | C6: =IF(MAX(PROJETO!H5:H9)>0,MATERIAIS!H24/MAX(PROJETO!H5:H9),0) | D6: =MATERIAIS!E6 | E6: =C6*D6 | F6: 3 sem
A7: =MATERIAIS!A25 | B7: m | C7: =IF(MAX(PROJETO!H5:H9)>0,MATERIAIS!H25/MAX(PROJETO!H5:H9),0) | D7: =MATERIAIS!E7 | E7: =C7*D7 | F7: 4 sem
A8: =MATERIAIS!A26 | B8: m | C8: =IF(MAX(PROJETO!H5:H9)>0,MATERIAIS!H26/MAX(PROJETO!H5:H9),0) | D8: =MATERIAIS!E8 | E8: =C8*D8 | F8: 4 sem
A9: =MATERIAIS!A27 | B9: un | C9: =IF(MAX(PROJETO!H5:H9)>0,MATERIAIS!H27/MAX(PROJETO!H5:H9),0) | D9: =MATERIAIS!E9 | E9: =C9*D9 | F9: 2 sem
A10: =MATERIAIS!A28 | B10: un | C10: =IF(MAX(PROJETO!H5:H9)>0,MATERIAIS!H28/MAX(PROJETO!H5:H9),0) | D10: =MATERIAIS!E10 | E10: =C10*D10 | F10: 2 sem
A11: =MATERIAIS!A29 | B11: un | C11: =IF(MAX(PROJETO!H5:H9)>0,MATERIAIS!H29/MAX(PROJETO!H5:H9),0) | D11: =MATERIAIS!E11 | E11: =C11*D11 | F11: 2 sem
A12: =MATERIAIS!A30 | B12: un | C12: =IF(MAX(PROJETO!H5:H9)>0,MATERIAIS!H30/MAX(PROJETO!H5:H9),0) | D12: =MATERIAIS!E12 | E12: =C12*D12 | F12: 2 sem
A13: =MATERIAIS!A31 | B13: un | C13: =IF(MAX(PROJETO!H5:H9)>0,MATERIAIS!H31/MAX(PROJETO!H5:H9),0) | D13: =MATERIAIS!E13 | E13: =C13*D13 | F13: 3 sem
A14: =MATERIAIS!A32 | B14: m³ | C14: =IF(MAX(PROJETO!H5:H9)>0,MATERIAIS!H32/MAX(PROJETO!H5:H9),0) | D14: =MATERIAIS!E14 | E14: =C14*D14 | F14: 1 sem
A15: =MATERIAIS!A33 | B15: m³ | C15: =IF(MAX(PROJETO!H5:H9)>0,MATERIAIS!H33/MAX(PROJETO!H5:H9),0) | D15: =MATERIAIS!E15 | E15: =C15*D15 | F15: 1 sem
A16: =MATERIAIS!A34 | B16: m³ | C16: =IF(MAX(PROJETO!H5:H9)>0,MATERIAIS!H34/MAX(PROJETO!H5:H9),0) | D16: =MATERIAIS!E16 | E16: =C16*D16 | F16: 1 sem
A17: =MATERIAIS!A35 | B17: t | C17: =IF(MAX(PROJETO!H5:H9)>0,MATERIAIS!H35/MAX(PROJETO!H5:H9),0) | D17: =MATERIAIS!E17 | E17: =C17*D17 | F17: 2 sem
A18: =MATERIAIS!A36 | B18: vb | C18: =IF(MAX(PROJETO!H5:H9)>0,MATERIAIS!H36/MAX(PROJETO!H5:H9),0) | D18: =MATERIAIS!E18 | E18: =C18*D18 | F18: 2 sem
A19: TOTAL MENSAL | E19: =SUM(E5:E18)

Sheet GANTT_COMPRAS
A1: GANTT — Execução + Compras (visual)
A3: NÚCLEO / ATIVIDADE | B3: Mar/26 | C3: Abr/26 | D3: Mai/26 | E3: Jun/26 | F3: Jul/26 | G3: Ago/26 | H3: Set/26
A4: =PROJETO!A5&" — saldo: "&TEXT(SALDO!D4,"#,##0")&"m"
A5: Exec AG | B5: █ | C5: █ | D5: █ | E5: █
A6: Exec ESG | B6: █ | C6: █ | D6: █ | E6: █
A7: $ Compras | B7: $ | C7: $ | D7: $ | E7: $
A9: =PROJETO!A6&" — saldo: "&TEXT(SALDO!D5,"#,##0")&"m"
A10: Exec AG
A11: Exec ESG
A12: $ Compras
A14: =PROJETO!A7&" — saldo: "&TEXT(SALDO!D6,"#,##0")&"m"
A15: Exec AG | B15: █ | C15: █ | D15: █ | E15: █ | F15: █
A16: Exec ESG | B16: █ | C16: █ | D16: █ | E16: █ | F16: █
A17: $ Compras | B17: $ | C17: $ | D17: $ | E17: $ | F17: $
A19: =PROJETO!A8&" — saldo: "&TEXT(SALDO!D7,"#,##0")&"m"
A20: Exec AG | B20: █ | C20: █ | D20: █ | E20: █ | F20: █
A21: Exec ESG | B21: █ | C21: █ | D21: █ | E21: █ | F21: █
A22: $ Compras | B22: $ | C22: $ | D22: $ | E22: $ | F22: $
A24: =PROJETO!A9&" — saldo: "&TEXT(SALDO!D8,"#,##0")&"m"
A25: Exec AG | B25: █ | C25: █ | D25: █ | E25: █ | F25: █
A26: Exec ESG | B26: █ | C26: █ | D26: █ | E26: █ | F26: █
A27: $ Compras | B27: $ | C27: $ | D27: $ | E27: $ | F27: $

Sheet _DIAGNOSTICO
A1: DIAGNÓSTICO — Diferenças entre as 4 versões | Esta planilha usa a MELHOR fonte de cada aba
A3: ABA/ASPECTO | B3: v2.xlsx | C3: FINAL4.xlsx | D3: COMPLETA.xlsx | E3: COMPRAS_v3.xlsx | F3: FONTE USADA AQUI
A4: Abas totais | B4: 34 ✅ | C4: 26 (falta 8) | D4: 32 | E4: 6 (só compras) | F4: v2 como base
A5: v2 integrada | B5: 0 ✅ | C5: 1.446 ❌ | D5: 1.446 ❌ | E5: 0 ✅ | F5: v2 (zero erros)
A6: M/Lig premissa | B6: 2 ✅ (correto) | C6: 2 ✅ | D6: 6 ❌ (errado! 3×) | E6: — | F6: v2 — mantido em 2
A7: Total metros | B7: 50.766m | C7: 50.766m | D7: 152.298m ❌ inflado | E7: — | F7: v2 — 50.766m
A8: Custo total plan. | B8: R$46,2M | C8: R$46,2M | D8: R$138,6M ❌ | E8: — | F8: v2 — R$46,2M
A9: Aba FATORES | B9: ✅ tem | C9: ❌ não tem | D9: ❌ não tem | E9: — | F9: v2
A10: Aba CUSTOS | B10: ✅ tem | C10: ❌ não tem | D10: ❌ não tem | E10: — | F10: v2
A11: COMPRAS total | B11: R$96k ❌ quebrado | C11: ❌ não tem | D11: R$19,4M ✅ | E11: R$19,2M ✅ | F11: COMPRAS_v3 (referência)
A12: PEDIDO URGENTE | B12: ❌ não calculado | C12: ❌ não tem | D12: R$4,2M ✅ | E12: R$4,2M ✅ | F12: COMPRAS_v3
A13: SD_ execução | B13: Idêntico nas 3 | C13: Idêntico | D13: Idêntico | E13: — | F13: v2
A14: TRECHOS_TODOS | B14: 2.241 trechos | C14: 2.241 | D14: 2.241 | E14: — | F14: v2
... A17: GANTT_COMPRAS | B17: simples (██) | C17: ❌ | D17: detalhado $/██ | E17: detalhado ✅ | F17: COMPRAS_v3 (melhor)

Sheet PAINEL_EXECUTIVO
A1: ⚡ PAINEL EXECUTIVO — 100% LINKADO ao PROJETO/SALDO/MATERIAIS
A3: Proj Total | B3: Executado | C3: Saldo | D3: % Global | E3: Custo Saldo R$ | F3: Compras R$
A4: =CURVA_S!B4 | B4: =CURVA_S!B5 | C4: =CURVA_S!B6 | D4: =CURVA_S!B7 | E4: =C4*910 | F4: =MATERIAIS!I37
A6: PROGRESSO POR NÚCLEO
A7: NÚCLEO | B7: PROJ | C7: EXEC | D7: SALDO | E7: % | F7: STATUS AG | G7: STATUS ESG | H7: RITMO AG | I7: RITMO ESG | J7: CUSTO SALDO
A8: =PROJETO!A5 | B8: =PROJETO!D5 | C8: =PROJETO!G5 | D8: =SALDO!D4 | E8: =IF(B8>0,C8/B8,0) | F8: =SALDO!H4 | G8: =SALDO!I4 | H8: =SALDO!K4 | I8: =SALDO!L4 | J8: =D8*910
A9: =PROJETO!A6 | B9: =PROJETO!D6 | C9: =PROJETO!G6 | D9: =SALDO!D5 | E9: =IF(B9>0,C9/B9,0) | F9: =SALDO!H5 | G9: =SALDO!I5 | H9: =SALDO!K5 | I9: =SALDO!L5 | J9: =D9*910
A10: =PROJETO!A7 | B10: =PROJETO!D7 | C10: =PROJETO!G7 | D10: =SALDO!D6 | E10: =IF(B10>0,C10/B10,0) | F10: =SALDO!H6 | G10: =SALDO!I6 | H10: =SALDO!K6 | I10: =SALDO!L6 | J10: =D10*910
A11: =PROJETO!A8 | B11: =PROJETO!D8 | C11: =PROJETO!G8 | D11: =SALDO!D7 | E11: =IF(B11>0,C11/B11,0) | F11: =SALDO!H7 | G11: =SALDO!I7 | H11: =SALDO!K7 | I11: =SALDO!L7 | J11: =D11*910
A12: =PROJETO!A9 | B12: =PROJETO!D9 | C12: =PROJETO!G9 | D12: =SALDO!D8 | E12: =IF(B12>0,C12/B12,0) | F12: =SALDO!H8 | G12: =SALDO!I8 | H12: =SALDO!K8 | I12: =SALDO!L8 | J12: =D12*910
A13: TOTAL | B13: =SUM(B8:B12) | C13: =SUM(C8:C12) | D13: =SUM(D8:D12) | E13: =IF(B13>0,C13/B13,0) | J13: =SUM(J8:J12)

Sheet SALDO_REDES_DXF
A1: SALDO DE REDES — PROJETADO × EXECUTADO × A EXECUTAR | SLNR Santos
A3: NÚCLEO | B3: TIPO | C3: MATERIAL | D3: DIÂMETRO | E3: PROJ. TOTAL m | F3: EXECUTADO m | G3: SALDO m | H3: % EXEC | I3: P.UNIT R$/m | J3: CUSTO SALDO R$ | K3: BARRAS 6m | L3: BARRAS 12m
A4: MORRO DO TETEU | B4: ESGOTO | C4: PVC | D4: DN100 | E4: 8879.5 | F4: 1037 | G4: =E4-F4 | H4: =IF(E4>0,F4/E4,0) | I4: 45.2 | J4: =G4*I4 | K4: 1308 | L4: 654
A5: MORRO DO TETEU | B5: ESGOTO | C5: PVC | D5: DN150 | E5: 0 | F5: 0 | G5: =E5-F5 | H5: =IF(E5>0,F5/E5,0) | I5: 68.4 | J5: =G5*I5 | K5: 0 | L5: 0
A6: MORRO DO TETEU | B6: AGUA | C6: PEAD | D6: DN63 | E6: 6480 | F6: 311.8 | G6: =E6-F6 | H6: =IF(E6>0,F6/E6,0) | I6: 85 | J6: =G6*I6 | K6: 1029 | L6: 515
A7: MORRO DO TETEU | B7: AGUA | C7: PEAD | D7: DN100 | E7: 543.7 | F7: 26.2 | G7: =E7-F7 | H7: =IF(E7>0,F7/E7,0) | I7: 101.8 | J7: =G7*I7 | K7: 87 | L7: 44
A8: CRIADORES | B8: ESGOTO | C8: PVC | D8: DN100 | E8: 10500 | F8: 186.5 | G8: =E8-F8 | H8: =IF(E8>0,F8/E8,0) | I8: 45.2 | J8: =G8*I8 | K8: 1719 | L8: 860
A9: CRIADORES | B9: ESGOTO | C9: PVC | D9: DN150 | E9: 6223.3 | F9: 110.5 | G9: =E9-F9 | H9: =IF(E9>0,F9/E9,0) | I9: 68.4 | J9: =G9*I9 | K9: 1019 | L9: 510
A10: CRIADORES | B10: AGUA | C10: PEAD | D10: DN63 | E10: 4191.3 | F10: 3147 | G10: =E10-F10 | H10: =IF(E10>0,F10/E10,0) | I10: 85 | J10: =G10*I10 | K10: 175 | L10: 88
A11: VILA ISRAEL | B11: ESGOTO | C11: PVC | D11: DN100 | E11: 3500 | F11: 937.9 | G11: =E11-F11 | H11: =IF(E11>0,F11/E11,0) | I11: 45.2 | J11: =G11*I11 | K11: 428 | L11: 214
A12: VILA ISRAEL | B12: ESGOTO | C12: PVC | D12: DN150 | E12: 1747 | F12: 468.1 | G12: =E12-F12 | H12: =IF(E12>0,F12/E12,0) | I12: 68.4 | J12: =G12*I12 | K12: 214 | L12: 107
A13: VILA ISRAEL | B13: AGUA | C13: PEAD | D13: DN63 | E13: 10250 | F13: 0 | G13: =E13-F13 | H13: =IF(E13>0,F13/E13,0) | I13: 85 | J13: =G13*I13 | K13: 1709 | L13: 855
A14: VILA ISRAEL | B14: AGUA | C14: PEAD | D14: DN100 | E14: 1404.5 | F14: 0 | G14: =E14-F14 | H14: =IF(E14>0,F14/E14,0) | I14: 101.8 | J14: =G14*I14 | K14: 235 | L14: 118
A15: SAO MANOEL | B15: ESGOTO | C15: PVC | D15: DN100 | E15: 13200 | F15: 791.5 | G15: =E15-F15 | H15: =IF(E15>0,F15/E15,0) | I15: 45.2 | J15: =G15*I15 | K15: 2069 | L15: 1035
... A27: JOAO CARLOS | B27: AGUA | C27: PEAD | D27: DN100 | E27: 2792.7 | F27: 223.1 | G27: =E27-F27 | H27: =IF(E27>0,F27/E27,0) | I27: 101.8 | J27: =G27*I27 | K27: 429 | L27: 215
A28: TOTAL | E28: =SUM(E4:E27) | F28: =SUM(F4:F27) | G28: =SUM(G4:G27) | J28: =SUM(J4:J27) | K28: =SUM(K4:K27) | L28: =SUM(L4:L27)

Sheet COMPRAS_DETALHADAS
A1: LISTA DE COMPRAS DETALHADA — TUBOS + CONEXÕES + PVs | CONSTRUDATA | 20/03/2026
A3: NÚCLEO | B3: TIPO | C3: CATEGORIA | D3: DESCRIÇÃO DA PEÇA / MATERIAL | E3: UN | F3: QTDE | G3: QTD UNID. | H3: UNID FORNEC. | I3: P.UNIT R$ | J3: TOTAL R$ | K3: LEAD (sem) | L3: NORMA/SPEC | M3: FORNECEDOR
A4: MORRO DO TETEU | B4: ESGOTO | C4: TUBO | D4: Tubo PVC DN100 (coletor esgoto) | E4: m | F4: 7842.5 | G4: 1308 | H4: barra 6m | I4: 45.2 | J4: =F4*I4 | K4: 3 | L4: NBR 7362 SN8 | M4: Tigre/Amanco
A5: MORRO DO TETEU | B5: ESGOTO | C5: CONEXÃO | D5: Joelho 90° PVC JE DN100 | E5: un | F5: 196.1 | G5: 196 | H5: un | I5: 8.5 | J5: =F5*I5 | K5: 2 | L5: NBR 5648 / SABESP | M5: Tigre/Amanco
A6: MORRO DO TETEU | B6: ESGOTO | C6: CONEXÃO | D6: Tê PVC JE DN100 | E6: un | F6: 376.4 | G6: 376 | H6: un | I6: 9.6 | J6: =F6*I6 | K6: 2 | L6: NBR 5648 / SABESP | M6: Tigre/Amanco
A7: MORRO DO TETEU | B7: ESGOTO | C7: CONEXÃO | D7: Luva PVC JE DN100 | E7: un | F7: 274.5 | G7: 274 | H7: un | I7: 4.2 | J7: =F7*I7 | K7: 2 | L7: NBR 5648 / SABESP | M7: Tigre/Amanco
A8: MORRO DO TETEU | B8: ESGOTO | C8: CONEXÃO | D8: Cap PVC JE DN100 (TIL) | E8: un | F8: 666.6 | G8: 666 | H8: un | I8: 9.8 | J8: =F8*I8 | K8: 2 | L8: NBR 5648 / SABESP | M8: Tigre/Amanco
A9: MORRO DO TETEU | B9: ESGOTO | C9: CONEXÃO | D9: Anel borracha DN100 JE | E9: un | F9: 1411.6 | G9: 1411 | H9: un | I9: 2.8 | J9: =F9*I9 | K9: 2 | L9: NBR 5648 / SABESP | M9: Tigre/Amanco
A10: MORRO DO TETEU | B10: ESGOTO | C10: PV/CAIXA | D10: PV concreto DN1200 (SABESP padrão) | E10: un | F10: 1054 | G10: 1054 | H10: un | I10: 3686 | J10: =F10*I10 | K10: 2 | L10: NBR 9794 DN1200 / SABESP | M10: Premold Santos
A11: MORRO DO TETEU | B11: ESGOTO | C11: PV/CAIXA | D11: PI plástico DN600 (caixa inspeção) | E11: un | F11: 324 | G11: 324 | H11: un | I11: 1412 | J11: =F11*I11 | K11: 2 | L11: NBR 9794 DN1200 / SABESP | M11: Premold Santos
A12: MORRO DO TETEU | B12: ESGOTO | C12: PV/CAIXA | D12: Caixa inspeção PP DN400 | E12: un | F12: 243 | G12: 243 | H12: un | I12: 1034 | J12: =F12*I12 | K12: 2 | L12: NBR 9794 DN1200 / SABESP | M12: Premold Santos
A13: MORRO DO TETEU | B13: AGUA | C13: TUBO | D13: Tubo PEAD DN63 (coletor água) | E13: m | F13: 6168.2 | G13: 515 | H13: rolo 100m | I13: 85 | J13: =F13*I13 | K13: 4 | L13: NBR ISO 4427 PN10 | M13: Plastubos/Fortlev
A14: MORRO DO TETEU | B14: AGUA | C14: CONEXÃO | D14: Sela eletrofusão DN63/DN25 | E14: un | F14: 259.1 | G14: 259 | H14: un | I14: 660 | J14: =F14*I14 | K14: 2 | L14: NBR 5648 / SABESP | M14: Tigre/Amanco
A15: MORRO DO TETEU | B15: AGUA | C15: CONEXÃO | D15: Tê PEAD DN63 | E15: un | F15: 172.7 | G15: 172 | H15: un | I15: 42.5 | J15: =F15*I15 | K15: 2 | L15: NBR 5648 / SABESP | M15: Tigre/Amanco
... A178: JOAO CARLOS | B178: AGUA | C178: CONEXÃO | D178: Tampão cego PEAD DN110 | E178: un | F178: 20.6 | G178: 20 | H178: un | I178: 12.6 | J178: =F178*I178 | K178: 2 | L178: NBR 5648 / SABESP | M178: Tigre/Amanco
A179: TOTAL COMPRAS | J179: =SUM(J4:J178)
A181: SUBTOTAIS POR CATEGORIA
A182: TUBO | F182: 106763 | J182: 7541630.2
A183: CONEXÃO | F183: 33011.5 | J183: 2219920.2
A184: PV/CAIXA | F184: 12617 | J184: 35751376

Sheet NOVOS_NUCLEOS
A1: NOVOS NÚCLEOS (N07-N12) — ESTIMATIVA DE MATERIAL SEM PROJETO EXECUTIVO | Fator: 2.2m/ligação
A2: ⚠️ Sem projeto executivo — quantitativos estimados por fator de ligação (SABESP SLNR padrão). Revisar quando projeto chegar.
A4: TAG | B4: NÚCLEO | C4: SETOR | D4: LIG ÁGUA | E4: LIG ESG | F4: LIG TOTAL | G4: INÍCIO | H4: EQ | I4: ESG m est. | J4: AGU m est. | K4: Tubo PVC DN100 m | L4: Tubo PVC DN150 m | M4: Tubo PEAD DN63 m | N4: Tubo PEAD DN110 m | O4: PV concreto un | P4: PI plástico un | Q4: Cx inspeção un | R4: Sela eletrofus. | S4: Cavaletes/HM | T4: Custo Est. R$
A5: N07 | B5: ZONA NOROESTE | C5: ST-NOROESTE | D5: 883 | E5: 2113 | F5: =D5+E5 | G5: Abr/26 | H5: 10 | I5: 4649 | J5: 1943 | K5: 3254 | L5: 1395 | M5: 1399 | N5: 544 | O5: 121 | P5: 37 | Q5: 28 | R5: 1060 | S5: 883 | T5: 2726360
A6: N07 | B6: Vila Alemoa | C6: Noroeste | D6: 461 | E6: 946 | F6: =D6+E6 | G6: Abr/26 | H6: 5 | I6: 2081 | J6: 1014 | K6: 1457 | L6: 624 | M6: 730 | N6: 284 | O6: 54 | P6: 17 | Q6: 12 | R6: 553 | S6: 461 | T6: 1280370
A7: N07 | B7: Ilheu Baixo | C7: Noroeste | D7: 73 | E7: 603 | F7: =D7+E7 | G7: Abr/26 | H7: 2 | I7: 1327 | J7: 161 | K7: 929 | L7: 398 | M7: 116 | N7: 45 | O7: 34 | P7: 11 | Q7: 8 | R7: 88 | S7: 73 | T7: 615160
A8: N07 | B8: NSRA Fatima | C8: Noroeste | D8: 91 | E8: 170 | F8: =D8+E8 | G8: Abr/26 | H8: 1 | I8: 374 | J8: 200 | K8: 262 | L8: 112 | M8: 144 | N8: 56 | O8: 10 | P8: 3 | Q8: 2 | R8: 109 | S8: 91 | T8: 237510
A9: N07 | B9: Vila Telma | C9: Noroeste | D9: 48 | E9: 143 | F9: =D9+E9 | G9: Abr/26 | H9: 1 | I9: 315 | J9: 106 | K9: 220 | L9: 94 | M9: 76 | N9: 30 | O9: 8 | P9: 3 | Q9: 2 | R9: 58 | S9: 48 | T9: 173810
A10: N08 | B10: VILA PROGRESSO | C10: ST-V.PROGRESSO | D10: 585 | E10: 1280 | F10: =D10+E10 | G10: Mai/26 | H10: 10 | I10: 2816 | J10: 1287 | K10: 1971 | L10: 845 | M10: 927 | N10: 360 | O10: 73 | P10: 23 | Q10: 17 | R10: 702 | S10: 585 | T10: 1697150
A11: N08 | B11: R Um N.Cintra | C11: V.Progresso | D11: 246 | E11: 450 | F11: =D11+E11 | G11: Mai/26 | H11: 4 | I11: 990 | J11: 541 | K11: 693 | L11: 297 | M11: 390 | N11: 152 | O11: 26 | P11: 8 | Q11: 6 | R11: 295 | S11: 246 | T11: 633360
A12: N08 | B12: V.Progresso | C12: V.Progresso | D12: 71 | E12: 537 | F12: =D12+E12 | G12: Mai/26 | H12: 3 | I12: 1181 | J12: 156 | K12: 827 | L12: 354 | M12: 112 | N12: 44 | O12: 31 | P12: 9 | Q12: 7 | R12: 85 | S12: 71 | T12: 553280
A13: N08 | B13: Encosta Saboo | C13: V.Progresso | D13: 140 | E13: 140 | F13: =D13+E13 | G13: Mai/26 | H13: 2 | I13: 308 | J13: 308 | K13: 216 | L13: 92 | M13: 222 | N13: 86 | O13: 8 | P13: 2 | Q13: 2 | R13: 168 | S13: 140 | T13: 254800
A14: N09 | B14: ZONA LESTE | C14: ST-Z.LESTE | D14: 480 | E14: 921 | F14: =D14+E14 | G14: Mai/26 | H14: 10 | I14: 2026 | J14: 1056 | K14: 1418 | L14: 608 | M14: 760 | N14: 296 | O14: 53 | P14: 16 | Q14: 12 | R14: 576 | S14: 480 | T14: 1274910
A15: N10 | B15: CONJUNTO | C15: ST-CONJUNTO | D15: 656 | E15: 1016 | F15: =D15+E15 | G15: Ago/26 | H15: 10 | I15: 2235 | J15: 1443 | K15: 1565 | L15: 671 | M15: 1039 | N15: 404 | O15: 58 | P15: 18 | Q15: 13 | R15: 787 | S15: 656 | T15: 1521520
A16: N11 | B16: ALAGADO/DIQUE | C16: ALAGADO | D16: 638 | E16: 1224 | F16: =D16+E16 | G16: Ago/26 | H16: 10 | I16: 2693 | J16: 1404 | K16: 1885 | L16: 808 | M16: 1011 | N16: 393 | O16: 70 | P16: 22 | Q16: 16 | R16: 766 | S16: 638 | T16: 1694420
A17: N12 | B17: MONTANHOSO | C17: MONTANHOSO | D17: 4367 | E17: 6144 | F17: =D17+E17 | G17: Ago/26 | H17: 15 | I17: 13517 | J17: 9607 | K17: 9462 | L17: 4055 | M17: 6917 | N17: 2690 | O17: 351 | P17: 108 | Q17: 81 | R17: 5240 | S17: 4367 | T17: 9565010
A18: TOTAL N07-N12 | D18: =SUMIF(A5:A17,"N*",D5:D17) | E18: =SUMIF(A5:A17,"N*",E5:E17) | F18: =SUMIF(A5:A17,"N*",F5:F17) | G18: =SUM(I5:I17) | H18: =SUM(J5:J17) | I18: =SUM(K5:K17) | J18: =SUM(L5:L17) | K18: =SUM(M5:M17) | L18: =SUM(N5:N17) | M18: =SUM(O5:O17) | N18: =SUM(P5:P17) | ... R18: =SUM(T5:T17)

Sheet RESUMO_MATERIAIS
A1: RESUMO MATERIAIS — Linkado a MATERIAIS
A3: MATERIAL | B3: UN | C3: QTD TOTAL | D3: P.UNIT | E3: CUSTO TOTAL | F3: LEAD
A4: =MATERIAIS!A23 | B4: =MATERIAIS!B5 | C4: =MATERIAIS!H23 | D4: =MATERIAIS!E5 | E4: =MATERIAIS!I23 | F4: =MATERIAIS!F5
A5: =MATERIAIS!A24 | B5: =MATERIAIS!B6 | C5: =MATERIAIS!H24 | D5: =MATERIAIS!E6 | E5: =MATERIAIS!I24 | F5: =MATERIAIS!F6
A6: =MATERIAIS!A25 | B6: =MATERIAIS!B7 | C6: =MATERIAIS!H25 | D6: =MATERIAIS!E7 | E6: =MATERIAIS!I25 | F6: =MATERIAIS!F7
A7: =MATERIAIS!A26 | B7: =MATERIAIS!B8 | C7: =MATERIAIS!H26 | D7: =MATERIAIS!E8 | E7: =MATERIAIS!I26 | F7: =MATERIAIS!F8
A8: =MATERIAIS!A27 | B8: =MATERIAIS!B9 | C8: =MATERIAIS!H27 | D8: =MATERIAIS!E9 | E8: =MATERIAIS!I27 | F8: =MATERIAIS!F9
A9: =MATERIAIS!A28 | B9: =MATERIAIS!B10 | C9: =MATERIAIS!H28 | D9: =MATERIAIS!E10 | E9: =MATERIAIS!I28 | F9: =MATERIAIS!F10
A10: =MATERIAIS!A29 | B10: =MATERIAIS!B11 | C10: =MATERIAIS!H29 | D10: =MATERIAIS!E11 | E10: =MATERIAIS!I29 | F10: =MATERIAIS!F11
A11: =MATERIAIS!A30 | B11: =MATERIAIS!B12 | C11: =MATERIAIS!H30 | D11: =MATERIAIS!E12 | E11: =MATERIAIS!I30 | F11: =MATERIAIS!F12
A12: =MATERIAIS!A31 | B12: =MATERIAIS!B13 | C12: =MATERIAIS!H31 | D12: =MATERIAIS!E13 | E12: =MATERIAIS!I31 | F12: =MATERIAIS!F13
A13: =MATERIAIS!A32 | B13: =MATERIAIS!B14 | C13: =MATERIAIS!H32 | D13: =MATERIAIS!E14 | E13: =MATERIAIS!I32 | F13: =MATERIAIS!F14
A14: =MATERIAIS!A33 | B14: =MATERIAIS!B15 | C14: =MATERIAIS!H33 | D14: =MATERIAIS!E15 | E14: =MATERIAIS!I33 | F14: =MATERIAIS!F15
A15: =MATERIAIS!A34 | B15: =MATERIAIS!B16 | C15: =MATERIAIS!H34 | D15: =MATERIAIS!E16 | E15: =MATERIAIS!I34 | F15: =MATERIAIS!F16
... A17: =MATERIAIS!A36 | B17: =MATERIAIS!B18 | C17: =MATERIAIS!H36 | D17: =MATERIAIS!E18 | E17: =MATERIAIS!I36 | F17: =MATERIAIS!F18
A18: TOTAL | E18: =MATERIAIS!I37

Sheet FORNECEDORES
A1: CATÁLOGO DE FORNECEDORES — CONSTRUDATA ENGENHARIA | SLNR Santos
A3: CATEGORIA | B3: DESCRIÇÃO | C3: UN | D3: FORNECEDOR | E3: CONTATO | F3: LEAD | G3: NORMA/SPEC
A4: TUBO | B4: Tubo PVC SN8 DN100 JE (barra 6m) | C4: m | D4: Tigre S.A. | E4: 0800 726 8836 | F4: 3sem | G4: NBR 7362 SN8
A5: TUBO | B5: Tubo PVC SN8 DN150 JE (barra 6m) | C5: m | D5: Tigre S.A. | E5: 0800 726 8836 | F5: 3sem | G5: NBR 7362 SN8
A6: TUBO | B6: Tubo PVC SN8 DN200 JE (barra 6m) | C6: m | D6: Amanco Wavin | E6: (11) 2111-4000 | F6: 3sem | G6: NBR 7362 SN8
A7: TUBO | B7: Tubo PVC SN4 DN300 JE (barra 6m) | C7: m | D7: Amanco Wavin | E7: (11) 2111-4000 | F7: 4sem | G7: NBR 7362 SN4
A8: TUBO | B8: Tubo PEAD PE100 DN63 PN10 (rolo 100m) | C8: m | D8: Plastubos | E8: (13) 3219-0000 | F8: 4sem | G8: NBR ISO 4427 PN10
A9: TUBO | B9: Tubo PEAD PE100 DN110 PN10 (barra 12m) | C9: m | D9: Plastubos | E9: (13) 3219-0000 | F9: 4sem | G9: NBR ISO 4427 PN10
A10: TUBO | B10: Tubo PEAD PE100 DN100 PN10 (barra 12m) | C10: m | D10: Fortlev | E10: (11) 4063-9600 | F10: 4sem | G10: NBR ISO 4427 PN10
A11: TUBO | B11: Tubo concreto DN300 armado (barra 2m) | C11: m | D11: Premold Santos | E11: (13) 3222-0000 | F11: 2sem | G11: NBR 8890 A2
A12: CONEXÃO | B12: Joelho 90° PVC JE DN100 | C12: un | D12: Tigre/Amanco | E12: — | F12: 2sem | G12: NBR 5648
A13: CONEXÃO | B13: Joelho 90° PVC JE DN150 | C13: un | D13: Tigre/Amanco | E13: — | F13: 2sem | G13: NBR 5648
A14: CONEXÃO | B14: Tê PVC JE DN100 | C14: un | D14: Tigre/Amanco | E14: — | F14: 2sem | G14: NBR 5648
... A34: INSUMO | B34: CBUQ (pré-misturado a quente) t | C34: t | D34: Usina Santos | E34: (13) local | F34: 2sem | G34: DNIT 031/2006

Sheet ML_PLANO_1044
A1: ML PLANO 1.044 — XGBoost R²=0.275 + Pipeline 11 Etapas
A3: DIAGNÓSTICO (Jan-Mar/2026)
A4: Lig/mês atual | B4: 359 | C4: Meta: 1.044 → GAP: 685 (66%)
A5: Rede/mês | B5: 2.367m | C5: Meta: 6.737m
A6: m/ligação | B6: 6,6 | C6: Contrato: ~2,85
A7: Equipes | B7: 36 | C7: Meta: 39
A8: Multiplicador | B8: 2,9x | C8: Precisamos quase triplicar
A9: Conversão rede→lig | B9: 35% | C9: 65% da rede NÃO virou ligação
A10: Ciclo pipeline | B10: ~76 dias | C10: Crítico: 47 dias
A11: Custo/lig atual | B11: R$ 6.708 | C11: Deveria ser R$ 4.300
A13: XGBOOST FEATURE IMPORTANCE
A14: lig_total_r3 | B14: 0.311 | C14: ███████████████
A15: rede_acum | B15: 0.102 | C15: █████
A16: rede_total_r7 | B16: 0.098 | C16: ████
A17: rede_total_r3 | B17: 0.097 | C17: ████
A18: lig_total_r7 | B18: 0.093 | C18: ████
A19: pvs_r3 | B19: 0.075 | C19: ███
A20: pre_r3 | B20: 0.074 | C20: ███
A21: equipe_count | B21: 0.046 | C21: ██
A22: dia_semana | B22: 0.044 | C22: ██
A23: mes | B23: 0.035 | C23: █
A24: nucleo_enc | B24: 0.026 | C24: █
A26: 💡 Momentum (31%) + rede acumulada (10%) dominam. Equipe = 5%. O gargalo é FLUXO, não gente.
A28: PIPELINE 11 ETAPAS — Atual vs Meta
A29: # | B29: ETAPA | C29: ATUAL | D29: META | E29: AÇÃO | F29: CUSTO/MÊS | G29: PARALELO | H29: REDUÇÃO %
A30: 1 | B30: Cadastro Social | C30: 5d | D30: 3d | E30: 2 eq + tablets | F30: R$ 8k | G30: SIM | H30: =1-D30/C30
A31: 2 | B31: Cartografia | C31: 3d | D31: 2d | E31: Drone | F31: R$ 15k | G31: SIM | H31: =1-D31/C31
A32: 3 | B32: Topografia | C32: 5d | D32: 3d | E32: RTK | F32: R$ 12k | G32: SIM | H32: =1-D32/C32
A33: 4 | B33: Projeto | C33: 10d | D33: 5d | E33: 2 projetistas | F33: R$ 25k | G33: NÃO | H33: =1-D33/C33
A34: 5 | B34: Planejamento | C34: 3d | D34: 2d | E34: ConstruData | F34: R$ 0 | G34: SIM | H34: =1-D34/C34
A35: 6 | B35: Execução Rede | C35: 15d | D35: 8d | E35: +10 eq MEC | F35: R$ 180k | G35: NÃO | H35: =1-D35/C35
A36: 7 | B36: Lavagem/Colif. | C36: 7d | D36: 3d | E36: Lab express | F36: R$ 5k | G36: NÃO | H36: =1-D36/C36
A37: 8 | B37: Liberação SABESP | C37: 15d | D37: 7d | E37: Lote 50 lig | F37: R$ 10k | G37: NÃO | H37: =1-D37/C37
A38: 9 | B38: Lig Intra | C38: 2d | D38: 1d | E38: 3 eq intra | F38: R$ 45k | G38: SIM | H38: =1-D38/C38
A39: 10 | B39: Docs SABESP | C39: 10d | D39: 5d | E39: Automação GIS | F39: R$ 8k | G39: SIM | H39: =1-D39/C39
A40: 11 | B40: Lig Concluída | C40: 1d | D40: 1d | E40: App mobile | F40: R$ 2k | G40: SIM | H40: =1-D40/C40
B41: TOTAL | C41: =SUM(C30:C40) | D41: =SUM(D30:D40)
B42: CAMINHO CRÍTICO | C42: =C33+C35+C36+C37 | D42: =D33+D35+D36+D37 | E42: 47d → 23d = −51%
A44: RESULTADO: 359→1.044 lig/mês | Ciclo 47→23d | Invest ~R$310k/mês | ROI 45 dias

Sheet ACAO_PRATICA
A1: PLANO DE AÇÃO — De 359 para 1.044 lig/mês (ramp-up Abr→Ago)
A3: FASE 1: DESTRAVAR BACKLOG (Abr/26) — converter rede pronta em ligação
A4: SEMANA | B4: AÇÃO | C4: RESPONSÁVEL | D4: KPI | E4: CUSTO | F4: PRIORIDADE | G4: STATUS
A5: S1 | B5: Mapear rede pronta sem ligação (backlog >500) | C5: Eng | D5: # lig mapeadas | E5: R$ 0 | F5: 🔴
A6: S1 | B6: Contratar lab express coliformes (48h) | C6: Compras | D6: Prazo lab | E6: R$ 5k/m | F6: 🔴
A7: S2 | B7: Reunião SABESP: liberação em lote 50 lig | C7: Coord | D7: # lig/lote | E7: R$ 0 | F7: 🔴
A8: S2 | B8: Mobilizar 3 eq intra dedicadas | C8: RH | D8: lig intra/dia | E8: R$ 45k/m | F8: 🟡
A9: S3 | B9: Lavagem + coleta em rede pronta SM+JC | C9: Campo | D9: m liberados | E9: R$ 3k | F9: 🔴
A10: S3 | B10: Automação docs GIS→PDF→SABESP | C10: TI | D10: docs/dia | E10: R$ 8k | F10: 🟡
A11: S4 | B11: Liberar lote 1: 100 lig SM+JC | C11: Coord | D11: # liberadas | E11: R$ 0 | F11: 🔴
A12: S4 | B12: Executar 100 lig intra (rede pronta) | C12: Intra | D12: lig/semana | E12: R$ 20k | F12: 🔴
A14: FASE 2: ESCALAR (Jun-Jul/26) — +equipes rede + pipeline contínuo
A15: Jun | B15: +4 eq MEC rede ESG (Tetéu+Pantanal) | C15: Campo | D15: m/dia ESG | E15: R$ 120k/m | F15: 🟡
A16: Jun | B16: +4 eq rede AG simultânea | C16: Campo | D16: m/dia AG | E16: R$ 60k/m | F16: 🟡
A17: Jun | B17: 2º projetista (template ProSaneamento) | C17: Eng | D17: projetos/sem | E17: R$ 15k/m | F17: 🟢
A18: Jun | B18: Pipeline contínuo: rede→lavagem→lib→intra | C18: Coord | D18: lig/semana | E18: R$ 0 | F18: 🔴
A19: Jul | B19: Tetéu plena carga (2 frentes ESG+AG) | C19: Campo | D19: m/dia | E19: R$ 80k/m | F19: 🟡
A20: Jul | B20: Pantanal plena carga | C20: Campo | D20: m/dia | E20: R$ 60k/m | F20: 🟡
A22: PROJEÇÃO DE RAMP-UP
A23: MÊS | B23: LIG/MÊS | C23: REDE/MÊS | D23: EQUIPES | E23: FAT EST. | F23: ACUM LIG | G23: % META
A24: Mar/26 | B24: 359 | C24: 2367 | D24: 36 | E24: R$ 2,2M | F24: 897 | G24: 34%
A25: Abr/26 | B25: 500 | C25: 3500 | D25: 36 | E25: R$ 3,2M | F25: 1397 | G25: 48%
A26: Mai/26 | B26: 650 | C26: 4500 | D26: 39 | E26: R$ 4,1M | F26: 2047 | G26: 62%
A27: Jun/26 | B27: 800 | C27: 5500 | D27: 44 | E27: R$ 5,0M | F27: 2847 | G27: 77%
A28: Jul/26 | B28: 1000 | C28: 6500 | D28: 46 | E28: R$ 6,1M | F28: 3847 | G28: 96%
A29: Ago/26 | B29: 1044 | C29: 6737 | D29: 46 | E29: R$ 6,3M | F29: 4891 | G29: 100%
A30: Set/26 | B30: 1044 | C30: 6737 | D30: 46 | E30: R$ 6,3M | F30: 5935 | G30: 100%
A31: Out/26 | B31: 1044 | C31: 6737 | D31: 46 | E31: R$ 6,3M | F31: 6979 | G31: 100%

Sheet HEATMAP_REDE
A1: MAPA DE CALOR — METROS DE REDE POR DIA | Cores = intensidade de produção
A2: Branco = 0 | Azul claro = baixo | Azul escuro = alta produção | Cada bloco = 1 núcleo | Semanas do ano
A4: São Manoel — REDE (metros/dia) | EQ: 8 | Total: 1502m
B5: S1 | C5: S2 | D5: S3 | E5: S4 | F5: S5 | G5: S6 | H5: S7 | I5: S8 | J5: S9 | K5: S10 | L5: S11 | M5: S12 | N5: S13 | O5: S14 | P5: S15 | Q5: S16 | R5: S17 | S5: S18 | T5: S19 | U5: S20 | V5: S21 | W5: S22 | X5: S23 | Y5: S24 | Z5: S25 | AA5: S26 | AB5: S27 | AC5: S28 | AD5: S29 | AE5: S30 | AF5: S31 | AG5: S32 | AH5: S33 | AI5: S34 | AJ5: S35 | AK5: S36 | AL5: S37 | AM5: S38 | AN5: S39 | AO5: S40 | AP5: S41 | AQ5: S42 | AR5: S43 | AS5: S44 | AT5: S45 | AU5: S46 | AV5: S47 | AW5: S48 | AX5: S49 | AY5: S50 | AZ5: S51 | BA5: S52 | BB5: S53 | BC5: S54 | BD5: S55 | BE5: S56 | BF5: S57 | BG5: S58 | BH5: S59 | BI5: TOTAL
A6: Seg | C6: 11 | D6: 0 | F6: 6 | G6: 59 | I6: 40 | J6: 55 | L6: 6 | BI6: =SUM(B6:BH6)
A7: Ter | C7: 24 | D7: 60 | F7: 37 | G7: 12 | I7: 94 | J7: 57 | L7: 16 | BI7: =SUM(B7:BH7)
A8: Qua | C8: 0 | D8: 73 | E8: 115 | F8: 88 | G8: 22 | H8: 37 | I8: 55 | J8: 6 | L8: 14 | BI8: =SUM(B8:BH8)
A9: Qui | C9: 0 | D9: 0 | E9: 20 | F9: 6 | G9: 53 | H9: 16 | I9: 41 | K9: 11 | M9: 48 | BI9: =SUM(B9:BH9)
A10: Sex | C10: 9 | D10: 6 | E10: 30 | F10: 47 | G10: 99 | H10: 25 | I10: 24 | J10: 25 | K10: 51 | L10: 2 | BI10: =SUM(B10:BH10)
A11: Sáb | C11: 11 | E11: 55 | F11: 30 | J11: 6 | BI11: =SUM(B11:BH11)
A12: Dom | BI12: =SUM(B12:BH12)
A13: TOTAL | B13: =SUM(B6:B12) | C13: =SUM(C6:C12) | D13: =SUM(D6:D12) | E13: =SUM(E6:E12) | F13: =SUM(F6:F12) | G13: =SUM(G6:G12) | H13: =SUM(H6:H12) | I13: =SUM(I6:I12) | ... BI13: =SUM(BI6:BI12)
A14: João Carlos — REDE (metros/dia) | EQ: 3 | Total: 943m
B15: S1 | C15: S2 | D15: S3 | E15: S4 | F15: S5 | G15: S6 | H15: S7 | I15: S8 | J15: S9 | K15: S10 | L15: S11 | M15: S12 | N15: S13 | O15: S14 | P15: S15 | Q15: S16 | R15: S17 | S15: S18 | T15: S19 | U15: S20 | V15: S21 | W15: S22 | X15: S23 | Y15: S24 | Z15: S25 | AA15: S26 | AB15: S27 | AC15: S28 | AD15: S29 | AE15: S30 | AF15: S31 | AG15: S32 | AH15: S33 | AI15: S34 | AJ15: S35 | AK15: S36 | AL15: S37 | AM15: S38 | AN15: S39 | AO15: S40 | AP15: S41 | AQ15: S42 | AR15: S43 | AS15: S44 | AT15: S45 | AU15: S46 | AV15: S47 | AW15: S48 | AX15: S49 | AY15: S50 | AZ15: S51 | BA15: S52 | BB15: S53 | BC15: S54 | BD15: S55 | BE15: S56 | BF15: S57 | BG15: S58 | BH15: S59 | BI15: TOTAL
A16: Seg | C16: 48 | D16: 13 | F16: 30 | H16: 1 | I16: 38 | J16: 41 | K16: 4 | L16: 63 | BI16: =SUM(B16:BH16)
A17: Ter | C17: 58 | D17: 15 | E17: 6 | F17: 3 | G17: 4 | H17: 1 | I17: 33 | J17: 44 | L17: 86 | BI17: =SUM(B17:BH17)
A18: Qua | C18: 40 | D18: 28 | E18: 10 | F18: 24 | G18: 12 | I18: 38 | J18: 58 | L18: 12 | BI18: =SUM(B18:BH18)
A19: Qui | D19: 30 | E19: 12 | K19: 46 | M19: 10 | BI19: =SUM(B19:BH19)
A20: Sex | E20: 12 | J20: 6 | K20: 25 | BI20: =SUM(B20:BH20)
A21: Sáb | D21: 6 | E21: 12 | F21: 42 | G21: 30 | J21: 2 | BI21: =SUM(B21:BH21)
A22: Dom | BI22: =SUM(B22:BH22)
A23: TOTAL | B23: =SUM(B16:B22) | C23: =SUM(C16:C22) | D23: =SUM(D16:D22) | E23: =SUM(E16:E22) | F23: =SUM(F16:F22) | G23: =SUM(G16:G22) | H23: =SUM(H16:H22) | I23: =SUM(I16:I22) | ... BI23: =SUM(BI16:BI22)
A24: Vila Israel — REDE (metros/dia) | EQ: 6 | Total: 464m
B25: S1 | C25: S2 | D25: S3 | E25: S4 | F25: S5 | G25: S6 | H25: S7 | I25: S8 | J25: S9 | K25: S10 | L25: S11 | M25: S12 | N25: S13 | O25: S14 | P25: S15 | Q25: S16 | R25: S17 | S25: S18 | T25: S19 | U25: S20 | V25: S21 | W25: S22 | X25: S23 | Y25: S24 | Z25: S25 | AA25: S26 | AB25: S27 | AC25: S28 | AD25: S29 | AE25: S30 | AF25: S31 | AG25: S32 | AH25: S33 | AI25: S34 | AJ25: S35 | AK25: S36 | AL25: S37 | AM25: S38 | AN25: S39 | AO25: S40 | AP25: S41 | AQ25: S42 | AR25: S43 | AS25: S44 | AT25: S45 | AU25: S46 | AV25: S47 | AW25: S48 | AX25: S49 | AY25: S50 | AZ25: S51 | BA25: S52 | BB25: S53 | BC25: S54 | BD25: S55 | BE25: S56 | BF25: S57 | BG25: S58 | BH25: S59 | BI25: TOTAL
A26: Seg | F26: 35 | G26: 64 | BI26: =SUM(B26:BH26)
A27: Ter | C27: 40 | E27: 21 | F27: 68 | L27: 33 | BI27: =SUM(B27:BH27)
A28: Qua | D28: 11 | E28: 13 | F28: 16 | J28: 3 | L28: 36 | BI28: =SUM(B28:BH28)
A29: Qui | F29: 52 | K29: 1 | M29: 25 | BI29: =SUM(B29:BH29)
A30: Sex | H30: 26 | J30: 1 | K30: 17 | L30: 2 | BI30: =SUM(B30:BH30)
A31: Sáb | BI31: =SUM(B31:BH31)
A32: Dom | BI32: =SUM(B32:BH32)
A33: TOTAL | B33: =SUM(B26:B32) | C33: =SUM(C26:C32) | D33: =SUM(D26:D32) | E33: =SUM(E26:E32) | F33: =SUM(F26:F32) | G33: =SUM(G26:G32) | H33: =SUM(H26:H32) | I33: =SUM(I26:I32) | ... BI33: =SUM(BI26:BI32)
A34: Morro Tetéu — REDE (metros/dia) | EQ: 4 | Total: 1255m
B35: S1 | C35: S2 | D35: S3 | E35: S4 | F35: S5 | G35: S6 | H35: S7 | I35: S8 | J35: S9 | K35: S10 | L35: S11 | M35: S12 | N35: S13 | O35: S14 | P35: S15 | Q35: S16 | R35: S17 | S35: S18 | T35: S19 | U35: S20 | V35: S21 | W35: S22 | X35: S23 | Y35: S24 | Z35: S25 | AA35: S26 | AB35: S27 | AC35: S28 | AD35: S29 | AE35: S30 | AF35: S31 | AG35: S32 | AH35: S33 | AI35: S34 | AJ35: S35 | AK35: S36 | AL35: S37 | AM35: S38 | AN35: S39 | AO35: S40 | AP35: S41 | AQ35: S42 | AR35: S43 | AS35: S44 | AT35: S45 | AU35: S46 | AV35: S47 | AW35: S48 | AX35: S49 | AY35: S50 | AZ35: S51 | BA35: S52 | BB35: S53 | BC35: S54 | BD35: S55 | BE35: S56 | BF35: S57 | BG35: S58 | BH35: S59 | BI35: TOTAL
A36: Seg | C36: 16 | D36: 3 | F36: 63 | G36: 5 | I36: 71 | J36: 7 | L36: 26 | BI36: =SUM(B36:BH36)
A37: Ter | C37: 37 | D37: 18 | E37: 9 | F37: 16 | G37: 20 | H37: 18 | I37: 40 | J37: 24 | L37: 61 | BI37: =SUM(B37:BH37)
A38: Qua | C38: 8 | D38: 7 | E38: 18 | F38: 45 | G38: 34 | H38: 100 | I38: 12 | J38: 7 | K38: 50 | L38: 15 | BI38: =SUM(B38:BH38)
A39: Qui | D39: 62 | E39: 9 | F39: 16 | H39: 60 | I39: 38 | K39: 44 | M39: 20 | BI39: =SUM(B39:BH39)
A40: Sex | C40: 6 | D40: 31 | E40: 60 | F40: 23 | G40: 6 | H40: 17 | I40: 41 | K40: 30 | L40: 14 | BI40: =SUM(B40:BH40)
A41: Sáb | C41: 20 | F41: 3 | G41: 25 | BI41: =SUM(B41:BH41)
A42: Dom | BI42: =SUM(B42:BH42)
A43: TOTAL | B43: =SUM(B36:B42) | C43: =SUM(C36:C42) | D43: =SUM(D36:D42) | E43: =SUM(E36:E42) | F43: =SUM(F36:F42) | G43: =SUM(G36:G42) | H43: =SUM(H36:H42) | I43: =SUM(I36:I42) | ... BI43: =SUM(BI36:BI42)
A44: Vila Criadores — REDE (metros/dia) | EQ: 7 | Total: 880m
B45: S1 | C45: S2 | D45: S3 | E45: S4 | F45: S5 | G45: S6 | H45: S7 | I45: S8 | J45: S9 | K45: S10 | L45: S11 | M45: S12 | N45: S13 | O45: S14 | P45: S15 | Q45: S16 | R45: S17 | S45: S18 | T45: S19 | U45: S20 | V45: S21 | W45: S22 | X45: S23 | Y45: S24 | Z45: S25 | AA45: S26 | AB45: S27 | AC45: S28 | AD45: S29 | AE45: S30 | AF45: S31 | AG45: S32 | AH45: S33 | AI45: S34 | AJ45: S35 | AK45: S36 | AL45: S37 | AM45: S38 | AN45: S39 | AO45: S40 | AP45: S41 | AQ45: S42 | AR45: S43 | AS45: S44 | AT45: S45 | AU45: S46 | AV45: S47 | AW45: S48 | AX45: S49 | AY45: S50 | AZ45: S51 | BA45: S52 | BB45: S53 | BC45: S54 | BD45: S55 | BE45: S56 | BF45: S57 | BG45: S58 | BH45: S59 | BI45: TOTAL
A46: Seg | C46: 7 | G46: 58 | H46: 48 | I46: 2 | L46: 257 | BI46: =SUM(B46:BH46)
A47: Ter | C47: 13 | J47: 4 | L47: 94 | BI47: =SUM(B47:BH47)
A48: Qua | J48: 2 | K48: 8 | L48: 2 | BI48: =SUM(B48:BH48)
A49: Qui | G49: 54 | H49: 47 | K49: 2 | M49: 101 | BI49: =SUM(B49:BH49)
A50: Sex | G50: 30 | H50: 30 | I50: 2 | K50: 2 | L50: 66 | BI50: =SUM(B50:BH50)
A51: Sáb | G51: 10 | L51: 41 | BI51: =SUM(B51:BH51)
A52: Dom | BI52: =SUM(B52:BH52)
A53: TOTAL | B53: =SUM(B46:B52) | C53: =SUM(C46:C52) | D53: =SUM(D46:D52) | E53: =SUM(E46:E52) | F53: =SUM(F46:F52) | G53: =SUM(G46:G52) | H53: =SUM(H46:H52) | I53: =SUM(I46:I52) | ... BI53: =SUM(BI46:BI52)
A54: Pantanal Baixo — REDE (metros/dia) | EQ: 8 | Total: 874m
B55: S1 | C55: S2 | D55: S3 | E55: S4 | F55: S5 | G55: S6 | H55: S7 | I55: S8 | J55: S9 | K55: S10 | L55: S11 | M55: S12 | N55: S13 | O55: S14 | P55: S15 | Q55: S16 | R55: S17 | S55: S18 | T55: S19 | U55: S20 | V55: S21 | W55: S22 | X55: S23 | Y55: S24 | Z55: S25 | AA55: S26 | AB55: S27 | AC55: S28 | AD55: S29 | AE55: S30 | AF55: S31 | AG55: S32 | AH55: S33 | AI55: S34 | AJ55: S35 | AK55: S36 | AL55: S37 | AM55: S38 | AN55: S39 | AO55: S40 | AP55: S41 | AQ55: S42 | AR55: S43 | AS55: S44 | AT55: S45 | AU55: S46 | AV55: S47 | AW55: S48 | AX55: S49 | AY55: S50 | AZ55: S51 | BA55: S52 | BB55: S53 | BC55: S54 | BD55: S55 | BE55: S56 | BF55: S57 | BG55: S58 | BH55: S59 | BI55: TOTAL
A56: Seg | B56: 3 | C56: 3 | G56: 24 | I56: 43 | J56: 7 | K56: 12 | BI56: =SUM(B56:BH56)
A57: Ter | B57: 3 | C57: 3 | E57: 24 | G57: 4 | I57: 11 | J57: 29 | BI57: =SUM(B57:BH57)
A58: Qua | B58: 3 | C58: 3 | D58: 11 | E58: 37 | G58: 7 | H58: 102 | I58: 8 | J58: 13 | K58: 34 | L58: 58 | BI58: =SUM(B58:BH58)
A59: Qui | C59: 3 | D59: 3 | E59: 30 | F59: 9 | I59: 3 | K59: 64 | M59: 37 | BI59: =SUM(B59:BH59)
A60: Sex | C60: 3 | E60: 8 | F60: 15 | H60: 15 | I60: 3 | J60: 33 | K60: 126 | L60: 20 | BI60: =SUM(B60:BH60)
A61: Sáb | C61: 3 | F61: 22 | G61: 13 | J61: 22 | BI61: =SUM(B61:BH61)
A62: Dom | BI62: =SUM(B62:BH62)
A63: TOTAL | B63: =SUM(B56:B62) | C63: =SUM(C56:C62) | D63: =SUM(D56:D62) | E63: =SUM(E56:E62) | F63: =SUM(F56:F62) | G63: =SUM(G56:G62) | H63: =SUM(H56:H62) | I63: =SUM(I56:I62) | ... BI63: =SUM(BI56:BI62)

Sheet HEATMAP_LIG
A1: MAPA DE CALOR — LIGAÇÕES POR DIA | Vermelho = mais ligações
A2: Branco = 0 | Rosa claro = poucas | Vermelho escuro = muitas ligações | Cada bloco = 1 núcleo
A4: São Manoel — LIGAÇÕES (un/dia) | Total: 127 lig
B5: S1 | C5: S2 | D5: S3 | E5: S4 | F5: S5 | G5: S6 | H5: S7 | I5: S8 | J5: S9 | K5: S10 | L5: S11 | M5: S12 | N5: S13 | O5: S14 | P5: S15 | Q5: S16 | R5: S17 | S5: S18 | T5: S19 | U5: S20 | V5: S21 | W5: S22 | X5: S23 | Y5: S24 | Z5: S25 | AA5: S26 | AB5: S27 | AC5: S28 | AD5: S29 | AE5: S30 | AF5: S31 | AG5: S32 | AH5: S33 | AI5: S34 | AJ5: S35 | AK5: S36 | AL5: S37 | AM5: S38 | AN5: S39 | AO5: S40 | AP5: S41 | AQ5: S42 | AR5: S43 | AS5: S44 | AT5: S45 | AU5: S46 | AV5: S47 | AW5: S48 | AX5: S49 | AY5: S50 | AZ5: S51 | BA5: S52 | BB5: S53 | BC5: S54 | BD5: S55 | BE5: S56 | BF5: S57 | BG5: S58 | BH5: S59 | BI5: TOTAL
A6: Seg | F6: 19 | BI6: =SUM(B6:BH6)
A7: Ter | F7: 13 | I7: 7 | BI7: =SUM(B7:BH7)
A8: Qua | C8: 12 | E8: 8 | F8: 4 | G8: 7 | BI8: =SUM(B8:BH8)
A9: Qui | D9: 2 | F9: 28 | G9: 6 | BI9: =SUM(B9:BH9)
A10: Sex | D10: 2 | G10: 12 | BI10: =SUM(B10:BH10)
A11: Sáb | F11: 7 | BI11: =SUM(B11:BH11)
A12: Dom | BI12: =SUM(B12:BH12)
A13: TOTAL | B13: =SUM(B6:B12) | C13: =SUM(C6:C12) | D13: =SUM(D6:D12) | E13: =SUM(E6:E12) | F13: =SUM(F6:F12) | G13: =SUM(G6:G12) | H13: =SUM(H6:H12) | I13: =SUM(I6:I12) | ... BI13: =SUM(BI6:BI12)
A14: João Carlos — LIGAÇÕES (un/dia) | Total: 166 lig
B15: S1 | C15: S2 | D15: S3 | E15: S4 | F15: S5 | G15: S6 | H15: S7 | I15: S8 | J15: S9 | K15: S10 | L15: S11 | M15: S12 | N15: S13 | O15: S14 | P15: S15 | Q15: S16 | R15: S17 | S15: S18 | T15: S19 | U15: S20 | V15: S21 | W15: S22 | X15: S23 | Y15: S24 | Z15: S25 | AA15: S26 | AB15: S27 | AC15: S28 | AD15: S29 | AE15: S30 | AF15: S31 | AG15: S32 | AH15: S33 | AI15: S34 | AJ15: S35 | AK15: S36 | AL15: S37 | AM15: S38 | AN15: S39 | AO15: S40 | AP15: S41 | AQ15: S42 | AR15: S43 | AS15: S44 | AT15: S45 | AU15: S46 | AV15: S47 | AW15: S48 | AX15: S49 | AY15: S50 | AZ15: S51 | BA15: S52 | BB15: S53 | BC15: S54 | BD15: S55 | BE15: S56 | BF15: S57 | BG15: S58 | BH15: S59 | BI15: TOTAL
A16: Seg | I16: 4 | J16: 2 | BI16: =SUM(B16:BH16)
A17: Ter | F17: 7 | I17: 7 | BI17: =SUM(B17:BH17)
A18: Qua | F18: 15 | G18: 23 | H18: 14 | I18: 6 | K18: 21 | BI18: =SUM(B18:BH18)
A19: Qui | G19: 12 | H19: 16 | I19: 4 | L19: 12 | BI19: =SUM(B19:BH19)
A20: Sex | H20: 13 | J20: 1 | BI20: =SUM(B20:BH20)
A21: Sáb | I21: 9 | BI21: =SUM(B21:BH21)
A22: Dom | BI22: =SUM(B22:BH22)
A23: TOTAL | B23: =SUM(B16:B22) | C23: =SUM(C16:C22) | D23: =SUM(D16:D22) | E23: =SUM(E16:E22) | F23: =SUM(F16:F22) | G23: =SUM(G16:G22) | H23: =SUM(H16:H22) | I23: =SUM(I16:I22) | ... BI23: =SUM(BI16:BI22)
A24: Vila Israel — LIGAÇÕES (un/dia) | Total: 105 lig
B25: S1 | C25: S2 | D25: S3 | E25: S4 | F25: S5 | G25: S6 | H25: S7 | I25: S8 | J25: S9 | K25: S10 | L25: S11 | M25: S12 | N25: S13 | O25: S14 | P25: S15 | Q25: S16 | R25: S17 | S25: S18 | T25: S19 | U25: S20 | V25: S21 | W25: S22 | X25: S23 | Y25: S24 | Z25: S25 | AA25: S26 | AB25: S27 | AC25: S28 | AD25: S29 | AE25: S30 | AF25: S31 | AG25: S32 | AH25: S33 | AI25: S34 | AJ25: S35 | AK25: S36 | AL25: S37 | AM25: S38 | AN25: S39 | AO25: S40 | AP25: S41 | AQ25: S42 | AR25: S43 | AS25: S44 | AT25: S45 | AU25: S46 | AV25: S47 | AW25: S48 | AX25: S49 | AY25: S50 | AZ25: S51 | BA25: S52 | BB25: S53 | BC25: S54 | BD25: S55 | BE25: S56 | BF25: S57 | BG25: S58 | BH25: S59 | BI25: TOTAL
A26: Seg | H26: 3 | I26: 4 | J26: 12 | BI26: =SUM(B26:BH26)
A27: Ter | I27: 8 | L27: 4 | BI27: =SUM(B27:BH27)
A28: Qua | H28: 20 | I28: 4 | J28: 7 | L28: 6 | BI28: =SUM(B28:BH28)
A29: Qui | I29: 10 | K29: 8 | M29: 9 | BI29: =SUM(B29:BH29)
A30: Sex | J30: 10 | BI30: =SUM(B30:BH30)
A31: Sáb | BI31: =SUM(B31:BH31)
A32: Dom | BI32: =SUM(B32:BH32)
A33: TOTAL | B33: =SUM(B26:B32) | C33: =SUM(C26:C32) | D33: =SUM(D26:D32) | E33: =SUM(E26:E32) | F33: =SUM(F26:F32) | G33: =SUM(G26:G32) | H33: =SUM(H26:H32) | I33: =SUM(I26:I32) | ... BI33: =SUM(BI26:BI32)
A34: Morro Tetéu — LIGAÇÕES (un/dia) | Total: 196 lig
B35: S1 | C35: S2 | D35: S3 | E35: S4 | F35: S5 | G35: S6 | H35: S7 | I35: S8 | J35: S9 | K35: S10 | L35: S11 | M35: S12 | N35: S13 | O35: S14 | P35: S15 | Q35: S16 | R35: S17 | S35: S18 | T35: S19 | U35: S20 | V35: S21 | W35: S22 | X35: S23 | Y35: S24 | Z35: S25 | AA35: S26 | AB35: S27 | AC35: S28 | AD35: S29 | AE35: S30 | AF35: S31 | AG35: S32 | AH35: S33 | AI35: S34 | AJ35: S35 | AK35: S36 | AL35: S37 | AM35: S38 | AN35: S39 | AO35: S40 | AP35: S41 | AQ35: S42 | AR35: S43 | AS35: S44 | AT35: S45 | AU35: S46 | AV35: S47 | AW35: S48 | AX35: S49 | AY35: S50 | AZ35: S51 | BA35: S52 | BB35: S53 | BC35: S54 | BD35: S55 | BE35: S56 | BF35: S57 | BG35: S58 | BH35: S59 | BI35: TOTAL
A36: Seg | F36: 6 | G36: 4 | J36: 21 | K36: 1 | BI36: =SUM(B36:BH36)
A37: Ter | F37: 9 | I37: 3 | J37: 6 | L37: 4 | BI37: =SUM(B37:BH37)
A38: Qua | D38: 1 | F38: 1 | I38: 8 | J38: 12 | K38: 9 | L38: 2 | BI38: =SUM(B38:BH38)
A39: Qui | E39: 5 | G39: 19 | H39: 4 | I39: 5 | K39: 7 | L39: 4 | BI39: =SUM(B39:BH39)
A40: Sex | E40: 4 | F40: 17 | G40: 8 | I40: 4 | J40: 18 | K40: 14 | BI40: =SUM(B40:BH40)
A41: Sáb | BI41: =SUM(B41:BH41)
A42: Dom | BI42: =SUM(B42:BH42)
A43: TOTAL | B43: =SUM(B36:B42) | C43: =SUM(C36:C42) | D43: =SUM(D36:D42) | E43: =SUM(E36:E42) | F43: =SUM(F36:F42) | G43: =SUM(G36:G42) | H43: =SUM(H36:H42) | I43: =SUM(I36:I42) | ... BI43: =SUM(BI36:BI42)
A44: Vila Criadores — LIGAÇÕES (un/dia) | Total: 212 lig
B45: S1 | C45: S2 | D45: S3 | E45: S4 | F45: S5 | G45: S6 | H45: S7 | I45: S8 | J45: S9 | K45: S10 | L45: S11 | M45: S12 | N45: S13 | O45: S14 | P45: S15 | Q45: S16 | R45: S17 | S45: S18 | T45: S19 | U45: S20 | V45: S21 | W45: S22 | X45: S23 | Y45: S24 | Z45: S25 | AA45: S26 | AB45: S27 | AC45: S28 | AD45: S29 | AE45: S30 | AF45: S31 | AG45: S32 | AH45: S33 | AI45: S34 | AJ45: S35 | AK45: S36 | AL45: S37 | AM45: S38 | AN45: S39 | AO45: S40 | AP45: S41 | AQ45: S42 | AR45: S43 | AS45: S44 | AT45: S45 | AU45: S46 | AV45: S47 | AW45: S48 | AX45: S49 | AY45: S50 | AZ45: S51 | BA45: S52 | BB45: S53 | BC45: S54 | BD45: S55 | BE45: S56 | BF45: S57 | BG45: S58 | BH45: S59 | BI45: TOTAL
A46: Seg | B46: 3 | C46: 7 | D46: 5 | F46: 5 | L46: 2 | BI46: =SUM(B46:BH46)
A47: Ter | B47: 11 | C47: 12 | D47: 9 | E47: 7 | F47: 5 | G47: 3 | H47: 2 | BI47: =SUM(B47:BH47)
A48: Qua | B48: 7 | C48: 10 | D48: 9 | E48: 4 | K48: 2 | BI48: =SUM(B48:BH48)
A49: Qui | C49: 8 | D49: 16 | E49: 7 | F49: 9 | G49: 4 | I49: 1 | BI49: =SUM(B49:BH49)
A50: Sex | C50: 15 | D50: 10 | E50: 3 | F50: 2 | I50: 6 | K50: 5 | L50: 2 | BI50: =SUM(B50:BH50)
A51: Sáb | C51: 17 | D51: 3 | F51: 1 | BI51: =SUM(B51:BH51)
A52: Dom | BI52: =SUM(B52:BH52)
A53: TOTAL | B53: =SUM(B46:B52) | C53: =SUM(C46:C52) | D53: =SUM(D46:D52) | E53: =SUM(E46:E52) | F53: =SUM(F46:F52) | G53: =SUM(G46:G52) | H53: =SUM(H46:H52) | I53: =SUM(I46:I52) | ... BI53: =SUM(BI46:BI52)
A54: Pantanal Baixo — LIGAÇÕES (un/dia) | Total: 91 lig
B55: S1 | C55: S2 | D55: S3 | E55: S4 | F55: S5 | G55: S6 | H55: S7 | I55: S8 | J55: S9 | K55: S10 | L55: S11 | M55: S12 | N55: S13 | O55: S14 | P55: S15 | Q55: S16 | R55: S17 | S55: S18 | T55: S19 | U55: S20 | V55: S21 | W55: S22 | X55: S23 | Y55: S24 | Z55: S25 | AA55: S26 | AB55: S27 | AC55: S28 | AD55: S29 | AE55: S30 | AF55: S31 | AG55: S32 | AH55: S33 | AI55: S34 | AJ55: S35 | AK55: S36 | AL55: S37 | AM55: S38 | AN55: S39 | AO55: S40 | AP55: S41 | AQ55: S42 | AR55: S43 | AS55: S44 | AT55: S45 | AU55: S46 | AV55: S47 | AW55: S48 | AX55: S49 | AY55: S50 | AZ55: S51 | BA55: S52 | BB55: S53 | BC55: S54 | BD55: S55 | BE55: S56 | BF55: S57 | BG55: S58 | BH55: S59 | BI55: TOTAL
A56: Seg | K56: 2 | L56: 4 | BI56: =SUM(B56:BH56)
A57: Ter | H57: 5 | L57: 2 | BI57: =SUM(B57:BH57)
A58: Qua | H58: 13 | L58: 2 | BI58: =SUM(B58:BH58)
A59: Qui | H59: 8 | K59: 1 | M59: 13 | BI59: =SUM(B59:BH59)
A60: Sex | F60: 14 | I60: 20 | K60: 1 | L60: 6 | BI60: =SUM(B60:BH60)
A61: Sáb | BI61: =SUM(B61:BH61)
A62: Dom | BI62: =SUM(B62:BH62)
A63: TOTAL | B63: =SUM(B56:B62) | C63: =SUM(C56:C62) | D63: =SUM(D56:D62) | E63: =SUM(E56:E62) | F63: =SUM(F56:F62) | G63: =SUM(G56:G62) | H63: =SUM(H56:H62) | I63: =SUM(I56:I62) | ... BI63: =SUM(BI56:BI62)

Sheet TENDENCIAS
A1: TENDÊNCIAS — Média móvel 7 dias por núcleo | Rede + Ligações + Indicador de tendência
A3: São Manoel | EQ: 8 | Tendência rede: DESCENDO | Tendência lig: DESCENDO
A4: SEMANA | B4: REDE 7d | C4: LIG 7d | D4: REDE ACUM | E4: LIG ACUM | F4: REDE/DIA | G4: LIG/DIA | H4: PVs/SEM | I4: TEND REDE | J4: TEND LIG | K4: EQ | L4: m/eq/dia | M4: lig/eq/dia
A5: S1 | B5: 4.1 | C5: 0.3 | D5: =B5 | E5: =C5 | F5: =ROUND(B5/7,1) | G5: =ROUND(C5/7,1) | H5: 6 | I5: INÍCIO | J5: INÍCIO | K5: 8 | L5: =IF(K5>0,ROUND(F5/K5,1),0) | M5: 0.25
A6: S2 | B6: 9.8 | C6: 1.9 | D6: =D5+B6 | E6: =E5+C6 | F6: =ROUND(B6/7,1) | G6: =ROUND(C6/7,1) | H6: 5 | I6: =IF(B6>B5*1.05,"SUBINDO",IF(B6<B5*0.95,"DESCENDO","ESTÁVEL")) | J6: =IF(C6>C5*1.05,"SUBINDO",IF(C6<C5*0.95,"DESCENDO","ESTÁVEL")) | K6: 8 | L6: =IF(K6>0,ROUND(F6/K6,1),0) | M6: 0.1
A7: S3 | B7: 28.6 | C7: 0.4 | D7: =D6+B7 | E7: =E6+C7 | F7: =ROUND(B7/7,1) | G7: =ROUND(C7/7,1) | H7: 4 | I7: =IF(B7>B6*1.05,"SUBINDO",IF(B7<B6*0.95,"DESCENDO","ESTÁVEL")) | J7: =IF(C7>C6*1.05,"SUBINDO",IF(C7<C6*0.95,"DESCENDO","ESTÁVEL")) | K7: 8 | L7: =IF(K7>0,ROUND(F7/K7,1),0) | M7: 0.25
A8: S4 | B8: 30.6 | C8: 7.7 | D8: =D7+B8 | E8: =E7+C8 | F8: =ROUND(B8/7,1) | G8: =ROUND(C8/7,1) | H8: 6 | I8: =IF(B8>B7*1.05,"SUBINDO",IF(B8<B7*0.95,"DESCENDO","ESTÁVEL")) | J8: =IF(C8>C7*1.05,"SUBINDO",IF(C8<C7*0.95,"DESCENDO","ESTÁVEL")) | K8: 8 | L8: =IF(K8>0,ROUND(F8/K8,1),0) | M8: 1.48
A9: S5 | B9: 41.9 | C9: 5.5 | D9: =D8+B9 | E9: =E8+C9 | F9: =ROUND(B9/7,1) | G9: =ROUND(C9/7,1) | H9: 5 | I9: =IF(B9>B8*1.05,"SUBINDO",IF(B9<B8*0.95,"DESCENDO","ESTÁVEL")) | J9: =IF(C9>C8*1.05,"SUBINDO",IF(C9<C8*0.95,"DESCENDO","ESTÁVEL")) | K9: 8 | L9: =IF(K9>0,ROUND(F9/K9,1),0) | M9: 0.62
A10: S6 | B10: 20 | C10: 1.2 | D10: =D9+B10 | E10: =E9+C10 | F10: =ROUND(B10/7,1) | G10: =ROUND(C10/7,1) | H10: 3 | I10: =IF(B10>B9*1.05,"SUBINDO",IF(B10<B9*0.95,"DESCENDO","ESTÁVEL")) | J10: =IF(C10>C9*1.05,"SUBINDO",IF(C10<C9*0.95,"DESCENDO","ESTÁVEL")) | K10: 8 | L10: =IF(K10>0,ROUND(F10/K10,1),0) | M10: 0
A11: S7 | B11: 23.9 | C11: 0.4 | D11: =D10+B11 | E11: =E10+C11 | F11: =ROUND(B11/7,1) | G11: =ROUND(C11/7,1) | H11: 5 | I11: =IF(B11>B10*1.05,"SUBINDO",IF(B11<B10*0.95,"DESCENDO","ESTÁVEL")) | J11: =IF(C11>C10*1.05,"SUBINDO",IF(C11<C10*0.95,"DESCENDO","ESTÁVEL")) | K11: 8 | L11: =IF(K11>0,ROUND(F11/K11,1),0) | M11: 0.18
A12: S8 | B12: 12.8 | C12: 0.2 | D12: =D11+B12 | E12: =E11+C12 | F12: =ROUND(B12/7,1) | G12: =ROUND(C12/7,1) | H12: 13 | I12: =IF(B12>B11*1.05,"SUBINDO",IF(B12<B11*0.95,"DESCENDO","ESTÁVEL")) | J12: =IF(C12>C11*1.05,"SUBINDO",IF(C12<C11*0.95,"DESCENDO","ESTÁVEL")) | K12: 8 | L12: =IF(K12>0,ROUND(F12/K12,1),0) | M12: 0
A13: S9 | B13: 5.2 | C13: 0 | D13: =D12+B13 | E13: =E12+C13 | F13: =ROUND(B13/7,1) | G13: =ROUND(C13/7,1) | H13: 6 | I13: =IF(B13>B12*1.05,"SUBINDO",IF(B13<B12*0.95,"DESCENDO","ESTÁVEL")) | J13: =IF(C13>C12*1.05,"SUBINDO",IF(C13<C12*0.95,"DESCENDO","ESTÁVEL")) | K13: 8 | L13: =IF(K13>0,ROUND(F13/K13,1),0) | M13: 0
A14: S10 | B14: 2.1 | C14: 0 | D14: =D13+B14 | E14: =E13+C14 | F14: =ROUND(B14/7,1) | G14: =ROUND(C14/7,1) | H14: 6 | I14: =IF(B14>B13*1.05,"SUBINDO",IF(B14<B13*0.95,"DESCENDO","ESTÁVEL")) | J14: =IF(C14>C13*1.05,"SUBINDO",IF(C14<C13*0.95,"DESCENDO","ESTÁVEL")) | K14: 8 | L14: =IF(K14>0,ROUND(F14/K14,1),0) | M14: 0
A15: S11 | B15: 4.9 | C15: 0 | D15: =D14+B15 | E15: =E14+C15 | F15: =ROUND(B15/7,1) | G15: =ROUND(C15/7,1) | H15: 3 | I15: =IF(B15>B14*1.05,"SUBINDO",IF(B15<B14*0.95,"DESCENDO","ESTÁVEL")) | J15: =IF(C15>C14*1.05,"SUBINDO",IF(C15<C14*0.95,"DESCENDO","ESTÁVEL")) | K15: 8 | L15: =IF(K15>0,ROUND(F15/K15,1),0) | M15: 0
A17: João Carlos | EQ: 3 | Tendência rede: DESCENDO | Tendência lig: ESTÁVEL
A18: SEMANA | B18: REDE 7d | C18: LIG 7d | D18: REDE ACUM | E18: LIG ACUM | F18: REDE/DIA | G18: LIG/DIA | H18: PVs/SEM | I18: TEND REDE | J18: TEND LIG | K18: EQ | L18: m/eq/dia | M18: lig/eq/dia
A19: S1 | B19: 18.8 | C19: 0 | D19: =B19 | E19: =C19 | F19: =ROUND(B19/7,1) | G19: =ROUND(C19/7,1) | H19: 5 | I19: INÍCIO | J19: INÍCIO | K19: 3 | L19: =IF(K19>0,ROUND(F19/K19,1),0) | M19: 0
A20: S2 | B20: 14.2 | C20: 0 | D20: =D19+B20 | E20: =E19+C20 | F20: =ROUND(B20/7,1) | G20: =ROUND(C20/7,1) | H20: 6 | I20: =IF(B20>B19*1.05,"SUBINDO",IF(B20<B19*0.95,"DESCENDO","ESTÁVEL")) | J20: =IF(C20>C19*1.05,"SUBINDO",IF(C20<C19*0.95,"DESCENDO","ESTÁVEL")) | K20: 3 | L20: =IF(K20>0,ROUND(F20/K20,1),0) | M20: 0
A21: S3 | B21: 8.6 | C21: 0 | D21: =D20+B21 | E21: =E20+C21 | F21: =ROUND(B21/7,1) | G21: =ROUND(C21/7,1) | H21: 3 | I21: =IF(B21>B20*1.05,"SUBINDO",IF(B21<B20*0.95,"DESCENDO","ESTÁVEL")) | J21: =IF(C21>C20*1.05,"SUBINDO",IF(C21<C20*0.95,"DESCENDO","ESTÁVEL")) | K21: 3 | L21: =IF(K21>0,ROUND(F21/K21,1),0) | M21: 0
A22: S4 | B22: 12.8 | C22: 2.2 | D22: =D21+B22 | E22: =E21+C22 | F22: =ROUND(B22/7,1) | G22: =ROUND(C22/7,1) | H22: 4 | I22: =IF(B22>B21*1.05,"SUBINDO",IF(B22<B21*0.95,"DESCENDO","ESTÁVEL")) | J22: =IF(C22>C21*1.05,"SUBINDO",IF(C22<C21*0.95,"DESCENDO","ESTÁVEL")) | K22: 3 | L22: =IF(K22>0,ROUND(F22/K22,1),0) | M22: 1.83
A23: S5 | B23: 7.4 | C23: 4.4 | D23: =D22+B23 | E23: =E22+C23 | F23: =ROUND(B23/7,1) | G23: =ROUND(C23/7,1) | H23: 2 | I23: =IF(B23>B22*1.05,"SUBINDO",IF(B23<B22*0.95,"DESCENDO","ESTÁVEL")) | J23: =IF(C23>C22*1.05,"SUBINDO",IF(C23<C22*0.95,"DESCENDO","ESTÁVEL")) | K23: 3 | L23: =IF(K23>0,ROUND(F23/K23,1),0) | M23: 3.83
A24: S6 | B24: 2.2 | C24: 7.4 | D24: =D23+B24 | E24: =E23+C24 | F24: =ROUND(B24/7,1) | G24: =ROUND(C24/7,1) | H24: 2 | I24: =IF(B24>B23*1.05,"SUBINDO",IF(B24<B23*0.95,"DESCENDO","ESTÁVEL")) | J24: =IF(C24>C23*1.05,"SUBINDO",IF(C24<C23*0.95,"DESCENDO","ESTÁVEL")) | K24: 3 | L24: =IF(K24>0,ROUND(F24/K24,1),0) | M24: 0
A25: S7 | B25: 12.9 | C25: 4.1 | D25: =D24+B25 | E25: =E24+C25 | F25: =ROUND(B25/7,1) | G25: =ROUND(C25/7,1) | H25: 5 | I25: =IF(B25>B24*1.05,"SUBINDO",IF(B25<B24*0.95,"DESCENDO","ESTÁVEL")) | J25: =IF(C25>C24*1.05,"SUBINDO",IF(C25<C24*0.95,"DESCENDO","ESTÁVEL")) | K25: 3 | L25: =IF(K25>0,ROUND(F25/K25,1),0) | M25: 1.2
A26: S8 | B26: 11.4 | C26: 0.3 | D26: =D25+B26 | E26: =E25+C26 | F26: =ROUND(B26/7,1) | G26: =ROUND(C26/7,1) | H26: 17 | I26: =IF(B26>B25*1.05,"SUBINDO",IF(B26<B25*0.95,"DESCENDO","ESTÁVEL")) | J26: =IF(C26>C25*1.05,"SUBINDO",IF(C26<C25*0.95,"DESCENDO","ESTÁVEL")) | K26: 3 | L26: =IF(K26>0,ROUND(F26/K26,1),0) | M26: 0
A27: S9 | B27: 3.7 | C27: 0 | D27: =D26+B27 | E27: =E26+C27 | F27: =ROUND(B27/7,1) | G27: =ROUND(C27/7,1) | H27: 1 | I27: =IF(B27>B26*1.05,"SUBINDO",IF(B27<B26*0.95,"DESCENDO","ESTÁVEL")) | J27: =IF(C27>C26*1.05,"SUBINDO",IF(C27<C26*0.95,"DESCENDO","ESTÁVEL")) | K27: 3 | L27: =IF(K27>0,ROUND(F27/K27,1),0) | M27: 0
A28: S10 | B28: 13.4 | C28: 0 | D28: =D27+B28 | E28: =E27+C28 | F28: =ROUND(B28/7,1) | G28: =ROUND(C28/7,1) | H28: 9 | I28: =IF(B28>B27*1.05,"SUBINDO",IF(B28<B27*0.95,"DESCENDO","ESTÁVEL")) | J28: =IF(C28>C27*1.05,"SUBINDO",IF(C28<C27*0.95,"DESCENDO","ESTÁVEL")) | K28: 3 | L28: =IF(K28>0,ROUND(F28/K28,1),0) | M28: 0
A30: Vila Israel | EQ: 6 | Tendência rede: DESCENDO | Tendência lig: ESTÁVEL
A31: SEMANA | B31: REDE 7d | C31: LIG 7d | D31: REDE ACUM | E31: LIG ACUM | F31: REDE/DIA | G31: LIG/DIA | H31: PVs/SEM | I31: TEND REDE | J31: TEND LIG | K31: EQ | L31: m/eq/dia | M31: lig/eq/dia
A32: S1 | B32: 5.7 | C32: 0 | D32: =B32 | E32: =C32 | F32: =ROUND(B32/7,1) | G32: =ROUND(C32/7,1) | H32: 1 | I32: INÍCIO | J32: INÍCIO | K32: 6 | L32: =IF(K32>0,ROUND(F32/K32,1),0) | M32: 0
A33: S2 | B33: 1.6 | C33: 0 | D33: =D32+B33 | E33: =E32+C33 | F33: =ROUND(B33/7,1) | G33: =ROUND(C33/7,1) | H33: 1 | I33: =IF(B33>B32*1.05,"SUBINDO",IF(B33<B32*0.95,"DESCENDO","ESTÁVEL")) | J33: =IF(C33>C32*1.05,"SUBINDO",IF(C33<C32*0.95,"DESCENDO","ESTÁVEL")) | K33: 6 | L33: =IF(K33>0,ROUND(F33/K33,1),0) | M33: 0
A34: S3 | B34: 9.8 | C34: 0 | D34: =D33+B34 | E34: =E33+C34 | F34: =ROUND(B34/7,1) | G34: =ROUND(C34/7,1) | H34: 4 | I34: =IF(B34>B33*1.05,"SUBINDO",IF(B34<B33*0.95,"DESCENDO","ESTÁVEL")) | J34: =IF(C34>C33*1.05,"SUBINDO",IF(C34<C33*0.95,"DESCENDO","ESTÁVEL")) | K34: 6 | L34: =IF(K34>0,ROUND(F34/K34,1),0) | M34: 0
A35: S4 | B35: 23.2 | C35: 0 | D35: =D34+B35 | E35: =E34+C35 | F35: =ROUND(B35/7,1) | G35: =ROUND(C35/7,1) | H35: 3 | I35: =IF(B35>B34*1.05,"SUBINDO",IF(B35<B34*0.95,"DESCENDO","ESTÁVEL")) | J35: =IF(C35>C34*1.05,"SUBINDO",IF(C35<C34*0.95,"DESCENDO","ESTÁVEL")) | K35: 6 | L35: =IF(K35>0,ROUND(F35/K35,1),0) | M35: 0
A36: S5 | B36: 12.9 | C36: 0 | D36: =D35+B36 | E36: =E35+C36 | F36: =ROUND(B36/7,1) | G36: =ROUND(C36/7,1) | H36: 1 | I36: =IF(B36>B35*1.05,"SUBINDO",IF(B36<B35*0.95,"DESCENDO","ESTÁVEL")) | J36: =IF(C36>C35*1.05,"SUBINDO",IF(C36<C35*0.95,"DESCENDO","ESTÁVEL")) | K36: 6 | L36: =IF(K36>0,ROUND(F36/K36,1),0) | M36: 0
A37: S7 | B37: 0.1 | C37: 3.7 | D37: =D36+B37 | E37: =E36+C37 | F37: =ROUND(B37/7,1) | G37: =ROUND(C37/7,1) | H37: 1 | I37: =IF(B37>B36*1.05,"SUBINDO",IF(B37<B36*0.95,"DESCENDO","ESTÁVEL")) | J37: =IF(C37>C36*1.05,"SUBINDO",IF(C37<C36*0.95,"DESCENDO","ESTÁVEL")) | K37: 6 | L37: =IF(K37>0,ROUND(F37/K37,1),0) | M37: 1.67
A38: S8 | B38: 1 | C38: 2.2 | D38: =D37+B38 | E38: =E37+C38 | F38: =ROUND(B38/7,1) | G38: =ROUND(C38/7,1) | H38: 5 | I38: =IF(B38>B37*1.05,"SUBINDO",IF(B38<B37*0.95,"DESCENDO","ESTÁVEL")) | J38: =IF(C38>C37*1.05,"SUBINDO",IF(C38<C37*0.95,"DESCENDO","ESTÁVEL")) | K38: 6 | L38: =IF(K38>0,ROUND(F38/K38,1),0) | M38: 0.27
A39: S9 | B39: 0.3 | C39: 0 | D39: =D38+B39 | E39: =E38+C39 | F39: =ROUND(B39/7,1) | G39: =ROUND(C39/7,1) | H39: 1 | I39: =IF(B39>B38*1.05,"SUBINDO",IF(B39<B38*0.95,"DESCENDO","ESTÁVEL")) | J39: =IF(C39>C38*1.05,"SUBINDO",IF(C39<C38*0.95,"DESCENDO","ESTÁVEL")) | K39: 6 | L39: =IF(K39>0,ROUND(F39/K39,1),0) | M39: 0
A40: S10 | B40: 6.5 | C40: 0.7 | D40: =D39+B40 | E40: =E39+C40 | F40: =ROUND(B40/7,1) | G40: =ROUND(C40/7,1) | H40: 5 | I40: =IF(B40>B39*1.05,"SUBINDO",IF(B40<B39*0.95,"DESCENDO","ESTÁVEL")) | J40: =IF(C40>C39*1.05,"SUBINDO",IF(C40<C39*0.95,"DESCENDO","ESTÁVEL")) | K40: 6 | L40: =IF(K40>0,ROUND(F40/K40,1),0) | M40: 0.17
A42: Morro Tetéu | EQ: 4 | Tendência rede: ESTÁVEL | Tendência lig: ESTÁVEL
A43: SEMANA | B43: REDE 7d | C43: LIG 7d | D43: REDE ACUM | E43: LIG ACUM | F43: REDE/DIA | G43: LIG/DIA | H43: PVs/SEM | I43: TEND REDE | J43: TEND LIG | K43: EQ | L43: m/eq/dia | M43: lig/eq/dia
A44: S1 | B44: 9.3 | C44: 0 | D44: =B44 | E44: =C44 | F44: =ROUND(B44/7,1) | G44: =ROUND(C44/7,1) | H44: 6 | I44: INÍCIO | J44: INÍCIO | K44: 4 | L44: =IF(K44>0,ROUND(F44/K44,1),0) | M44: 0
A45: S2 | B45: 17.9 | C45: 0.2 | D45: =D44+B45 | E45: =E44+C45 | F45: =ROUND(B45/7,1) | G45: =ROUND(C45/7,1) | H45: 5 | I45: =IF(B45>B44*1.05,"SUBINDO",IF(B45<B44*0.95,"DESCENDO","ESTÁVEL")) | J45: =IF(C45>C44*1.05,"SUBINDO",IF(C45<C44*0.95,"DESCENDO","ESTÁVEL")) | K45: 4 | L45: =IF(K45>0,ROUND(F45/K45,1),0) | M45: 0.3
A46: S3 | B46: 13.6 | C46: 1.2 | D46: =D45+B46 | E46: =E45+C46 | F46: =ROUND(B46/7,1) | G46: =ROUND(C46/7,1) | H46: 4 | I46: =IF(B46>B45*1.05,"SUBINDO",IF(B46<B45*0.95,"DESCENDO","ESTÁVEL")) | J46: =IF(C46>C45*1.05,"SUBINDO",IF(C46<C45*0.95,"DESCENDO","ESTÁVEL")) | K46: 4 | L46: =IF(K46>0,ROUND(F46/K46,1),0) | M46: 0.25
A47: S4 | B47: 16.3 | C47: 3.5 | D47: =D46+B47 | E47: =E46+C47 | F47: =ROUND(B47/7,1) | G47: =ROUND(C47/7,1) | H47: 5 | I47: =IF(B47>B46*1.05,"SUBINDO",IF(B47<B46*0.95,"DESCENDO","ESTÁVEL")) | J47: =IF(C47>C46*1.05,"SUBINDO",IF(C47<C46*0.95,"DESCENDO","ESTÁVEL")) | K47: 4 | L47: =IF(K47>0,ROUND(F47/K47,1),0) | M47: 1.65
A48: S5 | B48: 17.3 | C48: 4.9 | D48: =D47+B48 | E48: =E47+C48 | F48: =ROUND(B48/7,1) | G48: =ROUND(C48/7,1) | H48: 6 | I48: =IF(B48>B47*1.05,"SUBINDO",IF(B48<B47*0.95,"DESCENDO","ESTÁVEL")) | J48: =IF(C48>C47*1.05,"SUBINDO",IF(C48<C47*0.95,"DESCENDO","ESTÁVEL")) | K48: 4 | L48: =IF(K48>0,ROUND(F48/K48,1),0) | M48: 0.67
A49: S6 | B49: 23.5 | C49: 0.8 | D49: =D48+B49 | E49: =E48+C49 | F49: =ROUND(B49/7,1) | G49: =ROUND(C49/7,1) | H49: 4 | I49: =IF(B49>B48*1.05,"SUBINDO",IF(B49<B48*0.95,"DESCENDO","ESTÁVEL")) | J49: =IF(C49>C48*1.05,"SUBINDO",IF(C49<C48*0.95,"DESCENDO","ESTÁVEL")) | K49: 4 | L49: =IF(K49>0,ROUND(F49/K49,1),0) | M49: 0.31
A50: S7 | B50: 34.2 | C50: 1.8 | D50: =D49+B50 | E50: =E49+C50 | F50: =ROUND(B50/7,1) | G50: =ROUND(C50/7,1) | H50: 4 | I50: =IF(B50>B49*1.05,"SUBINDO",IF(B50<B49*0.95,"DESCENDO","ESTÁVEL")) | J50: =IF(C50>C49*1.05,"SUBINDO",IF(C50<C49*0.95,"DESCENDO","ESTÁVEL")) | K50: 4 | L50: =IF(K50>0,ROUND(F50/K50,1),0) | M50: 0.94
A51: S8 | B51: 4.5 | C51: 2.2 | D51: =D50+B51 | E51: =E50+C51 | F51: =ROUND(B51/7,1) | G51: =ROUND(C51/7,1) | H51: 9 | I51: =IF(B51>B50*1.05,"SUBINDO",IF(B51<B50*0.95,"DESCENDO","ESTÁVEL")) | J51: =IF(C51>C50*1.05,"SUBINDO",IF(C51<C50*0.95,"DESCENDO","ESTÁVEL")) | K51: 4 | L51: =IF(K51>0,ROUND(F51/K51,1),0) | M51: 0.17
A52: S9 | B52: 9.4 | C52: 2.6 | D52: =D51+B52 | E52: =E51+C52 | F52: =ROUND(B52/7,1) | G52: =ROUND(C52/7,1) | H52: 2 | I52: =IF(B52>B51*1.05,"SUBINDO",IF(B52<B51*0.95,"DESCENDO","ESTÁVEL")) | J52: =IF(C52>C51*1.05,"SUBINDO",IF(C52<C51*0.95,"DESCENDO","ESTÁVEL")) | K52: 4 | L52: =IF(K52>0,ROUND(F52/K52,1),0) | M52: 0.25
A53: S10 | B53: 9.3 | C53: 0.8 | D53: =D52+B53 | E53: =E52+C53 | F53: =ROUND(B53/7,1) | G53: =ROUND(C53/7,1) | H53: 9 | I53: =IF(B53>B52*1.05,"SUBINDO",IF(B53<B52*0.95,"DESCENDO","ESTÁVEL")) | J53: =IF(C53>C52*1.05,"SUBINDO",IF(C53<C52*0.95,"DESCENDO","ESTÁVEL")) | K53: 4 | L53: =IF(K53>0,ROUND(F53/K53,1),0) | M53: 0.11
A55: Vila Criadores | EQ: 7 | Tendência rede: SUBINDO | Tendência lig: DESCENDO
A56: SEMANA | B56: REDE 7d | C56: LIG 7d | D56: REDE ACUM | E56: LIG ACUM | F56: REDE/DIA | G56: LIG/DIA | H56: PVs/SEM | I56: TEND REDE | J56: TEND LIG | K56: EQ | L56: m/eq/dia | M56: lig/eq/dia
A57: S1 | B57: 1.9 | C57: 9.4 | D57: =B57 | E57: =C57 | F57: =ROUND(B57/7,1) | G57: =ROUND(C57/7,1) | H57: 2 | I57: INÍCIO | J57: INÍCIO | K57: 7 | L57: =IF(K57>0,ROUND(F57/K57,1),0) | M57: 1.36
A58: S4 | B58: 11 | C58: 2.2 | D58: =D57+B58 | E58: =E57+C58 | F58: =ROUND(B58/7,1) | G58: =ROUND(C58/7,1) | H58: 3 | I58: =IF(B58>B57*1.05,"SUBINDO",IF(B58<B57*0.95,"DESCENDO","ESTÁVEL")) | J58: =IF(C58>C57*1.05,"SUBINDO",IF(C58<C57*0.95,"DESCENDO","ESTÁVEL")) | K58: 7 | L58: =IF(K58>0,ROUND(F58/K58,1),0) | M58: 0.19
A59: S5 | B59: 21 | C59: 0.7 | D59: =D58+B59 | E59: =E58+C59 | F59: =ROUND(B59/7,1) | G59: =ROUND(C59/7,1) | H59: 3 | I59: =IF(B59>B58*1.05,"SUBINDO",IF(B59<B58*0.95,"DESCENDO","ESTÁVEL")) | J59: =IF(C59>C58*1.05,"SUBINDO",IF(C59<C58*0.95,"DESCENDO","ESTÁVEL")) | K59: 7 | L59: =IF(K59>0,ROUND(F59/K59,1),0) | M59: 0
A60: S6 | B60: 12.5 | C60: 0.9 | D60: =D59+B60 | E60: =E59+C60 | F60: =ROUND(B60/7,1) | G60: =ROUND(C60/7,1) | H60: 2 | I60: =IF(B60>B59*1.05,"SUBINDO",IF(B60<B59*0.95,"DESCENDO","ESTÁVEL")) | J60: =IF(C60>C59*1.05,"SUBINDO",IF(C60<C59*0.95,"DESCENDO","ESTÁVEL")) | K60: 7 | L60: =IF(K60>0,ROUND(F60/K60,1),0) | M60: 0.43
A61: S7 | B61: 0.6 | C61: 1.3 | D61: =D60+B61 | E61: =E60+C61 | F61: =ROUND(B61/7,1) | G61: =ROUND(C61/7,1) | H61: 1 | I61: =IF(B61>B60*1.05,"SUBINDO",IF(B61<B60*0.95,"DESCENDO","ESTÁVEL")) | J61: =IF(C61>C60*1.05,"SUBINDO",IF(C61<C60*0.95,"DESCENDO","ESTÁVEL")) | K61: 7 | L61: =IF(K61>0,ROUND(F61/K61,1),0) | M61: 0
A62: S8 | B62: 0.6 | C62: 0 | D62: =D61+B62 | E62: =E61+C62 | F62: =ROUND(B62/7,1) | G62: =ROUND(C62/7,1) | H62: 4 | I62: =IF(B62>B61*1.05,"SUBINDO",IF(B62<B61*0.95,"DESCENDO","ESTÁVEL")) | J62: =IF(C62>C61*1.05,"SUBINDO",IF(C62<C61*0.95,"DESCENDO","ESTÁVEL")) | K62: 7 | L62: =IF(K62>0,ROUND(F62/K62,1),0) | M62: 0
A63: S9 | B63: 6.8 | C63: 0.1 | D63: =D62+B63 | E63: =E62+C63 | F63: =ROUND(B63/7,1) | G63: =ROUND(C63/7,1) | H63: 4 | I63: =IF(B63>B62*1.05,"SUBINDO",IF(B63<B62*0.95,"DESCENDO","ESTÁVEL")) | J63: =IF(C63>C62*1.05,"SUBINDO",IF(C63<C62*0.95,"DESCENDO","ESTÁVEL")) | K63: 7 | L63: =IF(K63>0,ROUND(F63/K63,1),0) | M63: 0
A64: S10 | B64: 33.1 | C64: 0.2 | D64: =D63+B64 | E64: =E63+C64 | F64: =ROUND(B64/7,1) | G64: =ROUND(C64/7,1) | H64: 8 | I64: =IF(B64>B63*1.05,"SUBINDO",IF(B64<B63*0.95,"DESCENDO","ESTÁVEL")) | J64: =IF(C64>C63*1.05,"SUBINDO",IF(C64<C63*0.95,"DESCENDO","ESTÁVEL")) | K64: 7 | L64: =IF(K64>0,ROUND(F64/K64,1),0) | M64: 0
A66: Pantanal Baixo | EQ: 8 | Tendência rede: SUBINDO | Tendência lig: ESTÁVEL
A67: SEMANA | B67: REDE 7d | C67: LIG 7d | D67: REDE ACUM | E67: LIG ACUM | F67: REDE/DIA | G67: LIG/DIA | H67: PVs/SEM | I67: TEND REDE | J67: TEND LIG | K67: EQ | L67: m/eq/dia | M67: lig/eq/dia
A68: S1 | B68: 1.6 | C68: 0 | D68: =B68 | E68: =C68 | F68: =ROUND(B68/7,1) | G68: =ROUND(C68/7,1) | H68: 6 | I68: INÍCIO | J68: INÍCIO | K68: 8 | L68: =IF(K68>0,ROUND(F68/K68,1),0) | M68: 0
A69: S2 | B69: 2.6 | C69: 0 | D69: =D68+B69 | E69: =E68+C69 | F69: =ROUND(B69/7,1) | G69: =ROUND(C69/7,1) | H69: 4 | I69: =IF(B69>B68*1.05,"SUBINDO",IF(B69<B68*0.95,"DESCENDO","ESTÁVEL")) | J69: =IF(C69>C68*1.05,"SUBINDO",IF(C69<C68*0.95,"DESCENDO","ESTÁVEL")) | K69: 8 | L69: =IF(K69>0,ROUND(F69/K69,1),0) | M69: 0
A70: S3 | B70: 5 | C70: 0 | D70: =D69+B70 | E70: =E69+C70 | F70: =ROUND(B70/7,1) | G70: =ROUND(C70/7,1) | H70: 3 | I70: =IF(B70>B69*1.05,"SUBINDO",IF(B70<B69*0.95,"DESCENDO","ESTÁVEL")) | J70: =IF(C70>C69*1.05,"SUBINDO",IF(C70<C69*0.95,"DESCENDO","ESTÁVEL")) | K70: 8 | L70: =IF(K70>0,ROUND(F70/K70,1),0) | M70: 0
A71: S4 | B71: 12.6 | C71: 0.8 | D71: =D70+B71 | E71: =E70+C71 | F71: =ROUND(B71/7,1) | G71: =ROUND(C71/7,1) | H71: 5 | I71: =IF(B71>B70*1.05,"SUBINDO",IF(B71<B70*0.95,"DESCENDO","ESTÁVEL")) | J71: =IF(C71>C70*1.05,"SUBINDO",IF(C71<C70*0.95,"DESCENDO","ESTÁVEL")) | K71: 8 | L71: =IF(K71>0,ROUND(F71/K71,1),0) | M71: 0.35
A72: S5 | B72: 1.9 | C72: 0 | D72: =D71+B72 | E72: =E71+C72 | F72: =ROUND(B72/7,1) | G72: =ROUND(C72/7,1) | H72: 1 | I72: =IF(B72>B71*1.05,"SUBINDO",IF(B72<B71*0.95,"DESCENDO","ESTÁVEL")) | J72: =IF(C72>C71*1.05,"SUBINDO",IF(C72<C71*0.95,"DESCENDO","ESTÁVEL")) | K72: 8 | L72: =IF(K72>0,ROUND(F72/K72,1),0) | M72: 0
A73: S6 | B73: 6.8 | C73: 0.3 | D73: =D72+B73 | E73: =E72+C73 | F73: =ROUND(B73/7,1) | G73: =ROUND(C73/7,1) | H73: 4 | I73: =IF(B73>B72*1.05,"SUBINDO",IF(B73<B72*0.95,"DESCENDO","ESTÁVEL")) | J73: =IF(C73>C72*1.05,"SUBINDO",IF(C73<C72*0.95,"DESCENDO","ESTÁVEL")) | K73: 8 | L73: =IF(K73>0,ROUND(F73/K73,1),0) | M73: 0
A74: S7 | B74: 16.4 | C74: 3.9 | D74: =D73+B74 | E74: =E73+C74 | F74: =ROUND(B74/7,1) | G74: =ROUND(C74/7,1) | H74: 3 | I74: =IF(B74>B73*1.05,"SUBINDO",IF(B74<B73*0.95,"DESCENDO","ESTÁVEL")) | J74: =IF(C74>C73*1.05,"SUBINDO",IF(C74<C73*0.95,"DESCENDO","ESTÁVEL")) | K74: 8 | L74: =IF(K74>0,ROUND(F74/K74,1),0) | M74: 1.38
A75: S8 | B75: 16.9 | C75: 2.6 | D75: =D74+B75 | E75: =E74+C75 | F75: =ROUND(B75/7,1) | G75: =ROUND(C75/7,1) | H75: 5 | I75: =IF(B75>B74*1.05,"SUBINDO",IF(B75<B74*0.95,"DESCENDO","ESTÁVEL")) | J75: =IF(C75>C74*1.05,"SUBINDO",IF(C75<C74*0.95,"DESCENDO","ESTÁVEL")) | K75: 8 | L75: =IF(K75>0,ROUND(F75/K75,1),0) | M75: 0
A76: S9 | B76: 7.9 | C76: 0.1 | D76: =D75+B76 | E76: =E75+C76 | F76: =ROUND(B76/7,1) | G76: =ROUND(C76/7,1) | H76: 13 | I76: =IF(B76>B75*1.05,"SUBINDO",IF(B76<B75*0.95,"DESCENDO","ESTÁVEL")) | J76: =IF(C76>C75*1.05,"SUBINDO",IF(C76<C75*0.95,"DESCENDO","ESTÁVEL")) | K76: 8 | L76: =IF(K76>0,ROUND(F76/K76,1),0) | M76: 0.01
A77: S10 | B77: 5.8 | C77: 0.1 | D77: =D76+B77 | E77: =E76+C77 | F77: =ROUND(B77/7,1) | G77: =ROUND(C77/7,1) | H77: 14 | I77: =IF(B77>B76*1.05,"SUBINDO",IF(B77<B76*0.95,"DESCENDO","ESTÁVEL")) | J77: =IF(C77>C76*1.05,"SUBINDO",IF(C77<C76*0.95,"DESCENDO","ESTÁVEL")) | K77: 8 | L77: =IF(K77>0,ROUND(F77/K77,1),0) | M77: 0.07
A78: S11 | B78: 7.3 | C78: 0.3 | D78: =D77+B78 | E78: =E77+C78 | F78: =ROUND(B78/7,1) | G78: =ROUND(C78/7,1) | H78: 3 | I78: =IF(B78>B77*1.05,"SUBINDO",IF(B78<B77*0.95,"DESCENDO","ESTÁVEL")) | J78: =IF(C78>C77*1.05,"SUBINDO",IF(C78<C77*0.95,"DESCENDO","ESTÁVEL")) | K78: 8 | L78: =IF(K78>0,ROUND(F78/K78,1),0) | M78: 0

Sheet DASHBOARD
A1: DASHBOARD EXECUTIVO — SE LIGA NA REDE SANTOS
A2: Jan-Mar/2026 | 36 equipes | XGBoost R²=0.275 | Contrato CT 11481051 R$ 241M
A4: =CURVA_S!B5 | B4: =CURVA_S!B5*910 | C4: =1-CURVA_S!B7 | D4: 2.367m | G4: 66% | J4: 2.9x
A5: LIGAÇÕES/MÊS Meta: 1.044 | D5: REDE/MÊS Meta: 6.737m | G5: GAP abaixo da meta | J5: FATOR multiplicar
A7: PROGRESSO POR NÚCLEO
A8: =PROJ_vs_EXEC!A4 | B8: =PROJ_vs_EXEC!J4 | C8: =PROJ_vs_EXEC!K4 | D8: =PROJ_vs_EXEC!J4-PROJ_vs_EXEC!K4 | E8: =PROJ_vs_EXEC!L4 | F8: =IF(E8>=1,"PRONTO",IF(E8>=0.5,"EM EXECUÇÃO","ATRASADO")) | G8: STATUS AG | H8: STATUS ESG | I8: EQ | J8: m/eq/dia | K8: CUSTO SALDO
A9: =PROJ_vs_EXEC!A5 | B9: =PROJ_vs_EXEC!J5 | C9: =PROJ_vs_EXEC!K5 | D9: =PROJ_vs_EXEC!J5-PROJ_vs_EXEC!K5 | E9: =PROJ_vs_EXEC!L5 | F9: =IF(E9>=1,"PRONTO",IF(E9>=0.5,"EM EXECUÇÃO","ATRASADO")) | G9: PRONTO | H9: PRONTO | I9: 6 | J9: 0 | K9: 0
A10: =PROJ_vs_EXEC!A6 | B10: =PROJ_vs_EXEC!J6 | C10: =PROJ_vs_EXEC!K6 | D10: =PROJ_vs_EXEC!J6-PROJ_vs_EXEC!K6 | E10: =PROJ_vs_EXEC!L6 | F10: =IF(E10>=1,"PRONTO",IF(E10>=0.5,"EM EXECUÇÃO","ATRASADO")) | G10: FINALIZ. | H10: EXECUÇÃO | I10: 9 | J10: 13.7 | K10: R$ 3,8M
A11: =PROJ_vs_EXEC!A7 | B11: =PROJ_vs_EXEC!J7 | C11: =PROJ_vs_EXEC!K7 | D11: =PROJ_vs_EXEC!J7-PROJ_vs_EXEC!K7 | E11: =PROJ_vs_EXEC!L7 | F11: =IF(E11>=1,"PRONTO",IF(E11>=0.5,"EM EXECUÇÃO","ATRASADO")) | G11: EXECUÇÃO | H11: EXECUÇÃO | I11: 8 | J11: 10.3 | K11: R$ 5,7M
A12: =PROJ_vs_EXEC!A8 | B12: =PROJ_vs_EXEC!J8 | C12: =PROJ_vs_EXEC!K8 | D12: =PROJ_vs_EXEC!J8-PROJ_vs_EXEC!K8 | E12: =PROJ_vs_EXEC!L8 | F12: =IF(E12>=1,"PRONTO",IF(E12>=0.5,"EM EXECUÇÃO","ATRASADO")) | G12: EXECUÇÃO | H12: EXECUÇÃO | I12: 10 | J12: 5 | K12: R$ 7,3M
A13: =PROJ_vs_EXEC!A9 | B13: =PROJ_vs_EXEC!J9 | C13: =PROJ_vs_EXEC!K9 | D13: =PROJ_vs_EXEC!J9-PROJ_vs_EXEC!K9 | E13: =PROJ_vs_EXEC!L9 | F13: =IF(E13>=1,"PRONTO",IF(E13>=0.5,"EM EXECUÇÃO","ATRASADO")) | G13: EXECUÇÃO | H13: EXECUÇÃO | I13: 8 | J13: 2.1 | K13: R$ 6,8M
A15: INSIGHT XGBOOST
A16: O gargalo NÃO é equipe (5% de importância no modelo). É FLUXO DO PIPELINE.
A17: 65% da rede pronta NÃO virou ligação. Destravar: lab express + liberação em lote + 3 equipes intra = +685 lig/mês
A19: RAMP-UP: De 359 para 1.044 lig/mês
A20: Mar/26 | B20: Abr | C20: Mai | D20: Jun | E20: Jul | F20: Ago | G20: Set | H20: Out | I20: Nov | J20: Dez | K20: Jan/27
A21: 359 | B21: 500 | C21: 650 | D21: 800 | E21: 1000 | F21: 1044 | G21: 1044 | H21: 1044 | I21: 1044 | J21: 1044 | K21: 1044
A23: 4 GARGALOS CRÍTICOS DO PIPELINE
A24: GARGALO | B24: ATUAL | C24: META | D24: REDUÇÃO | E24: AÇÃO | F24: CUSTO/MÊS
A25: 4. Projeto | B25: 10 dias | C25: 5 dias | D25: −50% | E25: 2 projetistas + template | F25: R$ 25k
A26: 6. Execução Rede | B26: 15 dias | C26: 8 dias | D26: −47% | E26: +10 equipes MEC AG+ESG | F26: R$ 180k
A27: 7. Lavagem/Coliformes | B27: 7 dias | C27: 3 dias | D27: −57% | E27: Lab express Santos | F27: R$ 5k
A28: 8. Liberação SABESP | B28: 15 dias | C28: 7 dias | D28: −53% | E28: Lote 50 lig + reunião/sem | F28: R$ 10k
A30: RESULTADO: Ciclo 47d → 23d (−51%) | Lig: 359 → 1.044/mês | Invest: ~R$ 310k/mês | ROI: 45 dias

Sheet METODO_ML
A1: MÉTODO DE MACHINE LEARNING — XGBoost + GridSearchCV + Seaborn
A3: 1. O QUE É XGBOOST?
A4: XGBoost (eXtreme Gradient Boosting) é um algoritmo de Machine Learning baseado em árvores de decisão.
A5: Funciona assim: cria centenas de "árvores de decisão" simples, cada uma corrigindo os erros da anterior.
A6: É como ter 200 engenheiros juniores, cada um melhorando um pouco a estimativa do anterior, até chegar
A7: numa predição final muito mais precisa do que qualquer um sozinho conseguiria.
A9: POR QUE USAMOS: É o algoritmo #1 em competições de dados (Kaggle). Funciona muito bem com dados
A10: tabulares (planilhas), que é exatamente o que temos — produção diária por núcleo.
A11: Ele nos diz QUAIS FATORES mais influenciam a produtividade, o que é mais útil que a predição em si.
A13: 2. O QUE É GRIDSEARCHCV? (Busca Exaustiva)
A14: O XGBoost tem vários "botões" para ajustar (hiperparâmetros). O GridSearchCV testa TODAS as combinações:
A16: n_estimators (número de árvores): 50, 100, 200
... A29: 3. FEATURE IMPORTANCE — O que o modelo aprendeu
A30: FEATURE | B30: IMPORTÂNCIA | C30: % | D30: INTERPRETAÇÃO
A31: lig_total_r3 | B31: 0.311 | C31: 31% | D31: Média de ligações dos últimos 3 dias. MOMENTUM é o fator #1.
A32: rede_acum | B32: 0.102 | C32: 10% | D32: Metros acumulados no núcleo. Mais rede pronta = mais potencial de ligação.
A33: rede_total_r7 | B33: 0.098 | C33: 10% | D33: Média de rede dos últimos 7 dias. Ritmo recente de instalação.
A34: rede_total_r3 | B34: 0.097 | C34: 10% | D34: Média de rede dos últimos 3 dias. Ritmo imediato.
A35: lig_total_r7 | B35: 0.093 | C35: 9% | D35: Média de ligações dos últimos 7 dias. Estabilidade do ritmo.
A36: PVs | B36: 0.075 | C36: 8% | D36: PVs executados no dia. Indicador de rede pronta para ligar.
A37: PRE | B37: 0.074 | C37: 7% | D37: PRE (pré-assentamento) no dia. Preparação do terreno.
A38: equipes | B38: 0.046 | C38: 5% | D38: Número de equipes. APENAS 5% — NÃO é o fator principal!
A39: dia_semana | B39: 0.044 | C39: 4% | D39: Dia da semana (Seg-Dom). Produção cai sexta/sábado.
A40: mes | B40: 0.035 | C40: 4% | D40: Mês do ano. Janeiro fraco (início), fevereiro melhora.
A41: nucleo_enc | B41: 0.026 | C41: 3% | D41: Qual núcleo. Pouca diferença entre núcleos (bom!).
A43: 4. O QUE SIGNIFICA R² = 0.275?
A44: R² (coeficiente de determinação) mede quanto da variação nos dados o modelo consegue explicar.
A45: R²=0.275 significa que o modelo explica 27.5% da variação nas ligações diárias.
A47: PARECE BAIXO? Sim, mas tem motivo:
A48: • Dados de obra são extremamente ruidosos (chuva, falta de material, equipe faltou, trecho difícil)
A49: • Apenas 142 dias com ligações registradas (amostra pequena)
A50: • Muitos fatores externos que não estão nos dados (clima, acesso ao morro, SABESP atrasou)
A52: MAS: O FEATURE IMPORTANCE É CONFIÁVEL mesmo com R² baixo.
A53: O ranking de importância nos diz com confiança que:
A54: → Momentum (ritmo contínuo) é 6x mais importante que número de equipes
A55: → Rede acumulada pronta é 2x mais importante que equipes
A56: → O gargalo está no FLUXO do pipeline, não na capacidade de campo
... A69: HEATMAP_LIG e TENDENCIAS desta planilha.
